Workbook

Sheet Resumo
A1: Jalecon v2 · Resumo comparativo
A2: Cenário: | B2: =Premissas!$D$3
A3: Troque o cenário na aba Premissas, célula C3. Valores em reais nominais.
A5: Modelo A: software por assinatura
A6: Indicador | B6: Ano 1 | C6: Ano 2 | D6: Ano 3 | E6: Ano 4 | F6: Ano 5 | G6: Ano 6 | H6: Ano 7
A7: Clientes ativos (fim do ano) | B7: ='Modelo A'!N39 | C7: ='Modelo A'!Z39 | D7: ='Modelo A'!AL39 | E7: ='Modelo A'!AX39 | F7: ='Modelo A'!BJ39 | G7: ='Modelo A'!BV39 | H7: ='Modelo A'!CH39
A8: Receita bruta | B8: =SUMIF('Modelo A'!$C$3:$CH$3,1,'Modelo A'!$C$45:$CH$45) | C8: =SUMIF('Modelo A'!$C$3:$CH$3,2,'Modelo A'!$C$45:$CH$45) | D8: =SUMIF('Modelo A'!$C$3:$CH$3,3,'Modelo A'!$C$45:$CH$45) | E8: =SUMIF('Modelo A'!$C$3:$CH$3,4,'Modelo A'!$C$45:$CH$45) | F8: =SUMIF('Modelo A'!$C$3:$CH$3,5,'Modelo A'!$C$45:$CH$45) | G8: =SUMIF('Modelo A'!$C$3:$CH$3,6,'Modelo A'!$C$45:$CH$45) | H8: =SUMIF('Modelo A'!$C$3:$CH$3,7,'Modelo A'!$C$45:$CH$45)
A9: Receita recorrente anualizada (fim do ano) | B9: ='Modelo A'!N47 | C9: ='Modelo A'!Z47 | D9: ='Modelo A'!AL47 | E9: ='Modelo A'!AX47 | F9: ='Modelo A'!BJ47 | G9: ='Modelo A'!BV47 | H9: ='Modelo A'!CH47
A10: Lucro bruto | B10: =SUMIF('Modelo A'!$C$3:$CH$3,1,'Modelo A'!$C$57:$CH$57) | C10: =SUMIF('Modelo A'!$C$3:$CH$3,2,'Modelo A'!$C$57:$CH$57) | D10: =SUMIF('Modelo A'!$C$3:$CH$3,3,'Modelo A'!$C$57:$CH$57) | E10: =SUMIF('Modelo A'!$C$3:$CH$3,4,'Modelo A'!$C$57:$CH$57) | F10: =SUMIF('Modelo A'!$C$3:$CH$3,5,'Modelo A'!$C$57:$CH$57) | G10: =SUMIF('Modelo A'!$C$3:$CH$3,6,'Modelo A'!$C$57:$CH$57) | H10: =SUMIF('Modelo A'!$C$3:$CH$3,7,'Modelo A'!$C$57:$CH$57)
A11: Margem bruta (sobre a receita líquida) | B11: =IFERROR(SUMIF('Modelo A'!$C$3:$CH$3,1,'Modelo A'!$C$57:$CH$57)/SUMIF('Modelo A'!$C$3:$CH$3,1,'Modelo A'!$C$50:$CH$50),0) | C11: =IFERROR(SUMIF('Modelo A'!$C$3:$CH$3,2,'Modelo A'!$C$57:$CH$57)/SUMIF('Modelo A'!$C$3:$CH$3,2,'Modelo A'!$C$50:$CH$50),0) | D11: =IFERROR(SUMIF('Modelo A'!$C$3:$CH$3,3,'Modelo A'!$C$57:$CH$57)/SUMIF('Modelo A'!$C$3:$CH$3,3,'Modelo A'!$C$50:$CH$50),0) | E11: =IFERROR(SUMIF('Modelo A'!$C$3:$CH$3,4,'Modelo A'!$C$57:$CH$57)/SUMIF('Modelo A'!$C$3:$CH$3,4,'Modelo A'!$C$50:$CH$50),0) | F11: =IFERROR(SUMIF('Modelo A'!$C$3:$CH$3,5,'Modelo A'!$C$57:$CH$57)/SUMIF('Modelo A'!$C$3:$CH$3,5,'Modelo A'!$C$50:$CH$50),0) | G11: =IFERROR(SUMIF('Modelo A'!$C$3:$CH$3,6,'Modelo A'!$C$57:$CH$57)/SUMIF('Modelo A'!$C$3:$CH$3,6,'Modelo A'!$C$50:$CH$50),0) | H11: =IFERROR(SUMIF('Modelo A'!$C$3:$CH$3,7,'Modelo A'!$C$57:$CH$57)/SUMIF('Modelo A'!$C$3:$CH$3,7,'Modelo A'!$C$50:$CH$50),0)
A12: EBITDA | B12: =SUMIF('Modelo A'!$C$3:$CH$3,1,'Modelo A'!$C$73:$CH$73) | C12: =SUMIF('Modelo A'!$C$3:$CH$3,2,'Modelo A'!$C$73:$CH$73) | D12: =SUMIF('Modelo A'!$C$3:$CH$3,3,'Modelo A'!$C$73:$CH$73) | E12: =SUMIF('Modelo A'!$C$3:$CH$3,4,'Modelo A'!$C$73:$CH$73) | F12: =SUMIF('Modelo A'!$C$3:$CH$3,5,'Modelo A'!$C$73:$CH$73) | G12: =SUMIF('Modelo A'!$C$3:$CH$3,6,'Modelo A'!$C$73:$CH$73) | H12: =SUMIF('Modelo A'!$C$3:$CH$3,7,'Modelo A'!$C$73:$CH$73)
A13: Caixa acumulado sem captação (fim do ano) | B13: ='Modelo A'!N74 | C13: ='Modelo A'!Z74 | D13: ='Modelo A'!AL74 | E13: ='Modelo A'!AX74 | F13: ='Modelo A'!BJ74 | G13: ='Modelo A'!BV74 | H13: ='Modelo A'!CH74
A14: Pessoas (fim do ano) | B14: ='Modelo A'!N77 | C14: ='Modelo A'!Z77 | D14: ='Modelo A'!AL77 | E14: ='Modelo A'!AX77 | F14: ='Modelo A'!BJ77 | G14: ='Modelo A'!BV77 | H14: ='Modelo A'!CH77
A15: Participação no mercado endereçável (fim do ano) | B15: ='Modelo A'!N41 | C15: ='Modelo A'!Z41 | D15: ='Modelo A'!AL41 | E15: ='Modelo A'!AX41 | F15: ='Modelo A'!BJ41 | G15: ='Modelo A'!BV41 | H15: ='Modelo A'!CH41
A17: Modelo B: agência operada por agentes
A18: Indicador | B18: Ano 1 | C18: Ano 2 | D18: Ano 3 | E18: Ano 4 | F18: Ano 5 | G18: Ano 6 | H18: Ano 7
A19: Clientes ativos (fim do ano) | B19: ='Modelo B'!N33 | C19: ='Modelo B'!Z33 | D19: ='Modelo B'!AL33 | E19: ='Modelo B'!AX33 | F19: ='Modelo B'!BJ33 | G19: ='Modelo B'!BV33 | H19: ='Modelo B'!CH33
A20: Receita bruta | B20: =SUMIF('Modelo B'!$C$3:$CH$3,1,'Modelo B'!$C$39:$CH$39) | C20: =SUMIF('Modelo B'!$C$3:$CH$3,2,'Modelo B'!$C$39:$CH$39) | D20: =SUMIF('Modelo B'!$C$3:$CH$3,3,'Modelo B'!$C$39:$CH$39) | E20: =SUMIF('Modelo B'!$C$3:$CH$3,4,'Modelo B'!$C$39:$CH$39) | F20: =SUMIF('Modelo B'!$C$3:$CH$3,5,'Modelo B'!$C$39:$CH$39) | G20: =SUMIF('Modelo B'!$C$3:$CH$3,6,'Modelo B'!$C$39:$CH$39) | H20: =SUMIF('Modelo B'!$C$3:$CH$3,7,'Modelo B'!$C$39:$CH$39)
A21: Receita recorrente anualizada (fim do ano) | B21: ='Modelo B'!N41 | C21: ='Modelo B'!Z41 | D21: ='Modelo B'!AL41 | E21: ='Modelo B'!AX41 | F21: ='Modelo B'!BJ41 | G21: ='Modelo B'!BV41 | H21: ='Modelo B'!CH41
A22: Lucro bruto | B22: =SUMIF('Modelo B'!$C$3:$CH$3,1,'Modelo B'!$C$51:$CH$51) | C22: =SUMIF('Modelo B'!$C$3:$CH$3,2,'Modelo B'!$C$51:$CH$51) | D22: =SUMIF('Modelo B'!$C$3:$CH$3,3,'Modelo B'!$C$51:$CH$51) | E22: =SUMIF('Modelo B'!$C$3:$CH$3,4,'Modelo B'!$C$51:$CH$51) | F22: =SUMIF('Modelo B'!$C$3:$CH$3,5,'Modelo B'!$C$51:$CH$51) | G22: =SUMIF('Modelo B'!$C$3:$CH$3,6,'Modelo B'!$C$51:$CH$51) | H22: =SUMIF('Modelo B'!$C$3:$CH$3,7,'Modelo B'!$C$51:$CH$51)
A23: Margem bruta (sobre a receita líquida) | B23: =IFERROR(SUMIF('Modelo B'!$C$3:$CH$3,1,'Modelo B'!$C$51:$CH$51)/SUMIF('Modelo B'!$C$3:$CH$3,1,'Modelo B'!$C$44:$CH$44),0) | C23: =IFERROR(SUMIF('Modelo B'!$C$3:$CH$3,2,'Modelo B'!$C$51:$CH$51)/SUMIF('Modelo B'!$C$3:$CH$3,2,'Modelo B'!$C$44:$CH$44),0) | D23: =IFERROR(SUMIF('Modelo B'!$C$3:$CH$3,3,'Modelo B'!$C$51:$CH$51)/SUMIF('Modelo B'!$C$3:$CH$3,3,'Modelo B'!$C$44:$CH$44),0) | E23: =IFERROR(SUMIF('Modelo B'!$C$3:$CH$3,4,'Modelo B'!$C$51:$CH$51)/SUMIF('Modelo B'!$C$3:$CH$3,4,'Modelo B'!$C$44:$CH$44),0) | F23: =IFERROR(SUMIF('Modelo B'!$C$3:$CH$3,5,'Modelo B'!$C$51:$CH$51)/SUMIF('Modelo B'!$C$3:$CH$3,5,'Modelo B'!$C$44:$CH$44),0) | G23: =IFERROR(SUMIF('Modelo B'!$C$3:$CH$3,6,'Modelo B'!$C$51:$CH$51)/SUMIF('Modelo B'!$C$3:$CH$3,6,'Modelo B'!$C$44:$CH$44),0) | H23: =IFERROR(SUMIF('Modelo B'!$C$3:$CH$3,7,'Modelo B'!$C$51:$CH$51)/SUMIF('Modelo B'!$C$3:$CH$3,7,'Modelo B'!$C$44:$CH$44),0)
A24: EBITDA | B24: =SUMIF('Modelo B'!$C$3:$CH$3,1,'Modelo B'!$C$67:$CH$67) | C24: =SUMIF('Modelo B'!$C$3:$CH$3,2,'Modelo B'!$C$67:$CH$67) | D24: =SUMIF('Modelo B'!$C$3:$CH$3,3,'Modelo B'!$C$67:$CH$67) | E24: =SUMIF('Modelo B'!$C$3:$CH$3,4,'Modelo B'!$C$67:$CH$67) | F24: =SUMIF('Modelo B'!$C$3:$CH$3,5,'Modelo B'!$C$67:$CH$67) | G24: =SUMIF('Modelo B'!$C$3:$CH$3,6,'Modelo B'!$C$67:$CH$67) | H24: =SUMIF('Modelo B'!$C$3:$CH$3,7,'Modelo B'!$C$67:$CH$67)
A25: Caixa acumulado sem captação (fim do ano) | B25: ='Modelo B'!N68 | C25: ='Modelo B'!Z68 | D25: ='Modelo B'!AL68 | E25: ='Modelo B'!AX68 | F25: ='Modelo B'!BJ68 | G25: ='Modelo B'!BV68 | H25: ='Modelo B'!CH68
A26: Pessoas (fim do ano) | B26: ='Modelo B'!N71 | C26: ='Modelo B'!Z71 | D26: ='Modelo B'!AL71 | E26: ='Modelo B'!AX71 | F26: ='Modelo B'!BJ71 | G26: ='Modelo B'!BV71 | H26: ='Modelo B'!CH71
A27: Participação no mercado endereçável (fim do ano) | B27: ='Modelo B'!N35 | C27: ='Modelo B'!Z35 | D27: ='Modelo B'!AL35 | E27: ='Modelo B'!AX35 | F27: ='Modelo B'!BJ35 | G27: ='Modelo B'!BV35 | H27: ='Modelo B'!CH35
A29: Indicadores-chave e critérios de corte
A30: Indicador | B30: Modelo A | C30: Modelo B | D30: Critério | E30: A passa? | F30: B passa?
A31: Receita recorrente anualizada no ano 5 | B31: =INDEX('Modelo A'!$C$47:$CH$47,1,60) | C31: =INDEX('Modelo B'!$C$41:$CH$41,1,60)
A32: Receita recorrente anualizada no ano 7 | B32: =INDEX('Modelo A'!$C$47:$CH$47,1,84) | C32: =INDEX('Modelo B'!$C$41:$CH$41,1,84)
A33: Mês de equilíbrio (EBITDA positivo daí em diante) | B33: =IFERROR(1/(1/MIN('Modelo A'!$C$75:$CH$75)),"não chega") | C33: =IFERROR(1/(1/MIN('Modelo B'!$C$69:$CH$69)),"não chega")
A34: Capital necessário (pior caixa acumulado) | B34: =-MIN(0,MIN('Modelo A'!$C$74:$CH$74)) | C34: =-MIN(0,MIN('Modelo B'!$C$68:$CH$68))
A35: Margem bruta no ano 5 | B35: =SUMIF('Modelo A'!$C$3:$CH$3,5,'Modelo A'!$C$57:$CH$57)/SUMIF('Modelo A'!$C$3:$CH$3,5,'Modelo A'!$C$50:$CH$50) | C35: =SUMIF('Modelo B'!$C$3:$CH$3,5,'Modelo B'!$C$51:$CH$51)/SUMIF('Modelo B'!$C$3:$CH$3,5,'Modelo B'!$C$44:$CH$44) | D35: =Premissas!$F$97 | E35: =IF(B35>=Premissas!$F$97,"Sim","Não") | F35: =IF(C35>=Premissas!$F$97,"Sim","Não")
A36: LTV/CAC do plano principal (Consultório / Agenda Cheia), mídia paga | B36: =Unidade!H7 | C36: =Unidade!H14 | D36: =Premissas!$F$98 | E36: =IF(B36>=Premissas!$F$98,"Sim","Não") | F36: =IF(C36>=Premissas!$F$98,"Sim","Não")
A37: Recuperação do CAC do plano principal (meses) | B37: =Unidade!I7 | C37: =Unidade!I14 | D37: =Premissas!$F$99 | E37: =IF(B37<=Premissas!$F$99,"Sim","Não") | F37: =IF(C37<=Premissas!$F$99,"Sim","Não")
A38: Mês em que a receita anualizada chega a R$ 50 mi | B38: =IFERROR(1/(1/MIN('Modelo A'!$C$76:$CH$76)),"não chega") | C38: =IFERROR(1/(1/MIN('Modelo B'!$C$70:$CH$70)),"não chega")
A39: Participação no mercado nesse mês | B39: =IF(ISNUMBER(B38),INDEX('Modelo A'!$C$41:$CH$41,1,B38),"") | C39: =IF(ISNUMBER(C38),INDEX('Modelo B'!$C$35:$CH$35,1,C38),"") | D39: =Premissas!$F$101 | E39: =IF(ISNUMBER(B39),IF(B39<=Premissas!$F$101,"Sim","Não"),"Não chega a R$ 50 mi") | F39: =IF(ISNUMBER(C39),IF(C39<=Premissas!$F$101,"Sim","Não"),"Não chega a R$ 50 mi")
A40: Receita por pessoa no ano 5 | B40: =SUMIF('Modelo A'!$C$3:$CH$3,5,'Modelo A'!$C$45:$CH$45)/INDEX('Modelo A'!$C$77:$CH$77,1,60) | C40: =SUMIF('Modelo B'!$C$3:$CH$3,5,'Modelo B'!$C$39:$CH$39)/INDEX('Modelo B'!$C$71:$CH$71,1,60)
A41: Clientes ativos no ano 5 | B41: =INDEX('Modelo A'!$C$39:$CH$39,1,60) | C41: =INDEX('Modelo B'!$C$33:$CH$33,1,60)
A42: LTV/CAC ponderado pelo mix de novos clientes (mídia paga) | B42: =(Premissas!$F$47*Unidade!F6+Premissas!$F$52*Unidade!F7+Premissas!$F$57*Unidade!F8+Premissas!$F$63*Unidade!F9)/Premissas!$F$42 | C42: =(Premissas!$F$76*Unidade!F13+Premissas!$F$82*Unidade!F14+Premissas!$F$89*Unidade!F15)/Premissas!$F$70 | D42: =Premissas!$F$98 | E42: =IF(B42>=Premissas!$F$98,"Sim","Não") | F42: =IF(C42>=Premissas!$F$98,"Sim","Não")
A44: Como ler: H6 exige as três linhas com 'Sim' (margem, LTV/CAC e recuperação do CAC). H7 exige chegar a R$ 50 mi de receita anualizada em até 7 anos com no máximo 3% do mercado endereçável.
A45: As abas Cenarios e Sensibilidade são geradas pelo script sensibilidade_v2.py: são valores, não fórmulas. Ao mudar premissas, rode o script de novo.

Sheet Leia-me
A1: Jalecon v2 · Como usar este modelo
A2: Compara dois desenhos de negócio com as mesmas condições de mercado:
A3: Modelo A, software por assinatura: o médico usa a plataforma e faz o trabalho com ajuda da IA (planos de R$ 297 a R$ 3.900, como no v0).
A4: Modelo B, agência operada por agentes: uma equipe de agentes de IA executa marca, site, Google, conteúdo, anúncios e atendimento no WhatsApp; um especialista humano supervisiona dezenas de contas; parte do preço é cobrada por consulta agendada.
A6: Abas: Resumo (comparação e critérios de corte), Leia-me, Unidade (economia por cliente), Premissas (tudo o que pode ser mudado), Modelo A e Modelo B (mês a mês, 84 meses), Cenarios e Sensibilidade (geradas por script).
A7: Premissas em azul. Troque o cenário em Premissas!C3. Cada premissa tem a fonte na coluna G; as referências vêm do relatório 03 (mercado e concorrência).
A8: O caixa é calculado sem captação: o pior caixa acumulado é o capital necessário até o equilíbrio (sem reserva). A captação recomendada soma 6 meses de reserva a esse valor.
A9: Versão 2.1 (20/10/2026): incorpora a contraprova. Impostos de lucro presumido desde o início; churn, CAC e capacidade dos especialistas do Modelo B pela regra pré-registrada; cobrança por consulta desligada (art. 59 do Código de Ética Médica); custos de implantação e de indicação; mídia proporcional à expansão; Agenda Cheia a partir do mês 9.
A10: Limitações: churn e CAC ainda são referências de mercado, não medição própria; não há sazonalidade; as consultas atribuídas no Modelo B são suposição a validar em piloto.

Sheet Premissas
A1: Jalecon v2 · Premissas
A2: Texto azul = premissa editável. A coluna F (Usado) segue o cenário escolhido em C3. A coluna G diz de onde veio cada número.
A3: Cenário (1 = Conservador, 2 = Base, 3 = Otimista) | C3: 2 | D3: =CHOOSE(C3,"Conservador","Base","Otimista")
A6: 1. Gerais
A7: Premissa | B7: Unidade | C7: Conservador | D7: Base | E7: Otimista | F7: Usado | G7: Fonte ou justificativa
A8: Mês de lançamento comercial (antes: produto e piloto) | B8: mês | C8: 5 | D8: 4 | E8: 4 | F8: =CHOOSE($C$3,C8,D8,E8) | G8: Plano v0: 3 meses de piloto antes da venda
A9: Impostos sobre a receita até R$ 4,8 mi nos últimos 12 meses | B9: % | C9: 0.163 | D9: 0.163 | E9: 0.163 | F9: =CHOOSE($C$3,C9,D9,E9) | G9: v2.1: lucro presumido desde o início. O Simples não admite sócio pessoa jurídica, o que impede investidor institucional (contraprova)
A10: Impostos sobre a receita acima de R$ 4,8 mi nos últimos 12 meses | B10: % | C10: 0.163 | D10: 0.163 | E10: 0.163 | F10: =CHOOSE($C$3,C10,D10,E10) | G10: Lucro presumido para serviços: PIS, COFINS, ISS, IRPJ e CSLL (aprox.)
A11: Meios de pagamento | B11: % da receita | C11: 0.03 | D11: 0.03 | E11: 0.03 | F11: =CHOOSE($C$3,C11,D11,E11) | G11: Cartão e boleto recorrentes
A12: Mercado endereçável: médicos que dependem de atrair pacientes particulares | B12: médicos | C12: 115000 | D12: 150000 | E12: 230000 | F12: =CHOOSE($C$3,C12,D12,E12) | G12: Relatório 03, seção 1: 635,7 mil médicos × 48% em consultório × 50% dependem de pacientes particulares
A13: Expansão para dentistas: mês de início | B13: mês | C13: 37 | D13: 25 | E13: 25 | F13: =CHOOSE($C$3,C13,D13,E13) | G13: Decisão; exige base de regras do CFO 196/2019 e produto adaptado
A14: Expansão: aquisição adicional sobre a de médicos | B14: % | C14: 0.4 | D14: 0.7 | E14: 1 | F14: =CHOOSE($C$3,C14,D14,E14) | G14: Dentistas: mais de 450 mil e quase só atendimento particular (CFO, fonte secundária). Concorrência já presente (Sorriai)
A15: Mercado endereçável: dentistas | B15: dentistas | C15: 120000 | D15: 180000 | E15: 225000 | F15: =CHOOSE($C$3,C15,D15,E15) | G15: 450 mil × 40% a 50% com consultório próprio e dependentes de pacientes particulares (suposição)
A16: Custo único da expansão (regras, produto, jurídico) | B16: R$ | C16: 400000 | D16: 300000 | E16: 200000 | F16: =CHOOSE($C$3,C16,D16,E16) | G16: Estimativa
A17: Indicação: novos clientes por mês, como % da base ativa | B17: % | C17: 0.005 | D17: 0.01 | E17: 0.015 | F17: =CHOOSE($C$3,C17,D17,E17) | G17: Programa de indicação; v0 usava 1%
A18: Parcerias: multiplicador sobre o plano de parcerias | B18: x | C18: 0.6 | D18: 1 | E18: 1.3 | F18: =CHOOSE($C$3,C18,D18,E18) | G18: Residências, sociedades, contadores, coworkings, clube de benefícios da iClinic
A20: 2. Decisões por ano (iguais nos dois modelos e nos três cenários)
C21: Ano 1 | D21: Ano 2 | E21: Ano 3 | F21: Ano 4 | G21: Ano 5 | H21: Ano 6 | I21: Ano 7 | J21: Fonte
A22: Orçamento de mídia paga por mês | B22: R$ | C22: 20000 | D22: 50000 | E22: 100000 | F22: 160000 | G22: 220000 | H22: 280000 | I22: 340000 | J22: Decisão de investimento
A23: Novos clientes por parcerias por mês (antes do multiplicador) | B23: clientes | C23: 4 | D23: 10 | E23: 18 | F23: 26 | G23: 34 | H23: 42 | I23: 50 | J23: Plano v0, ampliado
A24: Produto, engenharia e IA (pessoas) | B24: pessoas | C24: 4 | D24: 7 | E24: 10 | F24: 13 | G24: 16 | H24: 18 | I24: 20 | J24: Plano de contratação
A25: Administrativo, jurídico e conformidade (pessoas) | B25: pessoas | C25: 1 | D25: 2 | E25: 4 | F25: 6 | G25: 8 | H25: 9 | I25: 10 | J25: Plano de contratação
A26: Pró-labore por fundador por mês | B26: R$ | C26: 5000 | D26: 10000 | E26: 15000 | F26: 15000 | G26: 18000 | H26: 18000 | I26: 20000 | J26: Plano v0 (6 fundadores)
A27: Modelo A: vendas e marketing (pessoas) | B27: pessoas | C27: 2 | D27: 4 | E27: 7 | F27: 10 | G27: 13 | H27: 15 | I27: 17 | J27: Venda por autosserviço e inside sales
A28: Modelo B: vendas e marketing (pessoas) | B28: pessoas | C28: 3 | D28: 6 | E28: 10 | F28: 15 | G28: 20 | H28: 24 | I28: 28 | J28: Venda consultiva: ticket maior pede mais gente
A30: 3. Custos de pessoas e despesas gerais
A31: Premissa | B31: Unidade | C31: Conservador | D31: Base | E31: Otimista | F31: Usado | G31: Fonte ou justificativa
A32: Custo mensal por pessoa de produto e engenharia (com encargos) | B32: R$ | C32: 20000 | D32: 18000 | E32: 16000 | F32: =CHOOSE($C$3,C32,D32,E32) | G32: Mercado de São Paulo, pleno e sênior
A33: Custo mensal por pessoa de vendas e marketing | B33: R$ | C33: 11000 | D33: 10000 | E33: 9000 | F33: =CHOOSE($C$3,C33,D33,E33) | G33: Mercado de São Paulo, com comissão média
A34: Custo mensal por pessoa administrativa e jurídica | B34: R$ | C34: 13000 | D34: 12000 | E34: 11000 | F34: =CHOOSE($C$3,C34,D34,E34) | G34: Mercado de São Paulo
A35: Número de fundadores | B35: pessoas | C35: 6 | D35: 6 | E35: 6 | F35: =CHOOSE($C$3,C35,D35,E35) | G35: Grupo 1
A36: Outras despesas fixas por mês (ferramentas, jurídico, contabilidade) | B36: R$ | C36: 20000 | D36: 15000 | E36: 12000 | F36: =CHOOSE($C$3,C36,D36,E36) | G36: Estimativa
A37: Outras despesas variáveis | B37: % da receita | C37: 0.04 | D37: 0.03 | E37: 0.025 | F37: =CHOOSE($C$3,C37,D37,E37) | G37: Estimativa
A38: Marca, eventos e conteúdo próprio | B38: % da mídia | C38: 0.08 | D38: 0.05 | E38: 0.05 | F38: =CHOOSE($C$3,C38,D38,E38) | G38: Congressos e conteúdo sobre regras do CFM
A40: 4. Modelo A: software por assinatura
A41: Premissa | B41: Unidade | C41: Conservador | D41: Base | E41: Otimista | F41: Usado | G41: Fonte ou justificativa
A42: CAC na mídia paga | B42: R$ | C42: 6000 | D42: 4500 | E42: 3000 | F42: =CHOOSE($C$3,C42,D42,E42) | G42: Relatório 03, seção 4: recuperação do CAC em 8 a 11 meses equivale a R$ 4.500 a R$ 6.100; v0 usava R$ 1.800
A43: Custo por cliente vindo de parceria (comissão) | B43: R$ | C43: 1800 | D43: 1500 | E43: 1200 | F43: =CHOOSE($C$3,C43,D43,E43) | G43: Comissão de cerca de 2 mensalidades
A44: Custo mensal do gestor de conta (com encargos) | B44: R$ | C44: 9500 | D44: 9000 | E44: 8500 | F44: =CHOOSE($C$3,C44,D44,E44) | G44: Mercado
A45: Essencial: preço mensal | B45: R$ | C45: 297 | D45: 297 | E45: 297 | F45: =CHOOSE($C$3,C45,D45,E45) | G45: Plano v0
A46: Essencial: taxa de implantação | B46: R$ | C46: 0 | D46: 0 | E46: 0 | F46: =CHOOSE($C$3,C46,D46,E46) | G46: Plano v0
A47: Essencial: participação nos novos clientes | B47: % | C47: 0.4 | D47: 0.4 | E47: 0.35 | F47: =CHOOSE($C$3,C47,D47,E47) | G47: Plano v0, ajustado
A48: Essencial: churn mensal | B48: % | C48: 0.09 | D48: 0.07 | E48: 0.055 | F48: =CHOOSE($C$3,C48,D48,E48) | G48: Relatório 03, seção 4: referências de 4% a 7% (até 9% abaixo de US$ 100) para software de pequena empresa
A49: Essencial: custo direto por conta por mês (IA, infraestrutura) | B49: R$ | C49: 32 | D49: 25 | E49: 20 | F49: =CHOOSE($C$3,C49,D49,E49) | G49: IA (Claude), imagens, hospedagem e publicação; v0 estimava de US$ 4 a US$ 45 por conta
A50: Consultório: preço mensal | B50: R$ | C50: 697 | D50: 697 | E50: 697 | F50: =CHOOSE($C$3,C50,D50,E50) | G50: Plano v0
A51: Consultório: taxa de implantação | B51: R$ | C51: 490 | D51: 490 | E51: 490 | F51: =CHOOSE($C$3,C51,D51,E51) | G51: Plano v0
A52: Consultório: participação nos novos clientes | B52: % | C52: 0.45 | D52: 0.45 | E52: 0.45 | F52: =CHOOSE($C$3,C52,D52,E52) | G52: Plano v0, ajustado
A53: Consultório: churn mensal | B53: % | C53: 0.07 | D53: 0.055 | E53: 0.04 | F53: =CHOOSE($C$3,C53,D53,E53) | G53: Relatório 03, seção 4: referências de 4% a 7% (até 9% abaixo de US$ 100) para software de pequena empresa
... A66: Clínica: contas por gestor humano | B66: contas | C66: 15 | D66: 20 | E66: 25 | F66: =CHOOSE($C$3,C66,D66,E66) | G66: Gestor de conta humano nos planos Autoridade e Clínica (v0: 1 para 40 e 1 para 20)
A68: 5. Modelo B: agência operada por agentes
A69: Premissa | B69: Unidade | C69: Conservador | D69: Base | E69: Otimista | F69: Usado | G69: Fonte ou justificativa
A70: CAC na mídia paga (venda consultiva) | B70: R$ | C70: 9000 | D70: 6500 | E70: 5000 | F70: =CHOOSE($C$3,C70,D70,E70) | G70: v2.1: mesmo método do Modelo A (recuperação do CAC em cerca de 8 meses sobre a contribuição ponderada pelos planos)
A71: Custo por cliente vindo de parceria (comissão) | B71: R$ | C71: 2500 | D71: 2000 | E71: 1600 | F71: =CHOOSE($C$3,C71,D71,E71) | G71: Comissão de cerca de 1,5 mensalidade
A72: Custo mensal do especialista que supervisiona as contas | B72: R$ | C72: 11000 | D72: 10000 | E72: 9000 | F72: =CHOOSE($C$3,C72,D72,E72) | G72: Profissional de marketing pleno ou sênior
A73: Preço por consulta nova agendada e atribuída à Jalecon | B73: R$ | C73: 0 | D73: 0 | E73: 0 | F73: =CHOOSE($C$3,C73,D73,E73) | G73: v2.1: desligado. Cobrar por paciente recebido pode ferir o art. 59 do Código de Ética Médica (contraprova); só volta com parecer jurídico favorável
A74: Presença: preço mensal fixo | B74: R$ | C74: 990 | D74: 990 | E74: 990 | F74: =CHOOSE($C$3,C74,D74,E74) | G74: Faixa entre a Doctoralia (R$ 429 a R$ 877) e a mediana de agências (R$ 3.250)
A75: Presença: taxa de implantação | B75: R$ | C75: 990 | D75: 990 | E75: 990 | F75: =CHOOSE($C$3,C75,D75,E75) | G75: Faixa entre a Doctoralia (R$ 429 a R$ 877) e a mediana de agências (R$ 3.250)
A76: Presença: participação nos novos clientes | B76: % | C76: 0.55 | D76: 0.55 | E76: 0.5 | F76: =CHOOSE($C$3,C76,D76,E76) | G76: Suposição
A77: Presença: churn mensal | B77: % | C77: 0.07 | D77: 0.055 | E77: 0.035 | F77: =CHOOSE($C$3,C77,D77,E77) | G77: v2.1: regra pré-registrada (referência de software para pequenas empresas, 4% a 7%), porque o contrato é mensal. O valor de agência com contrato (2% a 3,5%) virou o cenário otimista
A78: Presença: custo direto por conta por mês (agentes, ferramentas) | B78: R$ | C78: 155 | D78: 120 | E78: 95 | F78: =CHOOSE($C$3,C78,D78,E78) | G78: Agentes de IA (mais peças, anúncios, atendimento no WhatsApp), imagens, hospedagem, API do WhatsApp
A79: Presença: contas por especialista humano | B79: contas | C79: 35 | D79: 50 | E79: 70 | F79: =CHOOSE($C$3,C79,D79,E79) | G79: v2.1: agências trabalham com 5 a 30 contas por gerente (contraprova). O otimista (40 a 70) é a aposta a provar no piloto
A80: Agenda Cheia: preço mensal fixo | B80: R$ | C80: 1790 | D80: 1790 | E80: 1790 | F80: =CHOOSE($C$3,C80,D80,E80) | G80: Faixa entre a Doctoralia (R$ 429 a R$ 877) e a mediana de agências (R$ 3.250)
A81: Agenda Cheia: taxa de implantação | B81: R$ | C81: 1490 | D81: 1490 | E81: 1490 | F81: =CHOOSE($C$3,C81,D81,E81) | G81: Faixa entre a Doctoralia (R$ 429 a R$ 877) e a mediana de agências (R$ 3.250)
... A93: Clínica: consultas novas atribuídas por cliente por mês | B93: consultas | C93: 20 | D93: 35 | E93: 50 | F93: =CHOOSE($C$3,C93,D93,E93) | G93: Suposição a validar no piloto; medido pelo link de WhatsApp e agenda
A95: 6. Critérios de corte do plano v1 (fixados em 19/10/2026)
A96: Premissa | B96: Unidade | C96: Conservador | D96: Base | E96: Otimista | F96: Usado | G96: Fonte ou justificativa
A97: H6: margem bruta mínima | B97: % | C97: 0.7 | D97: 0.7 | E97: 0.7 | F97: =CHOOSE($C$3,C97,D97,E97) | G97: Plano v1, seção 2
A98: H6: LTV/CAC mínimo no plano principal | B98: x | C98: 3 | D98: 3 | E98: 3 | F98: =CHOOSE($C$3,C98,D98,E98) | G98: Plano v1, seção 2
A99: H6: recuperação máxima do CAC | B99: meses | C99: 12 | D99: 12 | E99: 12 | F99: =CHOOSE($C$3,C99,D99,E99) | G99: Plano v1, seção 2
A100: H7: receita recorrente anual mínima em até 7 anos | B100: R$ | C100: 50000000 | D100: 50000000 | E100: 50000000 | F100: =CHOOSE($C$3,C100,D100,E100) | G100: Plano v1, seção 2
A101: H7: participação máxima do mercado endereçável quando atingir esse valor | B101: % | C101: 0.03 | D101: 0.03 | E101: 0.03 | F101: =CHOOSE($C$3,C101,D101,E101) | G101: Plano v1, seção 2
A103: 7. Ajustes da contraprova (v2.1, 20/10/2026)
A104: Premissa | B104: Unidade | C104: Conservador | D104: Base | E104: Otimista | F104: Usado | G104: Fonte ou justificativa
A105: Modelo A: custo de implantação por cliente novo | B105: R$ | C105: 200 | D105: 150 | E105: 100 | F105: =CHOOSE($C$3,C105,D105,E105) | G105: Onboarding assistido; antes a taxa de implantação era receita sem custo (contraprova)
A106: Modelo B: custo de implantação por cliente novo | B106: R$ | C106: 900 | D106: 600 | E106: 400 | F106: =CHOOSE($C$3,C106,D106,E106) | G106: Cerca de 6 horas de especialista mais ferramentas para marca, site e perfil no Google
A107: Modelo A: custo por cliente indicado (mês grátis) | B107: R$ | C107: 697 | D107: 697 | E107: 697 | F107: =CHOOSE($C$3,C107,D107,E107) | G107: Programa de indicação: um mês grátis; antes sem custo (contraprova)
A108: Modelo B: custo por cliente indicado (mês grátis) | B108: R$ | C108: 1300 | D108: 1300 | E108: 1300 | F108: =CHOOSE($C$3,C108,D108,E108) | G108: Um mês grátis na mensalidade média ponderada

Sheet Unidade
A1: Economia por cliente, por plano (cenário selecionado)
A2: Contribuição = mensalidade e consultas, menos impostos (alíquota cheia), meios de pagamento, custo direto e parte do especialista humano. LTV = contribuição / churn + taxa de implantação - custo de implantação.
A4: Modelo A: software por assinatura
A5: Plano | B5: Receita mensal | C5: Contribuição mensal | D5: Margem de contribuição | E5: Churn mensal | F5: LTV | G5: CAC mídia paga | H5: LTV/CAC | I5: Recuperação do CAC (meses)
A6: Essencial | B6: =Premissas!$F$45 | C6: =B6*(1-Premissas!$F$10-Premissas!$F$11)-Premissas!$F$49 | D6: =C6/B6 | E6: =Premissas!$F$48 | F6: =C6/E6+Premissas!$F$46-Premissas!$F$105 | G6: =Premissas!$F$42 | H6: =F6/G6 | I6: =G6/C6
A7: Consultório | B7: =Premissas!$F$50 | C7: =B7*(1-Premissas!$F$10-Premissas!$F$11)-Premissas!$F$54 | D7: =C7/B7 | E7: =Premissas!$F$53 | F7: =C7/E7+Premissas!$F$51-Premissas!$F$105 | G7: =Premissas!$F$42 | H7: =F7/G7 | I7: =G7/C7
A8: Autoridade | B8: =Premissas!$F$55 | C8: =B8*(1-Premissas!$F$10-Premissas!$F$11)-Premissas!$F$59-Premissas!$F$44/Premissas!$F$60 | D8: =C8/B8 | E8: =Premissas!$F$58 | F8: =C8/E8+Premissas!$F$56-Premissas!$F$105 | G8: =Premissas!$F$42 | H8: =F8/G8 | I8: =G8/C8
A9: Clínica | B9: =Premissas!$F$61 | C9: =B9*(1-Premissas!$F$10-Premissas!$F$11)-Premissas!$F$65-Premissas!$F$44/Premissas!$F$66 | D9: =C9/B9 | E9: =Premissas!$F$64 | F9: =C9/E9+Premissas!$F$62-Premissas!$F$105 | G9: =Premissas!$F$42 | H9: =F9/G9 | I9: =G9/C9
A11: Modelo B: agência operada por agentes
A12: Plano | B12: Receita mensal | C12: Contribuição mensal | D12: Margem de contribuição | E12: Churn mensal | F12: LTV | G12: CAC mídia paga | H12: LTV/CAC | I12: Recuperação do CAC (meses)
A13: Presença | B13: =Premissas!$F$74 | C13: =B13*(1-Premissas!$F$10-Premissas!$F$11)-Premissas!$F$78-Premissas!$F$72/Premissas!$F$79 | D13: =C13/B13 | E13: =Premissas!$F$77 | F13: =C13/E13+Premissas!$F$75-Premissas!$F$106 | G13: =Premissas!$F$70 | H13: =F13/G13 | I13: =G13/C13
A14: Agenda Cheia | B14: =Premissas!$F$80+Premissas!$F$86*Premissas!$F$73 | C14: =B14*(1-Premissas!$F$10-Premissas!$F$11)-Premissas!$F$84-Premissas!$F$72/Premissas!$F$85 | D14: =C14/B14 | E14: =Premissas!$F$83 | F14: =C14/E14+Premissas!$F$81-Premissas!$F$106 | G14: =Premissas!$F$70 | H14: =F14/G14 | I14: =G14/C14
A15: Clínica | B15: =Premissas!$F$87+Premissas!$F$93*Premissas!$F$73 | C15: =B15*(1-Premissas!$F$10-Premissas!$F$11)-Premissas!$F$91-Premissas!$F$72/Premissas!$F$92 | D15: =C15/B15 | E15: =Premissas!$F$90 | F15: =C15/E15+Premissas!$F$88-Premissas!$F$106 | G15: =Premissas!$F$70 | H15: =F15/G15 | I15: =G15/C15

Sheet Modelo A
A1: Modelo A: software por assinatura · mês a mês
A2: Mês | C2: 1 | D2: 2 | E2: 3 | F2: 4 | G2: 5 | H2: 6 | I2: 7 | J2: 8 | K2: 9 | L2: 10 | M2: 11 | N2: 12 | O2: 13 | P2: 14 | Q2: 15 | R2: 16 | S2: 17 | T2: 18 | U2: 19 | V2: 20 | W2: 21 | X2: 22 | Y2: 23 | Z2: 24 | AA2: 25 | AB2: 26 | AC2: 27 | AD2: 28 | AE2: 29 | AF2: 30 | AG2: 31 | AH2: 32 | AI2: 33 | AJ2: 34 | AK2: 35 | AL2: 36 | AM2: 37 | AN2: 38 | AO2: 39 | AP2: 40 | AQ2: 41 | AR2: 42 | AS2: 43 | AT2: 44 | AU2: 45 | AV2: 46 | AW2: 47 | AX2: 48 | AY2: 49 | AZ2: 50 | BA2: 51 | BB2: 52 | BC2: 53 | BD2: 54 | BE2: 55 | BF2: 56 | BG2: 57 | BH2: 58 | BI2: 59 | BJ2: 60 | BK2: 61 | BL2: 62 | BM2: 63 | BN2: 64 | BO2: 65 | BP2: 66 | BQ2: 67 | BR2: 68 | BS2: 69 | BT2: 70 | BU2: 71 | BV2: 72 | BW2: 73 | BX2: 74 | BY2: 75 | BZ2: 76 | CA2: 77 | CB2: 78 | CC2: 79 | CD2: 80 | CE2: 81 | CF2: 82 | CG2: 83 | CH2: 84
A3: Ano | C3: =ROUNDUP(C2/12,0) | D3: =ROUNDUP(D2/12,0) | E3: =ROUNDUP(E2/12,0) | F3: =ROUNDUP(F2/12,0) | G3: =ROUNDUP(G2/12,0) | H3: =ROUNDUP(H2/12,0) | I3: =ROUNDUP(I2/12,0) | J3: =ROUNDUP(J2/12,0) | ... CH3: =ROUNDUP(CH2/12,0)
A4: Venda ativa (1 a partir do lançamento) | C4: =IF(C2>=Premissas!$F$8,1,0) | D4: =IF(D2>=Premissas!$F$8,1,0) | E4: =IF(E2>=Premissas!$F$8,1,0) | F4: =IF(F2>=Premissas!$F$8,1,0) | G4: =IF(G2>=Premissas!$F$8,1,0) | H4: =IF(H2>=Premissas!$F$8,1,0) | I4: =IF(I2>=Premissas!$F$8,1,0) | J4: =IF(J2>=Premissas!$F$8,1,0) | ... CH4: =IF(CH2>=Premissas!$F$8,1,0)
A5: Fator de expansão para dentistas | C5: =IF(C2>=Premissas!$F$13,1+Premissas!$F$14,1) | D5: =IF(D2>=Premissas!$F$13,1+Premissas!$F$14,1) | E5: =IF(E2>=Premissas!$F$13,1+Premissas!$F$14,1) | F5: =IF(F2>=Premissas!$F$13,1+Premissas!$F$14,1) | G5: =IF(G2>=Premissas!$F$13,1+Premissas!$F$14,1) | H5: =IF(H2>=Premissas!$F$13,1+Premissas!$F$14,1) | I5: =IF(I2>=Premissas!$F$13,1+Premissas!$F$14,1) | J5: =IF(J2>=Premissas!$F$13,1+Premissas!$F$14,1) | ... CH5: =IF(CH2>=Premissas!$F$13,1+Premissas!$F$14,1)
A7: Aquisição
A8: Mídia paga no mês | C8: =INDEX(Premissas!$C$22:$I$22,1,C3)*C4*C5 | D8: =INDEX(Premissas!$C$22:$I$22,1,D3)*D4*D5 | E8: =INDEX(Premissas!$C$22:$I$22,1,E3)*E4*E5 | F8: =INDEX(Premissas!$C$22:$I$22,1,F3)*F4*F5 | G8: =INDEX(Premissas!$C$22:$I$22,1,G3)*G4*G5 | H8: =INDEX(Premissas!$C$22:$I$22,1,H3)*H4*H5 | I8: =INDEX(Premissas!$C$22:$I$22,1,I3)*I4*I5 | J8: =INDEX(Premissas!$C$22:$I$22,1,J3)*J4*J5 | ... CH8: =INDEX(Premissas!$C$22:$I$22,1,CH3)*CH4*CH5
A9: Novos clientes por mídia paga | C9: =C8/Premissas!$F$42 | D9: =D8/Premissas!$F$42 | E9: =E8/Premissas!$F$42 | F9: =F8/Premissas!$F$42 | G9: =G8/Premissas!$F$42 | H9: =H8/Premissas!$F$42 | I9: =I8/Premissas!$F$42 | J9: =J8/Premissas!$F$42 | ... CH9: =CH8/Premissas!$F$42
A10: Novos clientes por parcerias | C10: =INDEX(Premissas!$C$23:$I$23,1,C3)*Premissas!$F$18*C4*C5 | D10: =INDEX(Premissas!$C$23:$I$23,1,D3)*Premissas!$F$18*D4*D5 | E10: =INDEX(Premissas!$C$23:$I$23,1,E3)*Premissas!$F$18*E4*E5 | F10: =INDEX(Premissas!$C$23:$I$23,1,F3)*Premissas!$F$18*F4*F5 | G10: =INDEX(Premissas!$C$23:$I$23,1,G3)*Premissas!$F$18*G4*G5 | H10: =INDEX(Premissas!$C$23:$I$23,1,H3)*Premissas!$F$18*H4*H5 | I10: =INDEX(Premissas!$C$23:$I$23,1,I3)*Premissas!$F$18*I4*I5 | J10: =INDEX(Premissas!$C$23:$I$23,1,J3)*Premissas!$F$18*J4*J5 | ... CH10: =INDEX(Premissas!$C$23:$I$23,1,CH3)*Premissas!$F$18*CH4*CH5
A11: Novos clientes por indicação | C11: =0 | D11: =C39*Premissas!$F$17*D4 | E11: =D39*Premissas!$F$17*E4 | F11: =E39*Premissas!$F$17*F4 | G11: =F39*Premissas!$F$17*G4 | H11: =G39*Premissas!$F$17*H4 | I11: =H39*Premissas!$F$17*I4 | J11: =I39*Premissas!$F$17*J4 | K11: =J39*Premissas!$F$17*K4 | ... CH11: =CG39*Premissas!$F$17*CH4
A12: Novos clientes no mês | C12: =C9+C10+C11 | D12: =D9+D10+D11 | E12: =E9+E10+E11 | F12: =F9+F10+F11 | G12: =G9+G10+G11 | H12: =H9+H10+H11 | I12: =I9+I10+I11 | J12: =J9+J10+J11 | ... CH12: =CH9+CH10+CH11
A14: Plano Essencial
A15: Participação nos novos | C15: =Premissas!$F$47 | D15: =Premissas!$F$47 | E15: =Premissas!$F$47 | F15: =Premissas!$F$47 | G15: =Premissas!$F$47 | H15: =Premissas!$F$47 | I15: =Premissas!$F$47 | J15: =Premissas!$F$47 | ... CH15: =Premissas!$F$47
A16: Novos | C16: =C12*C15 | D16: =D12*D15 | E16: =E12*E15 | F16: =F12*F15 | G16: =G12*G15 | H16: =H12*H15 | I16: =I12*I15 | J16: =J12*J15 | ... CH16: =CH12*CH15
A17: Cancelados | C17: =0*Premissas!$F$48 | D17: =C18*Premissas!$F$48 | E17: =D18*Premissas!$F$48 | F17: =E18*Premissas!$F$48 | G17: =F18*Premissas!$F$48 | H17: =G18*Premissas!$F$48 | I17: =H18*Premissas!$F$48 | J17: =I18*Premissas!$F$48 | K17: =J18*Premissas!$F$48 | ... CH17: =CG18*Premissas!$F$48
A18: Ativos no fim do mês | C18: =0+C16-C17 | D18: =C18+D16-D17 | E18: =D18+E16-E17 | F18: =E18+F16-F17 | G18: =F18+G16-G17 | H18: =G18+H16-H17 | I18: =H18+I16-I17 | J18: =I18+J16-J17 | K18: =J18+K16-K17 | ... CH18: =CG18+CH16-CH17
A20: Plano Consultório
A21: Participação nos novos | C21: =Premissas!$F$52+IF(C2<13,Premissas!$F$63,0) | D21: =Premissas!$F$52+IF(D2<13,Premissas!$F$63,0) | E21: =Premissas!$F$52+IF(E2<13,Premissas!$F$63,0) | F21: =Premissas!$F$52+IF(F2<13,Premissas!$F$63,0) | G21: =Premissas!$F$52+IF(G2<13,Premissas!$F$63,0) | H21: =Premissas!$F$52+IF(H2<13,Premissas!$F$63,0) | I21: =Premissas!$F$52+IF(I2<13,Premissas!$F$63,0) | J21: =Premissas!$F$52+IF(J2<13,Premissas!$F$63,0) | ... CH21: =Premissas!$F$52+IF(CH2<13,Premissas!$F$63,0)
A22: Novos | C22: =C12*C21 | D22: =D12*D21 | E22: =E12*E21 | F22: =F12*F21 | G22: =G12*G21 | H22: =H12*H21 | I22: =I12*I21 | J22: =J12*J21 | ... CH22: =CH12*CH21
A23: Cancelados | C23: =0*Premissas!$F$53 | D23: =C24*Premissas!$F$53 | E23: =D24*Premissas!$F$53 | F23: =E24*Premissas!$F$53 | G23: =F24*Premissas!$F$53 | H23: =G24*Premissas!$F$53 | I23: =H24*Premissas!$F$53 | J23: =I24*Premissas!$F$53 | K23: =J24*Premissas!$F$53 | ... CH23: =CG24*Premissas!$F$53
A24: Ativos no fim do mês | C24: =0+C22-C23 | D24: =C24+D22-D23 | E24: =D24+E22-E23 | F24: =E24+F22-F23 | G24: =F24+G22-G23 | H24: =G24+H22-H23 | I24: =H24+I22-I23 | J24: =I24+J22-J23 | K24: =J24+K22-K23 | ... CH24: =CG24+CH22-CH23
A26: Plano Autoridade
A27: Participação nos novos | C27: =Premissas!$F$57 | D27: =Premissas!$F$57 | E27: =Premissas!$F$57 | F27: =Premissas!$F$57 | G27: =Premissas!$F$57 | H27: =Premissas!$F$57 | I27: =Premissas!$F$57 | J27: =Premissas!$F$57 | ... CH27: =Premissas!$F$57
A28: Novos | C28: =C12*C27 | D28: =D12*D27 | E28: =E12*E27 | F28: =F12*F27 | G28: =G12*G27 | H28: =H12*H27 | I28: =I12*I27 | J28: =J12*J27 | ... CH28: =CH12*CH27
A29: Cancelados | C29: =0*Premissas!$F$58 | D29: =C30*Premissas!$F$58 | E29: =D30*Premissas!$F$58 | F29: =E30*Premissas!$F$58 | G29: =F30*Premissas!$F$58 | H29: =G30*Premissas!$F$58 | I29: =H30*Premissas!$F$58 | J29: =I30*Premissas!$F$58 | K29: =J30*Premissas!$F$58 | ... CH29: =CG30*Premissas!$F$58
A30: Ativos no fim do mês | C30: =0+C28-C29 | D30: =C30+D28-D29 | E30: =D30+E28-E29 | F30: =E30+F28-F29 | G30: =F30+G28-G29 | H30: =G30+H28-H29 | I30: =H30+I28-I29 | J30: =I30+J28-J29 | K30: =J30+K28-K29 | ... CH30: =CG30+CH28-CH29
A32: Plano Clínica
A33: Participação nos novos | C33: =IF(C2>=13,Premissas!$F$63,0) | D33: =IF(D2>=13,Premissas!$F$63,0) | E33: =IF(E2>=13,Premissas!$F$63,0) | F33: =IF(F2>=13,Premissas!$F$63,0) | G33: =IF(G2>=13,Premissas!$F$63,0) | H33: =IF(H2>=13,Premissas!$F$63,0) | I33: =IF(I2>=13,Premissas!$F$63,0) | J33: =IF(J2>=13,Premissas!$F$63,0) | ... CH33: =IF(CH2>=13,Premissas!$F$63,0)
A34: Novos | C34: =C12*C33 | D34: =D12*D33 | E34: =E12*E33 | F34: =F12*F33 | G34: =G12*G33 | H34: =H12*H33 | I34: =I12*I33 | J34: =J12*J33 | ... CH34: =CH12*CH33
A35: Cancelados | C35: =0*Premissas!$F$64 | D35: =C36*Premissas!$F$64 | E35: =D36*Premissas!$F$64 | F35: =E36*Premissas!$F$64 | G35: =F36*Premissas!$F$64 | H35: =G36*Premissas!$F$64 | I35: =H36*Premissas!$F$64 | J35: =I36*Premissas!$F$64 | K35: =J36*Premissas!$F$64 | ... CH35: =CG36*Premissas!$F$64
A36: Ativos no fim do mês | C36: =0+C34-C35 | D36: =C36+D34-D35 | E36: =D36+E34-E35 | F36: =E36+F34-F35 | G36: =F36+G34-G35 | H36: =G36+H34-H35 | I36: =H36+I34-I35 | J36: =I36+J34-J35 | K36: =J36+K34-K35 | ... CH36: =CG36+CH34-CH35
A38: Clientes e receita
A39: Clientes ativos | C39: =C18+C24+C30+C36 | D39: =D18+D24+D30+D36 | E39: =E18+E24+E30+E36 | F39: =F18+F24+F30+F36 | G39: =G18+G24+G30+G36 | H39: =H18+H24+H30+H36 | I39: =I18+I24+I30+I36 | J39: =J18+J24+J30+J36 | ... CH39: =CH18+CH24+CH30+CH36
A40: Mercado endereçável no mês | C40: =Premissas!$F$12+IF(C2>=Premissas!$F$13,Premissas!$F$15,0) | D40: =Premissas!$F$12+IF(D2>=Premissas!$F$13,Premissas!$F$15,0) | E40: =Premissas!$F$12+IF(E2>=Premissas!$F$13,Premissas!$F$15,0) | F40: =Premissas!$F$12+IF(F2>=Premissas!$F$13,Premissas!$F$15,0) | G40: =Premissas!$F$12+IF(G2>=Premissas!$F$13,Premissas!$F$15,0) | H40: =Premissas!$F$12+IF(H2>=Premissas!$F$13,Premissas!$F$15,0) | I40: =Premissas!$F$12+IF(I2>=Premissas!$F$13,Premissas!$F$15,0) | J40: =Premissas!$F$12+IF(J2>=Premissas!$F$13,Premissas!$F$15,0) | ... CH40: =Premissas!$F$12+IF(CH2>=Premissas!$F$13,Premissas!$F$15,0)
A41: Participação no mercado endereçável | C41: =C39/C40 | D41: =D39/D40 | E41: =E39/E40 | F41: =F39/F40 | G41: =G39/G40 | H41: =H39/H40 | I41: =I39/I40 | J41: =J39/J40 | ... CH41: =CH39/CH40
A42: Receita de mensalidades | C42: =C18*Premissas!$F$45+C24*Premissas!$F$50+C30*Premissas!$F$55+C36*Premissas!$F$61 | D42: =D18*Premissas!$F$45+D24*Premissas!$F$50+D30*Premissas!$F$55+D36*Premissas!$F$61 | E42: =E18*Premissas!$F$45+E24*Premissas!$F$50+E30*Premissas!$F$55+E36*Premissas!$F$61 | F42: =F18*Premissas!$F$45+F24*Premissas!$F$50+F30*Premissas!$F$55+F36*Premissas!$F$61 | G42: =G18*Premissas!$F$45+G24*Premissas!$F$50+G30*Premissas!$F$55+G36*Premissas!$F$61 | H42: =H18*Premissas!$F$45+H24*Premissas!$F$50+H30*Premissas!$F$55+H36*Premissas!$F$61 | I42: =I18*Premissas!$F$45+I24*Premissas!$F$50+I30*Premissas!$F$55+I36*Premissas!$F$61 | J42: =J18*Premissas!$F$45+J24*Premissas!$F$50+J30*Premissas!$F$55+J36*Premissas!$F$61 | ... CH42: =CH18*Premissas!$F$45+CH24*Premissas!$F$50+CH30*Premissas!$F$55+CH36*Premissas!$F$61
A43: Receita de implantação | C43: =C16*Premissas!$F$46+C22*Premissas!$F$51+C28*Premissas!$F$56+C34*Premissas!$F$62 | D43: =D16*Premissas!$F$46+D22*Premissas!$F$51+D28*Premissas!$F$56+D34*Premissas!$F$62 | E43: =E16*Premissas!$F$46+E22*Premissas!$F$51+E28*Premissas!$F$56+E34*Premissas!$F$62 | F43: =F16*Premissas!$F$46+F22*Premissas!$F$51+F28*Premissas!$F$56+F34*Premissas!$F$62 | G43: =G16*Premissas!$F$46+G22*Premissas!$F$51+G28*Premissas!$F$56+G34*Premissas!$F$62 | H43: =H16*Premissas!$F$46+H22*Premissas!$F$51+H28*Premissas!$F$56+H34*Premissas!$F$62 | I43: =I16*Premissas!$F$46+I22*Premissas!$F$51+I28*Premissas!$F$56+I34*Premissas!$F$62 | J43: =J16*Premissas!$F$46+J22*Premissas!$F$51+J28*Premissas!$F$56+J34*Premissas!$F$62 | ... CH43: =CH16*Premissas!$F$46+CH22*Premissas!$F$51+CH28*Premissas!$F$56+CH34*Premissas!$F$62
A44: Receita por consulta agendada | C44: =0 | D44: =0 | E44: =0 | F44: =0 | G44: =0 | H44: =0 | I44: =0 | J44: =0 | ... CH44: =0
A45: Receita bruta | C45: =C42+C43+C44 | D45: =D42+D43+D44 | E45: =E42+E43+E44 | F45: =F42+F43+F44 | G45: =G42+G43+G44 | H45: =H42+H43+H44 | I45: =I42+I43+I44 | J45: =J42+J43+J44 | ... CH45: =CH42+CH43+CH44
A46: Receita recorrente mensal (mensalidades + consultas) | C46: =C42+C44 | D46: =D42+D44 | E46: =E42+E44 | F46: =F42+F44 | G46: =G42+G44 | H46: =H42+H44 | I46: =I42+I44 | J46: =J42+J44 | ... CH46: =CH42+CH44
A47: Receita recorrente anualizada (MRR × 12) | C47: =C46*12 | D47: =D46*12 | E47: =E46*12 | F47: =F46*12 | G47: =G46*12 | H47: =H46*12 | I47: =I46*12 | J47: =J46*12 | ... CH47: =CH46*12
A48: Impostos sobre a receita | C48: =C45*IF(SUMIFS($C$45:$CH$45,$C$2:$CH$2,">="&(C2-12),$C$2:$CH$2,"<"&C2)>4800000,Premissas!$F$10,Premissas!$F$9) | D48: =D45*IF(SUMIFS($C$45:$CH$45,$C$2:$CH$2,">="&(D2-12),$C$2:$CH$2,"<"&D2)>4800000,Premissas!$F$10,Premissas!$F$9) | E48: =E45*IF(SUMIFS($C$45:$CH$45,$C$2:$CH$2,">="&(E2-12),$C$2:$CH$2,"<"&E2)>4800000,Premissas!$F$10,Premissas!$F$9) | F48: =F45*IF(SUMIFS($C$45:$CH$45,$C$2:$CH$2,">="&(F2-12),$C$2:$CH$2,"<"&F2)>4800000,Premissas!$F$10,Premissas!$F$9) | G48: =G45*IF(SUMIFS($C$45:$CH$45,$C$2:$CH$2,">="&(G2-12),$C$2:$CH$2,"<"&G2)>4800000,Premissas!$F$10,Premissas!$F$9) | H48: =H45*IF(SUMIFS($C$45:$CH$45,$C$2:$CH$2,">="&(H2-12),$C$2:$CH$2,"<"&H2)>4800000,Premissas!$F$10,Premissas!$F$9) | I48: =I45*IF(SUMIFS($C$45:$CH$45,$C$2:$CH$2,">="&(I2-12),$C$2:$CH$2,"<"&I2)>4800000,Premissas!$F$10,Premissas!$F$9) | J48: =J45*IF(SUMIFS($C$45:$CH$45,$C$2:$CH$2,">="&(J2-12),$C$2:$CH$2,"<"&J2)>4800000,Premissas!$F$10,Premissas!$F$9) | ... CH48: =CH45*IF(SUMIFS($C$45:$CH$45,$C$2:$CH$2,">="&(CH2-12),$C$2:$CH$2,"<"&CH2)>4800000,Premissas!$F$10,Premissas!$F$9)
A49: Meios de pagamento | C49: =C45*Premissas!$F$11 | D49: =D45*Premissas!$F$11 | E49: =E45*Premissas!$F$11 | F49: =F45*Premissas!$F$11 | G49: =G45*Premissas!$F$11 | H49: =H45*Premissas!$F$11 | I49: =I45*Premissas!$F$11 | J49: =J45*Premissas!$F$11 | ... CH49: =CH45*Premissas!$F$11
A50: Receita líquida | C50: =C45-C48-C49 | D50: =D45-D48-D49 | E50: =E45-E48-E49 | F50: =F45-F48-F49 | G50: =G45-G48-G49 | H50: =H45-H48-H49 | I50: =I45-I48-I49 | J50: =J45-J48-J49 | ... CH50: =CH45-CH48-CH49
A52: Custo do serviço
A53: Custo direto (IA, ferramentas, hospedagem, implantação) | C53: =C18*Premissas!$F$49+C24*Premissas!$F$54+C30*Premissas!$F$59+C36*Premissas!$F$65+C12*Premissas!$F$105 | D53: =D18*Premissas!$F$49+D24*Premissas!$F$54+D30*Premissas!$F$59+D36*Premissas!$F$65+D12*Premissas!$F$105 | E53: =E18*Premissas!$F$49+E24*Premissas!$F$54+E30*Premissas!$F$59+E36*Premissas!$F$65+E12*Premissas!$F$105 | F53: =F18*Premissas!$F$49+F24*Premissas!$F$54+F30*Premissas!$F$59+F36*Premissas!$F$65+F12*Premissas!$F$105 | G53: =G18*Premissas!$F$49+G24*Premissas!$F$54+G30*Premissas!$F$59+G36*Premissas!$F$65+G12*Premissas!$F$105 | H53: =H18*Premissas!$F$49+H24*Premissas!$F$54+H30*Premissas!$F$59+H36*Premissas!$F$65+H12*Premissas!$F$105 | I53: =I18*Premissas!$F$49+I24*Premissas!$F$54+I30*Premissas!$F$59+I36*Premissas!$F$65+I12*Premissas!$F$105 | J53: =J18*Premissas!$F$49+J24*Premissas!$F$54+J30*Premissas!$F$59+J36*Premissas!$F$65+J12*Premissas!$F$105 | ... CH53: =CH18*Premissas!$F$49+CH24*Premissas!$F$54+CH30*Premissas!$F$59+CH36*Premissas!$F$65+CH12*Premissas!$F$105
A54: Especialistas humanos nas contas (pessoas) | C54: =C30/Premissas!$F$60+C36/Premissas!$F$66 | D54: =D30/Premissas!$F$60+D36/Premissas!$F$66 | E54: =E30/Premissas!$F$60+E36/Premissas!$F$66 | F54: =F30/Premissas!$F$60+F36/Premissas!$F$66 | G54: =G30/Premissas!$F$60+G36/Premissas!$F$66 | H54: =H30/Premissas!$F$60+H36/Premissas!$F$66 | I54: =I30/Premissas!$F$60+I36/Premissas!$F$66 | J54: =J30/Premissas!$F$60+J36/Premissas!$F$66 | ... CH54: =CH30/Premissas!$F$60+CH36/Premissas!$F$66
A55: Custo dos especialistas | C55: =C54*Premissas!$F$44 | D55: =D54*Premissas!$F$44 | E55: =E54*Premissas!$F$44 | F55: =F54*Premissas!$F$44 | G55: =G54*Premissas!$F$44 | H55: =H54*Premissas!$F$44 | I55: =I54*Premissas!$F$44 | J55: =J54*Premissas!$F$44 | ... CH55: =CH54*Premissas!$F$44
A56: Custo do serviço total | C56: =C53+C55 | D56: =D53+D55 | E56: =E53+E55 | F56: =F53+F55 | G56: =G53+G55 | H56: =H53+H55 | I56: =I53+I55 | J56: =J53+J55 | ... CH56: =CH53+CH55
A57: Lucro bruto | C57: =C50-C56 | D57: =D50-D56 | E57: =E50-E56 | F57: =F50-F56 | G57: =G50-G56 | H57: =H50-H56 | I57: =I50-I56 | J57: =J50-J56 | ... CH57: =CH50-CH56
A58: Margem bruta (sobre a receita líquida) | C58: =IF(C50>0,C57/C50,0) | D58: =IF(D50>0,D57/D50,0) | E58: =IF(E50>0,E57/E50,0) | F58: =IF(F50>0,F57/F50,0) | G58: =IF(G50>0,G57/G50,0) | H58: =IF(H50>0,H57/H50,0) | I58: =IF(I50>0,I57/I50,0) | J58: =IF(J50>0,J57/J50,0) | ... CH58: =IF(CH50>0,CH57/CH50,0)
A60: Despesas operacionais
A61: Produto, engenharia e IA | C61: =INDEX(Premissas!$C$24:$I$24,1,C3)*Premissas!$F$32 | D61: =INDEX(Premissas!$C$24:$I$24,1,D3)*Premissas!$F$32 | E61: =INDEX(Premissas!$C$24:$I$24,1,E3)*Premissas!$F$32 | F61: =INDEX(Premissas!$C$24:$I$24,1,F3)*Premissas!$F$32 | G61: =INDEX(Premissas!$C$24:$I$24,1,G3)*Premissas!$F$32 | H61: =INDEX(Premissas!$C$24:$I$24,1,H3)*Premissas!$F$32 | I61: =INDEX(Premissas!$C$24:$I$24,1,I3)*Premissas!$F$32 | J61: =INDEX(Premissas!$C$24:$I$24,1,J3)*Premissas!$F$32 | ... CH61: =INDEX(Premissas!$C$24:$I$24,1,CH3)*Premissas!$F$32
A62: Equipe de vendas e marketing | C62: =INDEX(Premissas!$C$27:$I$27,1,C3)*Premissas!$F$33 | D62: =INDEX(Premissas!$C$27:$I$27,1,D3)*Premissas!$F$33 | E62: =INDEX(Premissas!$C$27:$I$27,1,E3)*Premissas!$F$33 | F62: =INDEX(Premissas!$C$27:$I$27,1,F3)*Premissas!$F$33 | G62: =INDEX(Premissas!$C$27:$I$27,1,G3)*Premissas!$F$33 | H62: =INDEX(Premissas!$C$27:$I$27,1,H3)*Premissas!$F$33 | I62: =INDEX(Premissas!$C$27:$I$27,1,I3)*Premissas!$F$33 | J62: =INDEX(Premissas!$C$27:$I$27,1,J3)*Premissas!$F$33 | ... CH62: =INDEX(Premissas!$C$27:$I$27,1,CH3)*Premissas!$F$33
A63: Administrativo, jurídico e conformidade | C63: =INDEX(Premissas!$C$25:$I$25,1,C3)*Premissas!$F$34 | D63: =INDEX(Premissas!$C$25:$I$25,1,D3)*Premissas!$F$34 | E63: =INDEX(Premissas!$C$25:$I$25,1,E3)*Premissas!$F$34 | F63: =INDEX(Premissas!$C$25:$I$25,1,F3)*Premissas!$F$34 | G63: =INDEX(Premissas!$C$25:$I$25,1,G3)*Premissas!$F$34 | H63: =INDEX(Premissas!$C$25:$I$25,1,H3)*Premissas!$F$34 | I63: =INDEX(Premissas!$C$25:$I$25,1,I3)*Premissas!$F$34 | J63: =INDEX(Premissas!$C$25:$I$25,1,J3)*Premissas!$F$34 | ... CH63: =INDEX(Premissas!$C$25:$I$25,1,CH3)*Premissas!$F$34
A64: Pró-labore dos fundadores | C64: =INDEX(Premissas!$C$26:$I$26,1,C3)*Premissas!$F$35 | D64: =INDEX(Premissas!$C$26:$I$26,1,D3)*Premissas!$F$35 | E64: =INDEX(Premissas!$C$26:$I$26,1,E3)*Premissas!$F$35 | F64: =INDEX(Premissas!$C$26:$I$26,1,F3)*Premissas!$F$35 | G64: =INDEX(Premissas!$C$26:$I$26,1,G3)*Premissas!$F$35 | H64: =INDEX(Premissas!$C$26:$I$26,1,H3)*Premissas!$F$35 | I64: =INDEX(Premissas!$C$26:$I$26,1,I3)*Premissas!$F$35 | J64: =INDEX(Premissas!$C$26:$I$26,1,J3)*Premissas!$F$35 | ... CH64: =INDEX(Premissas!$C$26:$I$26,1,CH3)*Premissas!$F$35
A65: Mídia paga | C65: =C8 | D65: =D8 | E65: =E8 | F65: =F8 | G65: =G8 | H65: =H8 | I65: =I8 | J65: =J8 | ... CH65: =CH8
A66: Comissões de parceria e meses grátis de indicação | C66: =C10*Premissas!$F$43+C11*Premissas!$F$107 | D66: =D10*Premissas!$F$43+D11*Premissas!$F$107 | E66: =E10*Premissas!$F$43+E11*Premissas!$F$107 | F66: =F10*Premissas!$F$43+F11*Premissas!$F$107 | G66: =G10*Premissas!$F$43+G11*Premissas!$F$107 | H66: =H10*Premissas!$F$43+H11*Premissas!$F$107 | I66: =I10*Premissas!$F$43+I11*Premissas!$F$107 | J66: =J10*Premissas!$F$43+J11*Premissas!$F$107 | ... CH66: =CH10*Premissas!$F$43+CH11*Premissas!$F$107
A67: Marca e eventos | C67: =C8*Premissas!$F$38 | D67: =D8*Premissas!$F$38 | E67: =E8*Premissas!$F$38 | F67: =F8*Premissas!$F$38 | G67: =G8*Premissas!$F$38 | H67: =H8*Premissas!$F$38 | I67: =I8*Premissas!$F$38 | J67: =J8*Premissas!$F$38 | ... CH67: =CH8*Premissas!$F$38
A68: Outras despesas | C68: =Premissas!$F$36+C45*Premissas!$F$37 | D68: =Premissas!$F$36+D45*Premissas!$F$37 | E68: =Premissas!$F$36+E45*Premissas!$F$37 | F68: =Premissas!$F$36+F45*Premissas!$F$37 | G68: =Premissas!$F$36+G45*Premissas!$F$37 | H68: =Premissas!$F$36+H45*Premissas!$F$37 | I68: =Premissas!$F$36+I45*Premissas!$F$37 | J68: =Premissas!$F$36+J45*Premissas!$F$37 | ... CH68: =Premissas!$F$36+CH45*Premissas!$F$37
A69: Custo único da expansão | C69: =IF(C2=Premissas!$F$13,Premissas!$F$16,0) | D69: =IF(D2=Premissas!$F$13,Premissas!$F$16,0) | E69: =IF(E2=Premissas!$F$13,Premissas!$F$16,0) | F69: =IF(F2=Premissas!$F$13,Premissas!$F$16,0) | G69: =IF(G2=Premissas!$F$13,Premissas!$F$16,0) | H69: =IF(H2=Premissas!$F$13,Premissas!$F$16,0) | I69: =IF(I2=Premissas!$F$13,Premissas!$F$16,0) | J69: =IF(J2=Premissas!$F$13,Premissas!$F$16,0) | ... CH69: =IF(CH2=Premissas!$F$13,Premissas!$F$16,0)
A70: Despesas operacionais totais | C70: =C61+C62+C63+C64+C65+C66+C67+C68+C69 | D70: =D61+D62+D63+D64+D65+D66+D67+D68+D69 | E70: =E61+E62+E63+E64+E65+E66+E67+E68+E69 | F70: =F61+F62+F63+F64+F65+F66+F67+F68+F69 | G70: =G61+G62+G63+G64+G65+G66+G67+G68+G69 | H70: =H61+H62+H63+H64+H65+H66+H67+H68+H69 | I70: =I61+I62+I63+I64+I65+I66+I67+I68+I69 | J70: =J61+J62+J63+J64+J65+J66+J67+J68+J69 | ... CH70: =CH61+CH62+CH63+CH64+CH65+CH66+CH67+CH68+CH69
A72: Resultado e caixa
A73: EBITDA | C73: =C57-C70 | D73: =D57-D70 | E73: =E57-E70 | F73: =F57-F70 | G73: =G57-G70 | H73: =H57-H70 | I73: =I57-I70 | J73: =J57-J70 | ... CH73: =CH57-CH70
A74: Caixa acumulado sem captação | C74: =0+C73 | D74: =C74+D73 | E74: =D74+E73 | F74: =E74+F73 | G74: =F74+G73 | H74: =G74+H73 | I74: =H74+I73 | J74: =I74+J73 | K74: =J74+K73 | ... CH74: =CG74+CH73
A75: Mês de equilíbrio candidato (EBITDA não volta a ficar negativo) | C75: =IF(COUNTIF(C73:$CH$73,"<0")=0,C2,"") | D75: =IF(COUNTIF(D73:$CH$73,"<0")=0,D2,"") | E75: =IF(COUNTIF(E73:$CH$73,"<0")=0,E2,"") | F75: =IF(COUNTIF(F73:$CH$73,"<0")=0,F2,"") | G75: =IF(COUNTIF(G73:$CH$73,"<0")=0,G2,"") | H75: =IF(COUNTIF(H73:$CH$73,"<0")=0,H2,"") | I75: =IF(COUNTIF(I73:$CH$73,"<0")=0,I2,"") | J75: =IF(COUNTIF(J73:$CH$73,"<0")=0,J2,"") | ... CH75: =IF(COUNTIF(CH73:$CH$73,"<0")=0,CH2,"")
A76: Mês em que a receita anualizada passa do critério H7 | C76: =IF(AND(C47>=Premissas!$F$100,0<Premissas!$F$100),C2,"") | D76: =IF(AND(D47>=Premissas!$F$100,C47<Premissas!$F$100),D2,"") | E76: =IF(AND(E47>=Premissas!$F$100,D47<Premissas!$F$100),E2,"") | F76: =IF(AND(F47>=Premissas!$F$100,E47<Premissas!$F$100),F2,"") | G76: =IF(AND(G47>=Premissas!$F$100,F47<Premissas!$F$100),G2,"") | H76: =IF(AND(H47>=Premissas!$F$100,G47<Premissas!$F$100),H2,"") | I76: =IF(AND(I47>=Premissas!$F$100,H47<Premissas!$F$100),I2,"") | J76: =IF(AND(J47>=Premissas!$F$100,I47<Premissas!$F$100),J2,"") | K76: =IF(AND(K47>=Premissas!$F$100,J47<Premissas!$F$100),K2,"") | ... CH76: =IF(AND(CH47>=Premissas!$F$100,CG47<Premissas!$F$100),CH2,"")
A77: Pessoas no total (fundadores, equipe e especialistas) | C77: =Premissas!$F$35+INDEX(Premissas!$C$24:$I$24,1,C3)+INDEX(Premissas!$C$27:$I$27,1,C3)+INDEX(Premissas!$C$25:$I$25,1,C3)+C54 | D77: =Premissas!$F$35+INDEX(Premissas!$C$24:$I$24,1,D3)+INDEX(Premissas!$C$27:$I$27,1,D3)+INDEX(Premissas!$C$25:$I$25,1,D3)+D54 | E77: =Premissas!$F$35+INDEX(Premissas!$C$24:$I$24,1,E3)+INDEX(Premissas!$C$27:$I$27,1,E3)+INDEX(Premissas!$C$25:$I$25,1,E3)+E54 | F77: =Premissas!$F$35+INDEX(Premissas!$C$24:$I$24,1,F3)+INDEX(Premissas!$C$27:$I$27,1,F3)+INDEX(Premissas!$C$25:$I$25,1,F3)+F54 | G77: =Premissas!$F$35+INDEX(Premissas!$C$24:$I$24,1,G3)+INDEX(Premissas!$C$27:$I$27,1,G3)+INDEX(Premissas!$C$25:$I$25,1,G3)+G54 | H77: =Premissas!$F$35+INDEX(Premissas!$C$24:$I$24,1,H3)+INDEX(Premissas!$C$27:$I$27,1,H3)+INDEX(Premissas!$C$25:$I$25,1,H3)+H54 | I77: =Premissas!$F$35+INDEX(Premissas!$C$24:$I$24,1,I3)+INDEX(Premissas!$C$27:$I$27,1,I3)+INDEX(Premissas!$C$25:$I$25,1,I3)+I54 | J77: =Premissas!$F$35+INDEX(Premissas!$C$24:$I$24,1,J3)+INDEX(Premissas!$C$27:$I$27,1,J3)+INDEX(Premissas!$C$25:$I$25,1,J3)+J54 | ... CH77: =Premissas!$F$35+INDEX(Premissas!$C$24:$I$24,1,CH3)+INDEX(Premissas!$C$27:$I$27,1,CH3)+INDEX(Premissas!$C$25:$I$25,1,CH3)+CH54

Sheet Modelo B
A1: Modelo B: agência operada por agentes · mês a mês
A2: Mês | C2: 1 | D2: 2 | E2: 3 | F2: 4 | G2: 5 | H2: 6 | I2: 7 | J2: 8 | K2: 9 | L2: 10 | M2: 11 | N2: 12 | O2: 13 | P2: 14 | Q2: 15 | R2: 16 | S2: 17 | T2: 18 | U2: 19 | V2: 20 | W2: 21 | X2: 22 | Y2: 23 | Z2: 24 | AA2: 25 | AB2: 26 | AC2: 27 | AD2: 28 | AE2: 29 | AF2: 30 | AG2: 31 | AH2: 32 | AI2: 33 | AJ2: 34 | AK2: 35 | AL2: 36 | AM2: 37 | AN2: 38 | AO2: 39 | AP2: 40 | AQ2: 41 | AR2: 42 | AS2: 43 | AT2: 44 | AU2: 45 | AV2: 46 | AW2: 47 | AX2: 48 | AY2: 49 | AZ2: 50 | BA2: 51 | BB2: 52 | BC2: 53 | BD2: 54 | BE2: 55 | BF2: 56 | BG2: 57 | BH2: 58 | BI2: 59 | BJ2: 60 | BK2: 61 | BL2: 62 | BM2: 63 | BN2: 64 | BO2: 65 | BP2: 66 | BQ2: 67 | BR2: 68 | BS2: 69 | BT2: 70 | BU2: 71 | BV2: 72 | BW2: 73 | BX2: 74 | BY2: 75 | BZ2: 76 | CA2: 77 | CB2: 78 | CC2: 79 | CD2: 80 | CE2: 81 | CF2: 82 | CG2: 83 | CH2: 84
A3: Ano | C3: =ROUNDUP(C2/12,0) | D3: =ROUNDUP(D2/12,0) | E3: =ROUNDUP(E2/12,0) | F3: =ROUNDUP(F2/12,0) | G3: =ROUNDUP(G2/12,0) | H3: =ROUNDUP(H2/12,0) | I3: =ROUNDUP(I2/12,0) | J3: =ROUNDUP(J2/12,0) | ... CH3: =ROUNDUP(CH2/12,0)
A4: Venda ativa (1 a partir do lançamento) | C4: =IF(C2>=Premissas!$F$8,1,0) | D4: =IF(D2>=Premissas!$F$8,1,0) | E4: =IF(E2>=Premissas!$F$8,1,0) | F4: =IF(F2>=Premissas!$F$8,1,0) | G4: =IF(G2>=Premissas!$F$8,1,0) | H4: =IF(H2>=Premissas!$F$8,1,0) | I4: =IF(I2>=Premissas!$F$8,1,0) | J4: =IF(J2>=Premissas!$F$8,1,0) | ... CH4: =IF(CH2>=Premissas!$F$8,1,0)
A5: Fator de expansão para dentistas | C5: =IF(C2>=Premissas!$F$13,1+Premissas!$F$14,1) | D5: =IF(D2>=Premissas!$F$13,1+Premissas!$F$14,1) | E5: =IF(E2>=Premissas!$F$13,1+Premissas!$F$14,1) | F5: =IF(F2>=Premissas!$F$13,1+Premissas!$F$14,1) | G5: =IF(G2>=Premissas!$F$13,1+Premissas!$F$14,1) | H5: =IF(H2>=Premissas!$F$13,1+Premissas!$F$14,1) | I5: =IF(I2>=Premissas!$F$13,1+Premissas!$F$14,1) | J5: =IF(J2>=Premissas!$F$13,1+Premissas!$F$14,1) | ... CH5: =IF(CH2>=Premissas!$F$13,1+Premissas!$F$14,1)
A7: Aquisição
A8: Mídia paga no mês | C8: =INDEX(Premissas!$C$22:$I$22,1,C3)*C4*C5 | D8: =INDEX(Premissas!$C$22:$I$22,1,D3)*D4*D5 | E8: =INDEX(Premissas!$C$22:$I$22,1,E3)*E4*E5 | F8: =INDEX(Premissas!$C$22:$I$22,1,F3)*F4*F5 | G8: =INDEX(Premissas!$C$22:$I$22,1,G3)*G4*G5 | H8: =INDEX(Premissas!$C$22:$I$22,1,H3)*H4*H5 | I8: =INDEX(Premissas!$C$22:$I$22,1,I3)*I4*I5 | J8: =INDEX(Premissas!$C$22:$I$22,1,J3)*J4*J5 | ... CH8: =INDEX(Premissas!$C$22:$I$22,1,CH3)*CH4*CH5
A9: Novos clientes por mídia paga | C9: =C8/Premissas!$F$70 | D9: =D8/Premissas!$F$70 | E9: =E8/Premissas!$F$70 | F9: =F8/Premissas!$F$70 | G9: =G8/Premissas!$F$70 | H9: =H8/Premissas!$F$70 | I9: =I8/Premissas!$F$70 | J9: =J8/Premissas!$F$70 | ... CH9: =CH8/Premissas!$F$70
A10: Novos clientes por parcerias | C10: =INDEX(Premissas!$C$23:$I$23,1,C3)*Premissas!$F$18*C4*C5 | D10: =INDEX(Premissas!$C$23:$I$23,1,D3)*Premissas!$F$18*D4*D5 | E10: =INDEX(Premissas!$C$23:$I$23,1,E3)*Premissas!$F$18*E4*E5 | F10: =INDEX(Premissas!$C$23:$I$23,1,F3)*Premissas!$F$18*F4*F5 | G10: =INDEX(Premissas!$C$23:$I$23,1,G3)*Premissas!$F$18*G4*G5 | H10: =INDEX(Premissas!$C$23:$I$23,1,H3)*Premissas!$F$18*H4*H5 | I10: =INDEX(Premissas!$C$23:$I$23,1,I3)*Premissas!$F$18*I4*I5 | J10: =INDEX(Premissas!$C$23:$I$23,1,J3)*Premissas!$F$18*J4*J5 | ... CH10: =INDEX(Premissas!$C$23:$I$23,1,CH3)*Premissas!$F$18*CH4*CH5
A11: Novos clientes por indicação | C11: =0 | D11: =C33*Premissas!$F$17*D4 | E11: =D33*Premissas!$F$17*E4 | F11: =E33*Premissas!$F$17*F4 | G11: =F33*Premissas!$F$17*G4 | H11: =G33*Premissas!$F$17*H4 | I11: =H33*Premissas!$F$17*I4 | J11: =I33*Premissas!$F$17*J4 | K11: =J33*Premissas!$F$17*K4 | ... CH11: =CG33*Premissas!$F$17*CH4
A12: Novos clientes no mês | C12: =C9+C10+C11 | D12: =D9+D10+D11 | E12: =E9+E10+E11 | F12: =F9+F10+F11 | G12: =G9+G10+G11 | H12: =H9+H10+H11 | I12: =I9+I10+I11 | J12: =J9+J10+J11 | ... CH12: =CH9+CH10+CH11
A14: Plano Presença
A15: Participação nos novos | C15: =Premissas!$F$76+IF(C2<9,Premissas!$F$82+IF(C2<13,Premissas!$F$89,0),0) | D15: =Premissas!$F$76+IF(D2<9,Premissas!$F$82+IF(D2<13,Premissas!$F$89,0),0) | E15: =Premissas!$F$76+IF(E2<9,Premissas!$F$82+IF(E2<13,Premissas!$F$89,0),0) | F15: =Premissas!$F$76+IF(F2<9,Premissas!$F$82+IF(F2<13,Premissas!$F$89,0),0) | G15: =Premissas!$F$76+IF(G2<9,Premissas!$F$82+IF(G2<13,Premissas!$F$89,0),0) | H15: =Premissas!$F$76+IF(H2<9,Premissas!$F$82+IF(H2<13,Premissas!$F$89,0),0) | I15: =Premissas!$F$76+IF(I2<9,Premissas!$F$82+IF(I2<13,Premissas!$F$89,0),0) | J15: =Premissas!$F$76+IF(J2<9,Premissas!$F$82+IF(J2<13,Premissas!$F$89,0),0) | ... CH15: =Premissas!$F$76+IF(CH2<9,Premissas!$F$82+IF(CH2<13,Premissas!$F$89,0),0)
A16: Novos | C16: =C12*C15 | D16: =D12*D15 | E16: =E12*E15 | F16: =F12*F15 | G16: =G12*G15 | H16: =H12*H15 | I16: =I12*I15 | J16: =J12*J15 | ... CH16: =CH12*CH15
A17: Cancelados | C17: =0*Premissas!$F$77 | D17: =C18*Premissas!$F$77 | E17: =D18*Premissas!$F$77 | F17: =E18*Premissas!$F$77 | G17: =F18*Premissas!$F$77 | H17: =G18*Premissas!$F$77 | I17: =H18*Premissas!$F$77 | J17: =I18*Premissas!$F$77 | K17: =J18*Premissas!$F$77 | ... CH17: =CG18*Premissas!$F$77
A18: Ativos no fim do mês | C18: =0+C16-C17 | D18: =C18+D16-D17 | E18: =D18+E16-E17 | F18: =E18+F16-F17 | G18: =F18+G16-G17 | H18: =G18+H16-H17 | I18: =H18+I16-I17 | J18: =I18+J16-J17 | K18: =J18+K16-K17 | ... CH18: =CG18+CH16-CH17
A20: Plano Agenda Cheia
A21: Participação nos novos | C21: =IF(C2>=9,Premissas!$F$82+IF(C2<13,Premissas!$F$89,0),0) | D21: =IF(D2>=9,Premissas!$F$82+IF(D2<13,Premissas!$F$89,0),0) | E21: =IF(E2>=9,Premissas!$F$82+IF(E2<13,Premissas!$F$89,0),0) | F21: =IF(F2>=9,Premissas!$F$82+IF(F2<13,Premissas!$F$89,0),0) | G21: =IF(G2>=9,Premissas!$F$82+IF(G2<13,Premissas!$F$89,0),0) | H21: =IF(H2>=9,Premissas!$F$82+IF(H2<13,Premissas!$F$89,0),0) | I21: =IF(I2>=9,Premissas!$F$82+IF(I2<13,Premissas!$F$89,0),0) | J21: =IF(J2>=9,Premissas!$F$82+IF(J2<13,Premissas!$F$89,0),0) | ... CH21: =IF(CH2>=9,Premissas!$F$82+IF(CH2<13,Premissas!$F$89,0),0)
A22: Novos | C22: =C12*C21 | D22: =D12*D21 | E22: =E12*E21 | F22: =F12*F21 | G22: =G12*G21 | H22: =H12*H21 | I22: =I12*I21 | J22: =J12*J21 | ... CH22: =CH12*CH21
A23: Cancelados | C23: =0*Premissas!$F$83 | D23: =C24*Premissas!$F$83 | E23: =D24*Premissas!$F$83 | F23: =E24*Premissas!$F$83 | G23: =F24*Premissas!$F$83 | H23: =G24*Premissas!$F$83 | I23: =H24*Premissas!$F$83 | J23: =I24*Premissas!$F$83 | K23: =J24*Premissas!$F$83 | ... CH23: =CG24*Premissas!$F$83
A24: Ativos no fim do mês | C24: =0+C22-C23 | D24: =C24+D22-D23 | E24: =D24+E22-E23 | F24: =E24+F22-F23 | G24: =F24+G22-G23 | H24: =G24+H22-H23 | I24: =H24+I22-I23 | J24: =I24+J22-J23 | K24: =J24+K22-K23 | ... CH24: =CG24+CH22-CH23
A26: Plano Clínica
A27: Participação nos novos | C27: =IF(C2>=13,Premissas!$F$89,0) | D27: =IF(D2>=13,Premissas!$F$89,0) | E27: =IF(E2>=13,Premissas!$F$89,0) | F27: =IF(F2>=13,Premissas!$F$89,0) | G27: =IF(G2>=13,Premissas!$F$89,0) | H27: =IF(H2>=13,Premissas!$F$89,0) | I27: =IF(I2>=13,Premissas!$F$89,0) | J27: =IF(J2>=13,Premissas!$F$89,0) | ... CH27: =IF(CH2>=13,Premissas!$F$89,0)
A28: Novos | C28: =C12*C27 | D28: =D12*D27 | E28: =E12*E27 | F28: =F12*F27 | G28: =G12*G27 | H28: =H12*H27 | I28: =I12*I27 | J28: =J12*J27 | ... CH28: =CH12*CH27
A29: Cancelados | C29: =0*Premissas!$F$90 | D29: =C30*Premissas!$F$90 | E29: =D30*Premissas!$F$90 | F29: =E30*Premissas!$F$90 | G29: =F30*Premissas!$F$90 | H29: =G30*Premissas!$F$90 | I29: =H30*Premissas!$F$90 | J29: =I30*Premissas!$F$90 | K29: =J30*Premissas!$F$90 | ... CH29: =CG30*Premissas!$F$90
A30: Ativos no fim do mês | C30: =0+C28-C29 | D30: =C30+D28-D29 | E30: =D30+E28-E29 | F30: =E30+F28-F29 | G30: =F30+G28-G29 | H30: =G30+H28-H29 | I30: =H30+I28-I29 | J30: =I30+J28-J29 | K30: =J30+K28-K29 | ... CH30: =CG30+CH28-CH29
A32: Clientes e receita
A33: Clientes ativos | C33: =C18+C24+C30 | D33: =D18+D24+D30 | E33: =E18+E24+E30 | F33: =F18+F24+F30 | G33: =G18+G24+G30 | H33: =H18+H24+H30 | I33: =I18+I24+I30 | J33: =J18+J24+J30 | ... CH33: =CH18+CH24+CH30
A34: Mercado endereçável no mês | C34: =Premissas!$F$12+IF(C2>=Premissas!$F$13,Premissas!$F$15,0) | D34: =Premissas!$F$12+IF(D2>=Premissas!$F$13,Premissas!$F$15,0) | E34: =Premissas!$F$12+IF(E2>=Premissas!$F$13,Premissas!$F$15,0) | F34: =Premissas!$F$12+IF(F2>=Premissas!$F$13,Premissas!$F$15,0) | G34: =Premissas!$F$12+IF(G2>=Premissas!$F$13,Premissas!$F$15,0) | H34: =Premissas!$F$12+IF(H2>=Premissas!$F$13,Premissas!$F$15,0) | I34: =Premissas!$F$12+IF(I2>=Premissas!$F$13,Premissas!$F$15,0) | J34: =Premissas!$F$12+IF(J2>=Premissas!$F$13,Premissas!$F$15,0) | ... CH34: =Premissas!$F$12+IF(CH2>=Premissas!$F$13,Premissas!$F$15,0)
A35: Participação no mercado endereçável | C35: =C33/C34 | D35: =D33/D34 | E35: =E33/E34 | F35: =F33/F34 | G35: =G33/G34 | H35: =H33/H34 | I35: =I33/I34 | J35: =J33/J34 | ... CH35: =CH33/CH34
A36: Receita de mensalidades | C36: =C18*Premissas!$F$74+C24*Premissas!$F$80+C30*Premissas!$F$87 | D36: =D18*Premissas!$F$74+D24*Premissas!$F$80+D30*Premissas!$F$87 | E36: =E18*Premissas!$F$74+E24*Premissas!$F$80+E30*Premissas!$F$87 | F36: =F18*Premissas!$F$74+F24*Premissas!$F$80+F30*Premissas!$F$87 | G36: =G18*Premissas!$F$74+G24*Premissas!$F$80+G30*Premissas!$F$87 | H36: =H18*Premissas!$F$74+H24*Premissas!$F$80+H30*Premissas!$F$87 | I36: =I18*Premissas!$F$74+I24*Premissas!$F$80+I30*Premissas!$F$87 | J36: =J18*Premissas!$F$74+J24*Premissas!$F$80+J30*Premissas!$F$87 | ... CH36: =CH18*Premissas!$F$74+CH24*Premissas!$F$80+CH30*Premissas!$F$87
A37: Receita de implantação | C37: =C16*Premissas!$F$75+C22*Premissas!$F$81+C28*Premissas!$F$88 | D37: =D16*Premissas!$F$75+D22*Premissas!$F$81+D28*Premissas!$F$88 | E37: =E16*Premissas!$F$75+E22*Premissas!$F$81+E28*Premissas!$F$88 | F37: =F16*Premissas!$F$75+F22*Premissas!$F$81+F28*Premissas!$F$88 | G37: =G16*Premissas!$F$75+G22*Premissas!$F$81+G28*Premissas!$F$88 | H37: =H16*Premissas!$F$75+H22*Premissas!$F$81+H28*Premissas!$F$88 | I37: =I16*Premissas!$F$75+I22*Premissas!$F$81+I28*Premissas!$F$88 | J37: =J16*Premissas!$F$75+J22*Premissas!$F$81+J28*Premissas!$F$88 | ... CH37: =CH16*Premissas!$F$75+CH22*Premissas!$F$81+CH28*Premissas!$F$88
A38: Receita por consulta agendada | C38: =(C24*Premissas!$F$86+C30*Premissas!$F$93)*Premissas!$F$73 | D38: =(D24*Premissas!$F$86+D30*Premissas!$F$93)*Premissas!$F$73 | E38: =(E24*Premissas!$F$86+E30*Premissas!$F$93)*Premissas!$F$73 | F38: =(F24*Premissas!$F$86+F30*Premissas!$F$93)*Premissas!$F$73 | G38: =(G24*Premissas!$F$86+G30*Premissas!$F$93)*Premissas!$F$73 | H38: =(H24*Premissas!$F$86+H30*Premissas!$F$93)*Premissas!$F$73 | I38: =(I24*Premissas!$F$86+I30*Premissas!$F$93)*Premissas!$F$73 | J38: =(J24*Premissas!$F$86+J30*Premissas!$F$93)*Premissas!$F$73 | ... CH38: =(CH24*Premissas!$F$86+CH30*Premissas!$F$93)*Premissas!$F$73
A39: Receita bruta | C39: =C36+C37+C38 | D39: =D36+D37+D38 | E39: =E36+E37+E38 | F39: =F36+F37+F38 | G39: =G36+G37+G38 | H39: =H36+H37+H38 | I39: =I36+I37+I38 | J39: =J36+J37+J38 | ... CH39: =CH36+CH37+CH38
A40: Receita recorrente mensal (mensalidades + consultas) | C40: =C36+C38 | D40: =D36+D38 | E40: =E36+E38 | F40: =F36+F38 | G40: =G36+G38 | H40: =H36+H38 | I40: =I36+I38 | J40: =J36+J38 | ... CH40: =CH36+CH38
A41: Receita recorrente anualizada (MRR × 12) | C41: =C40*12 | D41: =D40*12 | E41: =E40*12 | F41: =F40*12 | G41: =G40*12 | H41: =H40*12 | I41: =I40*12 | J41: =J40*12 | ... CH41: =CH40*12
A42: Impostos sobre a receita | C42: =C39*IF(SUMIFS($C$39:$CH$39,$C$2:$CH$2,">="&(C2-12),$C$2:$CH$2,"<"&C2)>4800000,Premissas!$F$10,Premissas!$F$9) | D42: =D39*IF(SUMIFS($C$39:$CH$39,$C$2:$CH$2,">="&(D2-12),$C$2:$CH$2,"<"&D2)>4800000,Premissas!$F$10,Premissas!$F$9) | E42: =E39*IF(SUMIFS($C$39:$CH$39,$C$2:$CH$2,">="&(E2-12),$C$2:$CH$2,"<"&E2)>4800000,Premissas!$F$10,Premissas!$F$9) | F42: =F39*IF(SUMIFS($C$39:$CH$39,$C$2:$CH$2,">="&(F2-12),$C$2:$CH$2,"<"&F2)>4800000,Premissas!$F$10,Premissas!$F$9) | G42: =G39*IF(SUMIFS($C$39:$CH$39,$C$2:$CH$2,">="&(G2-12),$C$2:$CH$2,"<"&G2)>4800000,Premissas!$F$10,Premissas!$F$9) | H42: =H39*IF(SUMIFS($C$39:$CH$39,$C$2:$CH$2,">="&(H2-12),$C$2:$CH$2,"<"&H2)>4800000,Premissas!$F$10,Premissas!$F$9) | I42: =I39*IF(SUMIFS($C$39:$CH$39,$C$2:$CH$2,">="&(I2-12),$C$2:$CH$2,"<"&I2)>4800000,Premissas!$F$10,Premissas!$F$9) | J42: =J39*IF(SUMIFS($C$39:$CH$39,$C$2:$CH$2,">="&(J2-12),$C$2:$CH$2,"<"&J2)>4800000,Premissas!$F$10,Premissas!$F$9) | ... CH42: =CH39*IF(SUMIFS($C$39:$CH$39,$C$2:$CH$2,">="&(CH2-12),$C$2:$CH$2,"<"&CH2)>4800000,Premissas!$F$10,Premissas!$F$9)
A43: Meios de pagamento | C43: =C39*Premissas!$F$11 | D43: =D39*Premissas!$F$11 | E43: =E39*Premissas!$F$11 | F43: =F39*Premissas!$F$11 | G43: =G39*Premissas!$F$11 | H43: =H39*Premissas!$F$11 | I43: =I39*Premissas!$F$11 | J43: =J39*Premissas!$F$11 | ... CH43: =CH39*Premissas!$F$11
A44: Receita líquida | C44: =C39-C42-C43 | D44: =D39-D42-D43 | E44: =E39-E42-E43 | F44: =F39-F42-F43 | G44: =G39-G42-G43 | H44: =H39-H42-H43 | I44: =I39-I42-I43 | J44: =J39-J42-J43 | ... CH44: =CH39-CH42-CH43
A46: Custo do serviço
A47: Custo direto (IA, ferramentas, hospedagem, implantação) | C47: =C18*Premissas!$F$78+C24*Premissas!$F$84+C30*Premissas!$F$91+C12*Premissas!$F$106 | D47: =D18*Premissas!$F$78+D24*Premissas!$F$84+D30*Premissas!$F$91+D12*Premissas!$F$106 | E47: =E18*Premissas!$F$78+E24*Premissas!$F$84+E30*Premissas!$F$91+E12*Premissas!$F$106 | F47: =F18*Premissas!$F$78+F24*Premissas!$F$84+F30*Premissas!$F$91+F12*Premissas!$F$106 | G47: =G18*Premissas!$F$78+G24*Premissas!$F$84+G30*Premissas!$F$91+G12*Premissas!$F$106 | H47: =H18*Premissas!$F$78+H24*Premissas!$F$84+H30*Premissas!$F$91+H12*Premissas!$F$106 | I47: =I18*Premissas!$F$78+I24*Premissas!$F$84+I30*Premissas!$F$91+I12*Premissas!$F$106 | J47: =J18*Premissas!$F$78+J24*Premissas!$F$84+J30*Premissas!$F$91+J12*Premissas!$F$106 | ... CH47: =CH18*Premissas!$F$78+CH24*Premissas!$F$84+CH30*Premissas!$F$91+CH12*Premissas!$F$106
A48: Especialistas humanos nas contas (pessoas) | C48: =C18/Premissas!$F$79+C24/Premissas!$F$85+C30/Premissas!$F$92 | D48: =D18/Premissas!$F$79+D24/Premissas!$F$85+D30/Premissas!$F$92 | E48: =E18/Premissas!$F$79+E24/Premissas!$F$85+E30/Premissas!$F$92 | F48: =F18/Premissas!$F$79+F24/Premissas!$F$85+F30/Premissas!$F$92 | G48: =G18/Premissas!$F$79+G24/Premissas!$F$85+G30/Premissas!$F$92 | H48: =H18/Premissas!$F$79+H24/Premissas!$F$85+H30/Premissas!$F$92 | I48: =I18/Premissas!$F$79+I24/Premissas!$F$85+I30/Premissas!$F$92 | J48: =J18/Premissas!$F$79+J24/Premissas!$F$85+J30/Premissas!$F$92 | ... CH48: =CH18/Premissas!$F$79+CH24/Premissas!$F$85+CH30/Premissas!$F$92
A49: Custo dos especialistas | C49: =C48*Premissas!$F$72 | D49: =D48*Premissas!$F$72 | E49: =E48*Premissas!$F$72 | F49: =F48*Premissas!$F$72 | G49: =G48*Premissas!$F$72 | H49: =H48*Premissas!$F$72 | I49: =I48*Premissas!$F$72 | J49: =J48*Premissas!$F$72 | ... CH49: =CH48*Premissas!$F$72
A50: Custo do serviço total | C50: =C47+C49 | D50: =D47+D49 | E50: =E47+E49 | F50: =F47+F49 | G50: =G47+G49 | H50: =H47+H49 | I50: =I47+I49 | J50: =J47+J49 | ... CH50: =CH47+CH49
A51: Lucro bruto | C51: =C44-C50 | D51: =D44-D50 | E51: =E44-E50 | F51: =F44-F50 | G51: =G44-G50 | H51: =H44-H50 | I51: =I44-I50 | J51: =J44-J50 | ... CH51: =CH44-CH50
A52: Margem bruta (sobre a receita líquida) | C52: =IF(C44>0,C51/C44,0) | D52: =IF(D44>0,D51/D44,0) | E52: =IF(E44>0,E51/E44,0) | F52: =IF(F44>0,F51/F44,0) | G52: =IF(G44>0,G51/G44,0) | H52: =IF(H44>0,H51/H44,0) | I52: =IF(I44>0,I51/I44,0) | J52: =IF(J44>0,J51/J44,0) | ... CH52: =IF(CH44>0,CH51/CH44,0)
A54: Despesas operacionais
A55: Produto, engenharia e IA | C55: =INDEX(Premissas!$C$24:$I$24,1,C3)*Premissas!$F$32 | D55: =INDEX(Premissas!$C$24:$I$24,1,D3)*Premissas!$F$32 | E55: =INDEX(Premissas!$C$24:$I$24,1,E3)*Premissas!$F$32 | F55: =INDEX(Premissas!$C$24:$I$24,1,F3)*Premissas!$F$32 | G55: =INDEX(Premissas!$C$24:$I$24,1,G3)*Premissas!$F$32 | H55: =INDEX(Premissas!$C$24:$I$24,1,H3)*Premissas!$F$32 | I55: =INDEX(Premissas!$C$24:$I$24,1,I3)*Premissas!$F$32 | J55: =INDEX(Premissas!$C$24:$I$24,1,J3)*Premissas!$F$32 | ... CH55: =INDEX(Premissas!$C$24:$I$24,1,CH3)*Premissas!$F$32
A56: Equipe de vendas e marketing | C56: =INDEX(Premissas!$C$28:$I$28,1,C3)*Premissas!$F$33 | D56: =INDEX(Premissas!$C$28:$I$28,1,D3)*Premissas!$F$33 | E56: =INDEX(Premissas!$C$28:$I$28,1,E3)*Premissas!$F$33 | F56: =INDEX(Premissas!$C$28:$I$28,1,F3)*Premissas!$F$33 | G56: =INDEX(Premissas!$C$28:$I$28,1,G3)*Premissas!$F$33 | H56: =INDEX(Premissas!$C$28:$I$28,1,H3)*Premissas!$F$33 | I56: =INDEX(Premissas!$C$28:$I$28,1,I3)*Premissas!$F$33 | J56: =INDEX(Premissas!$C$28:$I$28,1,J3)*Premissas!$F$33 | ... CH56: =INDEX(Premissas!$C$28:$I$28,1,CH3)*Premissas!$F$33
A57: Administrativo, jurídico e conformidade | C57: =INDEX(Premissas!$C$25:$I$25,1,C3)*Premissas!$F$34 | D57: =INDEX(Premissas!$C$25:$I$25,1,D3)*Premissas!$F$34 | E57: =INDEX(Premissas!$C$25:$I$25,1,E3)*Premissas!$F$34 | F57: =INDEX(Premissas!$C$25:$I$25,1,F3)*Premissas!$F$34 | G57: =INDEX(Premissas!$C$25:$I$25,1,G3)*Premissas!$F$34 | H57: =INDEX(Premissas!$C$25:$I$25,1,H3)*Premissas!$F$34 | I57: =INDEX(Premissas!$C$25:$I$25,1,I3)*Premissas!$F$34 | J57: =INDEX(Premissas!$C$25:$I$25,1,J3)*Premissas!$F$34 | ... CH57: =INDEX(Premissas!$C$25:$I$25,1,CH3)*Premissas!$F$34
A58: Pró-labore dos fundadores | C58: =INDEX(Premissas!$C$26:$I$26,1,C3)*Premissas!$F$35 | D58: =INDEX(Premissas!$C$26:$I$26,1,D3)*Premissas!$F$35 | E58: =INDEX(Premissas!$C$26:$I$26,1,E3)*Premissas!$F$35 | F58: =INDEX(Premissas!$C$26:$I$26,1,F3)*Premissas!$F$35 | G58: =INDEX(Premissas!$C$26:$I$26,1,G3)*Premissas!$F$35 | H58: =INDEX(Premissas!$C$26:$I$26,1,H3)*Premissas!$F$35 | I58: =INDEX(Premissas!$C$26:$I$26,1,I3)*Premissas!$F$35 | J58: =INDEX(Premissas!$C$26:$I$26,1,J3)*Premissas!$F$35 | ... CH58: =INDEX(Premissas!$C$26:$I$26,1,CH3)*Premissas!$F$35
A59: Mídia paga | C59: =C8 | D59: =D8 | E59: =E8 | F59: =F8 | G59: =G8 | H59: =H8 | I59: =I8 | J59: =J8 | ... CH59: =CH8
A60: Comissões de parceria e meses grátis de indicação | C60: =C10*Premissas!$F$71+C11*Premissas!$F$108 | D60: =D10*Premissas!$F$71+D11*Premissas!$F$108 | E60: =E10*Premissas!$F$71+E11*Premissas!$F$108 | F60: =F10*Premissas!$F$71+F11*Premissas!$F$108 | G60: =G10*Premissas!$F$71+G11*Premissas!$F$108 | H60: =H10*Premissas!$F$71+H11*Premissas!$F$108 | I60: =I10*Premissas!$F$71+I11*Premissas!$F$108 | J60: =J10*Premissas!$F$71+J11*Premissas!$F$108 | ... CH60: =CH10*Premissas!$F$71+CH11*Premissas!$F$108
A61: Marca e eventos | C61: =C8*Premissas!$F$38 | D61: =D8*Premissas!$F$38 | E61: =E8*Premissas!$F$38 | F61: =F8*Premissas!$F$38 | G61: =G8*Premissas!$F$38 | H61: =H8*Premissas!$F$38 | I61: =I8*Premissas!$F$38 | J61: =J8*Premissas!$F$38 | ... CH61: =CH8*Premissas!$F$38
A62: Outras despesas | C62: =Premissas!$F$36+C39*Premissas!$F$37 | D62: =Premissas!$F$36+D39*Premissas!$F$37 | E62: =Premissas!$F$36+E39*Premissas!$F$37 | F62: =Premissas!$F$36+F39*Premissas!$F$37 | G62: =Premissas!$F$36+G39*Premissas!$F$37 | H62: =Premissas!$F$36+H39*Premissas!$F$37 | I62: =Premissas!$F$36+I39*Premissas!$F$37 | J62: =Premissas!$F$36+J39*Premissas!$F$37 | ... CH62: =Premissas!$F$36+CH39*Premissas!$F$37
A63: Custo único da expansão | C63: =IF(C2=Premissas!$F$13,Premissas!$F$16,0) | D63: =IF(D2=Premissas!$F$13,Premissas!$F$16,0) | E63: =IF(E2=Premissas!$F$13,Premissas!$F$16,0) | F63: =IF(F2=Premissas!$F$13,Premissas!$F$16,0) | G63: =IF(G2=Premissas!$F$13,Premissas!$F$16,0) | H63: =IF(H2=Premissas!$F$13,Premissas!$F$16,0) | I63: =IF(I2=Premissas!$F$13,Premissas!$F$16,0) | J63: =IF(J2=Premissas!$F$13,Premissas!$F$16,0) | ... CH63: =IF(CH2=Premissas!$F$13,Premissas!$F$16,0)
A64: Despesas operacionais totais | C64: =C55+C56+C57+C58+C59+C60+C61+C62+C63 | D64: =D55+D56+D57+D58+D59+D60+D61+D62+D63 | E64: =E55+E56+E57+E58+E59+E60+E61+E62+E63 | F64: =F55+F56+F57+F58+F59+F60+F61+F62+F63 | G64: =G55+G56+G57+G58+G59+G60+G61+G62+G63 | H64: =H55+H56+H57+H58+H59+H60+H61+H62+H63 | I64: =I55+I56+I57+I58+I59+I60+I61+I62+I63 | J64: =J55+J56+J57+J58+J59+J60+J61+J62+J63 | ... CH64: =CH55+CH56+CH57+CH58+CH59+CH60+CH61+CH62+CH63
A66: Resultado e caixa
A67: EBITDA | C67: =C51-C64 | D67: =D51-D64 | E67: =E51-E64 | F67: =F51-F64 | G67: =G51-G64 | H67: =H51-H64 | I67: =I51-I64 | J67: =J51-J64 | ... CH67: =CH51-CH64
A68: Caixa acumulado sem captação | C68: =0+C67 | D68: =C68+D67 | E68: =D68+E67 | F68: =E68+F67 | G68: =F68+G67 | H68: =G68+H67 | I68: =H68+I67 | J68: =I68+J67 | K68: =J68+K67 | ... CH68: =CG68+CH67
A69: Mês de equilíbrio candidato (EBITDA não volta a ficar negativo) | C69: =IF(COUNTIF(C67:$CH$67,"<0")=0,C2,"") | D69: =IF(COUNTIF(D67:$CH$67,"<0")=0,D2,"") | E69: =IF(COUNTIF(E67:$CH$67,"<0")=0,E2,"") | F69: =IF(COUNTIF(F67:$CH$67,"<0")=0,F2,"") | G69: =IF(COUNTIF(G67:$CH$67,"<0")=0,G2,"") | H69: =IF(COUNTIF(H67:$CH$67,"<0")=0,H2,"") | I69: =IF(COUNTIF(I67:$CH$67,"<0")=0,I2,"") | J69: =IF(COUNTIF(J67:$CH$67,"<0")=0,J2,"") | ... CH69: =IF(COUNTIF(CH67:$CH$67,"<0")=0,CH2,"")
A70: Mês em que a receita anualizada passa do critério H7 | C70: =IF(AND(C41>=Premissas!$F$100,0<Premissas!$F$100),C2,"") | D70: =IF(AND(D41>=Premissas!$F$100,C41<Premissas!$F$100),D2,"") | E70: =IF(AND(E41>=Premissas!$F$100,D41<Premissas!$F$100),E2,"") | F70: =IF(AND(F41>=Premissas!$F$100,E41<Premissas!$F$100),F2,"") | G70: =IF(AND(G41>=Premissas!$F$100,F41<Premissas!$F$100),G2,"") | H70: =IF(AND(H41>=Premissas!$F$100,G41<Premissas!$F$100),H2,"") | I70: =IF(AND(I41>=Premissas!$F$100,H41<Premissas!$F$100),I2,"") | J70: =IF(AND(J41>=Premissas!$F$100,I41<Premissas!$F$100),J2,"") | K70: =IF(AND(K41>=Premissas!$F$100,J41<Premissas!$F$100),K2,"") | ... CH70: =IF(AND(CH41>=Premissas!$F$100,CG41<Premissas!$F$100),CH2,"")
A71: Pessoas no total (fundadores, equipe e especialistas) | C71: =Premissas!$F$35+INDEX(Premissas!$C$24:$I$24,1,C3)+INDEX(Premissas!$C$28:$I$28,1,C3)+INDEX(Premissas!$C$25:$I$25,1,C3)+C48 | D71: =Premissas!$F$35+INDEX(Premissas!$C$24:$I$24,1,D3)+INDEX(Premissas!$C$28:$I$28,1,D3)+INDEX(Premissas!$C$25:$I$25,1,D3)+D48 | E71: =Premissas!$F$35+INDEX(Premissas!$C$24:$I$24,1,E3)+INDEX(Premissas!$C$28:$I$28,1,E3)+INDEX(Premissas!$C$25:$I$25,1,E3)+E48 | F71: =Premissas!$F$35+INDEX(Premissas!$C$24:$I$24,1,F3)+INDEX(Premissas!$C$28:$I$28,1,F3)+INDEX(Premissas!$C$25:$I$25,1,F3)+F48 | G71: =Premissas!$F$35+INDEX(Premissas!$C$24:$I$24,1,G3)+INDEX(Premissas!$C$28:$I$28,1,G3)+INDEX(Premissas!$C$25:$I$25,1,G3)+G48 | H71: =Premissas!$F$35+INDEX(Premissas!$C$24:$I$24,1,H3)+INDEX(Premissas!$C$28:$I$28,1,H3)+INDEX(Premissas!$C$25:$I$25,1,H3)+H48 | I71: =Premissas!$F$35+INDEX(Premissas!$C$24:$I$24,1,I3)+INDEX(Premissas!$C$28:$I$28,1,I3)+INDEX(Premissas!$C$25:$I$25,1,I3)+I48 | J71: =Premissas!$F$35+INDEX(Premissas!$C$24:$I$24,1,J3)+INDEX(Premissas!$C$28:$I$28,1,J3)+INDEX(Premissas!$C$25:$I$25,1,J3)+J48 | ... CH71: =Premissas!$F$35+INDEX(Premissas!$C$24:$I$24,1,CH3)+INDEX(Premissas!$C$28:$I$28,1,CH3)+INDEX(Premissas!$C$25:$I$25,1,CH3)+CH48

Sheet Cenarios
A1: Cenários e testes de estresse (valores gerados por sensibilidade_v2.py)
A3: Modelo A: software por assinatura
A4: Indicador | B4: Conservador | C4: Base | D4: Otimista
A5: Receita recorrente anualizada no ano 5 | B5: 9425293.1 | C5: 20911682 | D5: 50946261
A6: Receita recorrente anualizada no ano 7 | B6: 16259058 | C6: 37026396 | D6: 97798177
A7: Mês de equilíbrio (EBITDA positivo daí em diante) | B7: não chega | C7: 65 | D7: 31
A8: Capital necessário (pior caixa acumulado) | B8: 44020986 | C8: 14551737 | D8: 4842978.2
A9: Margem bruta no ano 5 | B9: 0.75429414 | C9: 0.82050529 | D9: 0.85712085
A10: LTV/CAC do plano principal (Consultório / Agenda Cheia), mídia paga | B10: 1.2328071 | C10: 2.1461778 | D10: 4.4839917
A11: LTV/CAC ponderado pelo mix de novos clientes (mídia paga) | B11: 1.3756812 | C11: 2.5912237 | D11: 6.65219
A12: Recuperação do CAC do plano principal (meses) | B12: 12.060811 | C12: 8.7808476 | D12: 5.7418576
A13: Mês em que a receita anualizada chega a R$ 50 mi | B13: não chega | C13: não chega | D13: 60
A14: Participação no mercado nesse mês | D14: 0.010031052
A15: Receita por pessoa no ano 5 | B15: 167417.66 | C15: 334474.96 | D15: 618215.34
A16: Clientes ativos no ano 5 | B16: 948.55358 | C16: 2126.4989 | D16: 4564.1287
A18: Modelo B: agência operada por agentes
A19: Indicador | B19: Conservador | C19: Base | D19: Otimista
A20: Receita recorrente anualizada no ano 5 | B20: 14804181 | C20: 34605229 | D20: 77481260
A21: Receita recorrente anualizada no ano 7 | B21: 25174222 | C21: 60631763 | D21: 1.5022428e+08
A22: Mês de equilíbrio (EBITDA positivo daí em diante) | B22: não chega | C22: 56 | D22: 29
A23: Capital necessário (pior caixa acumulado) | B23: 55143316 | C23: 12489561 | D23: 4327759.4
A24: Margem bruta no ano 5 | B24: 0.40297964 | C24: 0.60280085 | D24: 0.71874857
A25: LTV/CAC do plano principal (Consultório / Agenda Cheia), mídia paga | B25: 1.1074872 | C25: 2.8790667 | D25: 7.1815333
A26: LTV/CAC ponderado pelo mix de novos clientes (mídia paga) | B26: 1.0079462 | C26: 2.6539549 | D26: 6.6889438
A27: Recuperação do CAC do plano principal (meses) | B27: 14.765475 | C27: 7.2935641 | D27: 4.7868419
A28: Mês em que a receita anualizada chega a R$ 50 mi | B28: não chega | C28: 75 | D28: 49
A29: Participação no mercado nesse mês | C29: 0.0082530084 | D29: 0.0056289594
A30: Receita por pessoa no ano 5 | B30: 162593.26 | C30: 301399.11 | D30: 478291.89
A31: Clientes ativos no ano 5 | B31: 792.82873 | C31: 1855.9642 | D31: 3914.079
A33: Testes de estresse do Modelo B (cenário base, uma aposta por vez)
A34: Teste | B34: Receita recorrente anualizada no ano 5 | C34: Receita recorrente anualizada no ano 7 | D34: Mês de equilíbrio (EBITDA positivo daí em diante) | E34: Capital necessário (pior caixa acumulado) | F34: Margem bruta no ano 5 | G34: LTV/CAC do plano principal (Consultório / Agenda Cheia), mídia paga | H34: LTV/CAC ponderado pelo mix de novos clientes (mídia paga) | I34: Recuperação do CAC do plano principal (meses) | J34: Mês em que a receita anualizada chega a R$ 50 mi | K34: Participação no mercado nesse mês | L34: Receita por pessoa no ano 5 | M34: Clientes ativos no ano 5
A35: B se as apostas se confirmarem (churn de agência, 40 a 70 contas por especialista, CAC R$ 5.500) | B35: 47196517 | C35: 88530927 | D35: 41 | E35: 7937541.8 | F35: 0.66108754 | G35: 6.0680606 | H35: 5.0463871 | I35: 5.6437462 | J35: 62 | K35: 0.008451415 | L35: 394735.13 | M35: 2590.3452
A36: B com cobrança de R$ 30 por consulta (só com parecer jurídico favorável) | B36: 38907850 | C36: 68322314 | D36: 51 | E36: 9358328.5 | F36: 0.64387192 | G36: 3.6239897 | H36: 3.2126472 | I36: 5.7354797 | J36: 69 | K36: 0.0072195857 | L36: 336158.47 | M36: 1855.9642
A37: B com as apostas confirmadas e cobrança por consulta (o base da v2) | B37: 52884368 | C37: 99344534 | D37: 39 | E37: 6532844.1 | F37: 0.69556431 | G37: 7.5353333 | H37: 5.9834409 | I37: 4.5206842 | J37: 59 | K37: 0.007637957 | L37: 439438.14 | M37: 2590.3452
A38: B com o dobro de contas por especialista, sem mudar o resto | B38: 34605229 | C38: 60631763 | D38: 51 | E38: 9248513.8 | F38: 0.71353444 | G38: 3.3918872 | H38: 3.1411344 | I38: 6.144461 | J38: 75 | K38: 0.0082530084 | L38: 408563.86 | M38: 1855.9642
A39: B com churn de agência com contrato, sem mudar o resto | B39: 43360493 | C39: 81127016 | D39: 51 | E39: 9925656.4 | F39: 0.60395094 | G39: 4.7071624 | H39: 3.9026571 | I39: 7.2935641 | J39: 65 | K39: 0.0085417363 | L39: 323042.43 | M39: 2379.723
A40: Sem expansão para dentistas | B40: 20736220 | C40: 35830707 | D40: 81 | E40: 19276295 | F40: 0.60309218 | G40: 2.8790667 | H40: 2.6539549 | I40: 7.2935641 | J40: não chega | L40: 230177.78 | M40: 1110.3203

Sheet Sensibilidade
A1: Sensibilidade no cenário base: quanto cada premissa mexe no resultado (valores gerados por script)
A3: Modelo A
A4: Premissa (ordenada pelo impacto no capital e na receita) | B4: Valor baixo | C4: Valor alto | D4: ARR ano 7 (baixo) | E4: ARR ano 7 (alto) | F4: Diferença no ARR | G4: Capital necessário (baixo) | H4: Capital necessário (alto) | I4: LTV/CAC (baixo / alto)
A5: CAC na mídia paga | B5: 6000 | C5: 3000 | D5: 31516385 | E5: 48046418 | F5: 16530033 | G5: 19630810 | H5: 9444707.4 | I5: 1.6x / 3.2x
A6: Preço do Consultório | B6: 497 | C6: 897 | D6: 33047651 | E6: 41005141 | F6: 7957489.3 | G6: 19124212 | H6: 11626535 | I6: 1.5x / 2.8x
A7: Parcerias (multiplicador) | B7: 0.6 | C7: 1.3 | D7: 31031855 | E7: 41522302 | F7: 10490446 | G7: 19021797 | H7: 12358774 | I7: 2.1x / 2.1x
A8: Churn do Consultório | B8: 0.07 | C8: 0.04 | D8: 34413704 | E8: 40791717 | F8: 6378013.5 | G8: 16213739 | H8: 12967525 | I8: 1.7x / 2.9x
A9: Indicação (% da base por mês) | B9: 0.005 | C9: 0.015 | D9: 34559955 | E9: 39821819 | F9: 5261864.1 | G9: 15737540 | H9: 13450833 | I9: 2.1x / 2.1x
A10: Churn do Essencial | B10: 0.09 | C10: 0.055 | D10: 35924257 | E10: 38211599 | F10: 2287342.1 | G10: 15226253 | H10: 13933188 | I10: 2.1x / 2.1x
A11: Custo direto do Consultório | B11: 80 | C11: 30 | D11: 37026396 | E11: 37026396 | F11: 0 | G11: 15303496 | H11: 14066164 | I11: 2.0x / 2.2x
A12: Base: ARR ano 7 = R$ 37.026.396; capital necessário = R$ 14.551.737
A14: Modelo B
A15: Premissa (ordenada pelo impacto no capital e na receita) | B15: Valor baixo | C15: Valor alto | D15: ARR ano 7 (baixo) | E15: ARR ano 7 (alto) | F15: Diferença no ARR | G15: Capital necessário (baixo) | H15: Capital necessário (alto) | I15: LTV/CAC (baixo / alto)
A16: Preço da Agenda Cheia | B16: 1290 | C16: 2290 | D16: 52851815 | E16: 68411710 | F16: 15559896 | G16: 19693977 | H16: 9143550.1 | I16: 1.6x / 4.1x
A17: CAC na mídia paga | B17: 9000 | C17: 5000 | D17: 52131039 | E17: 69812544 | F17: 17681505 | G17: 16346275 | H17: 9864383 | I17: 2.1x / 3.7x
A18: Churn da Agenda Cheia | B18: 0.065 | C18: 0.03 | D18: 55298076 | E18: 71845204 | F18: 16547128 | G18: 13765013 | H18: 10810516 | I18: 2.2x / 4.7x
A19: Preço por consulta atribuída | B19: 0 | C19: 30 | D19: 60631763 | E19: 68322314 | F19: 7690551.2 | G19: 12489561 | H19: 9358328.5 | I19: 2.9x / 3.6x
A20: Contas por especialista (Agenda Cheia) | B20: 20 | C20: 50 | D20: 60631763 | E20: 60631763 | F20: 0 | G20: 14820731 | H20: 11044277 | I20: 2.4x / 3.3x
A21: Churn da Presença | B21: 0.07 | C21: 0.035 | D21: 56686722 | E21: 68817425 | F21: 12130703 | G21: 13400854 | H21: 11131736 | I21: 2.9x / 2.9x
A22: Custo dos agentes por conta (Agenda Cheia) | B22: 400 | C22: 150 | D22: 60631763 | E22: 60631763 | F22: 0 | G22: 15069945 | H22: 11708227 | I22: 2.3x / 3.1x
A23: Contas por especialista (Presença) | B23: 35 | C23: 90 | D23: 60631763 | E23: 60631763 | F23: 0 | G23: 13935983 | H23: 11155129 | I23: 2.9x / 2.9x
A24: Indicação (% da base por mês) | B24: 0.005 | C24: 0.015 | D24: 56314643 | E24: 65561171 | F24: 9246527.5 | G24: 13286448 | H24: 11731195 | I24: 2.9x / 2.9x
A25: Base: ARR ano 7 = R$ 60.631.763; capital necessário = R$ 12.489.561
