Workbook

Sheet Premissas
A1: Jalecon: premissas do modelo financeiro
A2: Legenda: texto azul = premissa editável · preto = fórmula · verde = vínculo com outra aba · fundo amarelo = premissa-chave a validar. Valores em R$ nominais, mês 1 = jan/2027.
A4: Geral
A5: Câmbio (R$ por US$) | B5: 5.4 | I5: Premissa do grupo; ajustar à cotação do dia da banca.
A6: Carga tributária no Simples Nacional (% da receita) | B6: 0.11 | I6: Alíquota efetiva média estimada para SaaS no Anexo III/V; confirmar com contador.
A7: Carga tributária após sair do Simples (% da receita) | B7: 0.1633 | I7: Aproximação de Lucro Presumido (PIS/COFINS 3,65% + ISS ~2,9% + IRPJ/CSLL presumidos ~9,8%); confirmar com contador.
A8: Limite anual do Simples Nacional (R$) | B8: 4800000 | I8: Lei Complementar 123/2006.
A9: Taxa de meio de pagamento (% da receita) | B9: 0.035 | I9: Média de gateways de cartão/Pix recorrente.
A10: Encargos e benefícios CLT (% do salário) | B10: 0.7 | I10: Média de mercado para CLT no Brasil.
A11: Encargos sobre pró-labore (% do pró-labore) | B11: 0.2 | I11: INSS patronal no pró-labore (fora do Simples Anexo III).
A12: % de clientes no plano anual | B12: 0.3 | I12: Premissa; validar na pré-venda.
A13: Desconto do plano anual | B13: 0.15 | I13: Premissa de política comercial.
A14: Aporte pré-seed no mês 1 (R$) | B14: 3300000 | I14: Valor a decidir após o modelo; ver aba Resumo (necessidade de caixa).
A16: Planos
A17: Item | B17: Essencial | C17: Consultório | D17: Autoridade | E17: Clínica | I17: Nota
A18: Preço mensal (R$) | B18: 297 | C18: 697 | D18: 1497 | E18: 3900 | I18: Ancorado entre geradores de post (R$ 50 a 600) e agências (R$ 1,5 mil a 12 mil). Validar com Van Westendorp.
A19: Taxa de implantação média por novo cliente (R$) | B19: 0 | C19: 490 | D19: 990 | E19: 2900 | I19: Marca + site + diagnóstico completo; isenta no plano anual (já refletido na média).
A20: Churn mensal no ano 1 (cenário base) | B20: 0.05 | C20: 0.03 | D20: 0.025 | E20: 0.02 | I20: SaaS para pequenos negócios tem mediana perto de 3,5%/mês; planos maiores retêm mais.
A21: Custo de IA por conta/mês (US$) | B21: 4 | C21: 9 | D21: 18 | E21: 45 | I21: Estimativa: ~0,6 a 1,5 milhão de tokens/mês por conta com Claude Sonnet 5.5 (US$ 2/10 por milhão) e cache; inclui imagens.
A22: Infra, APIs e hospedagem por conta/mês (R$) | B22: 8 | C22: 12 | D22: 18 | E22: 40 | I22: Hospedagem de site, banco de dados, APIs de publicação e WhatsApp.
A23: Contas por gestor de conta humano | B23: 0 | C23: 0 | D23: 40 | E23: 20 | I23: Só planos com revisão humana dedicada. 0 = sem gestor.
A24: Salário mensal do gestor de conta (R$) | B24: 7000
A25: Melhoria anual do churn (redução relativa por ano) | B25: 0.08 | I25: Produto e sucesso do cliente amadurecem; aplicado a partir do ano 2.
A27: Mix de novos clientes por plano
A28: Ano | B28: Essencial | C28: Consultório | D28: Autoridade | E28: Clínica | F28: Soma
A29: Ano 1 | B29: 0.4 | C29: 0.5 | D29: 0.1 | E29: 0 | F29: =SUM(B29:E29) -> 1
A30: Ano 2 | B30: 0.35 | C30: 0.5 | D30: 0.13 | E30: 0.02 | F30: =SUM(B30:E30) -> 1
A31: Ano 3 | B31: 0.3 | C31: 0.5 | D31: 0.15 | E31: 0.05 | F31: =SUM(B31:E31) -> 1
A32: Ano 4 | B32: 0.28 | C32: 0.5 | D32: 0.16 | E32: 0.06 | F32: =SUM(B32:E32) -> 1
A33: Ano 5 | B33: 0.25 | C33: 0.5 | D33: 0.18 | E33: 0.07 | F33: =SUM(B33:E33) -> 1
A35: Aquisição e receitas adicionais (cenário base)
A36: Item | B36: Ano 1 | C36: Ano 2 | D36: Ano 3 | E36: Ano 4 | F36: Ano 5 | H36: Nota
A37: Mídia paga e inbound: orçamento mensal (R$) | B37: 25000 | C37: 70000 | D37: 150000 | E37: 240000 | F37: 320000 | H37: Meta, Google, conteúdo, ferramentas de captação.
A38: Parcerias: novos clientes por mês | B38: 4 | C38: 12 | D38: 25 | E38: 40 | F38: 55 | H38: Residências, sociedades de especialidade, contadores médicos, coworkings de consultório.
A39: Serviços adicionais (% da receita recorrente) | B39: 0.05 | C39: 0.08 | D39: 0.11 | E39: 0.13 | F39: 0.15 | H39: Check-up de conformidade avulso, gestão de tráfego, ensaio de fotos (comissão), domínio.
A40: CAC de mídia paga no ano 1 (R$ por cliente) | B40: 1800 | H40: Premissa-chave: SaaS para pequenos negócios com venda assistida. Validar com testes de campanha.
A41: Queda anual do CAC (marca, indicação, conteúdo) | B41: 0.07
A42: CAC de mídia paga por ano (R$) | B42: =$B$40 -> 1800 | C42: =B42*(1-$B$41) -> 1674 | D42: =C42*(1-$B$41) -> 1556.82 | E42: =D42*(1-$B$41) -> 1447.8426 | F42: =E42*(1-$B$41) -> 1346.4936
A43: Indicação: novos clientes por mês (% da base ativa) | B43: 0.01
A45: Cenários
A46: Alavanca | B46: Conservador | C46: Base | D46: Otimista | H46: Nota
A47: Multiplicador do CAC | B47: 1.3 | C47: 1 | D47: 0.8 | H47: CAC 30% maior no conservador, 20% menor no otimista.
A48: Multiplicador do churn | B48: 1.3 | C48: 1 | D48: 0.8
A49: Multiplicador de parcerias e indicação | B49: 0.7 | C49: 1 | D49: 1.3
A50: Multiplicador de serviços adicionais | B50: 0.7 | C50: 1 | D50: 1.2
A51: Multiplicador do orçamento de mídia | B51: 0.8 | C51: 1 | D51: 1.15 | H51: No conservador a empresa gasta menos por ter menos caixa.
A52: Rodada seed (R$) | B52: 5000000 | C52: 8000000 | D52: 10000000 | H52: Premissa de captação futura; não é compromisso.
A53: Mês da rodada seed | B53: 20 | C53: 16 | D53: 14
A55: Equipe (custo mensal por pessoa e quadro por ano)
A56: Função | B56: Salário (R$) | C56: Encargos | D56: Ano 1 | E56: Ano 2 | F56: Ano 3 | G56: Ano 4 | H56: Ano 5 | I56: Nota
A57: Engenharia de software | B57: 14000 | C57: =$B$10 -> 0.7 | D57: 2 | E57: 4 | F57: 7 | G57: 10 | H57: 13 | I57: Plataforma, integrações (Meta, Google, WhatsApp, agendas).
A58: Engenharia de IA e dados | B58: 18000 | C58: =$B$10 -> 0.7 | D58: 1 | E58: 2 | F58: 3 | G58: 4 | H58: 5 | I58: Agentes, Guardião, avaliação de qualidade, dados de conversão.
A59: Produto e design | B59: 12000 | C59: =$B$10 -> 0.7 | D59: 1 | E59: 2 | F59: 3 | G59: 4 | H59: 5 | I59: Ano 1: designer de produto; gestão de produto com a fundadora (Mariana).
A60: Marketing e growth | B60: 10000 | C60: =$B$10 -> 0.7 | D60: 0 | E60: 2 | F60: 3 | G60: 5 | H60: 6 | I60: Ano 1 conduzido pelo fundador de marketing (Vitor).
A61: Vendas (inside sales) | B61: 7000 | C61: =$B$10 -> 0.7 | D61: 1 | E61: 3 | F61: 6 | G61: 9 | H61: 12 | I61: Salário fixo; comissão incluída no CAC.
A62: Sucesso do cliente e suporte | B62: 6500 | C62: =$B$10 -> 0.7 | D62: 1 | E62: 2 | F62: 4 | G62: 7 | H62: 10 | I62: Onboarding e suporte geral (gestores de conta dedicados estão no custo do serviço).
A63: Médicos revisores de conteúdo (PJ) | B63: 9000 | C63: 0 | D63: 1 | E63: 1 | F63: 2 | G63: 3 | H63: 4 | I63: Revisão científica por especialidade.
A64: Financeiro e administrativo | B64: 8000 | C64: =$B$10 -> 0.7 | D64: 0 | E64: 1 | F64: 2 | G64: 3 | H64: 4
A65: Fundadores (quantidade) | C65: =$B$11 -> 0.2 | D65: 5 | E65: 5 | F65: 5 | G65: 5 | H65: 5 | I65: Mariana, Vitor, Fabiana, Manuella e Alessandra em tempo integral; Daniela como estagiária/part-time a definir.
A66: Pró-labore mensal por fundador (R$) | D66: 5000 | E66: 10000 | F66: 15000 | G66: 20000 | H66: 22000 | I66: Baixo no ano 1 para preservar caixa; sobe com a receita.
A67: Custo mensal total de pessoal (R$) | D67: =SUMPRODUCT($B$57:$B$64,1+$C$57:$C$64,D57:D64)+D65*D66*(1+$C$65) -> 160550 | E67: =SUMPRODUCT($B$57:$B$64,1+$C$57:$C$64,E57:E64)+E65*E66*(1+$C$65) -> 371600 | F67: =SUMPRODUCT($B$57:$B$64,1+$C$57:$C$64,F57:F64)+F65*F66*(1+$C$65) -> 621400 | G67: =SUMPRODUCT($B$57:$B$64,1+$C$57:$C$64,G57:G64)+G65*G66*(1+$C$65) -> 899250 | H67: =SUMPRODUCT($B$57:$B$64,1+$C$57:$C$64,H57:H64)+H65*H66*(1+$C$65) -> 1142100
A68: Quadro total (pessoas, sem gestores de conta) | D68: =SUM(D57:D64)+D65 -> 12 | E68: =SUM(E57:E64)+E65 -> 22 | F68: =SUM(F57:F64)+F65 -> 35 | G68: =SUM(G57:G64)+G65 -> 50 | H68: =SUM(H57:H64)+H65 -> 64
A70: Outras despesas mensais (R$)
A71: Item | B71: Ano 1 | C71: Ano 2 | D71: Ano 3 | E71: Ano 4 | F71: Ano 5 | H71: Nota
A72: Jurídico e curadoria normativa (advogado de direito médico) | B72: 5000 | C72: 8000 | D72: 12000 | E72: 18000 | F72: 25000 | H72: Mantém a biblioteca do Guardião atualizada.
A73: Marca: eventos, congressos e conteúdo institucional | B73: 2000 | C73: 8000 | D73: 15000 | E73: 25000 | F73: 35000
A74: Ferramentas e software internos | B74: 3000 | C74: 8000 | D74: 15000 | E74: 25000 | F74: 35000
A75: Escritório / coworking | B75: 2000 | C75: 6000 | D75: 15000 | E75: 25000 | F75: 35000
A76: Contabilidade, seguros e outras despesas | B76: 3000 | C76: 5000 | D76: 9000 | E76: 14000 | F76: 20000

Sheet Resumo
A1: Jalecon: resumo anual e comparação de cenários
A2: Todos os valores vêm das abas Modelo_*. Para mudar premissas, edite a aba Premissas.
A4: DRE anual: cenário base (R$)
A5: Linha | B5: Ano 1 (2027) | C5: Ano 2 (2028) | D5: Ano 3 (2029) | E5: Ano 4 (2030) | F5: Ano 5 (2031)
A6: Clientes ativos no fim do ano | B6: =INDEX(Modelo_Base!$C$26:$BJ$26,1*12) -> 185.33502 | C6: =INDEX(Modelo_Base!$C$26:$BJ$26,2*12) -> 709.49457 | D6: =INDEX(Modelo_Base!$C$26:$BJ$26,3*12) -> 1870.4941 | E6: =INDEX(Modelo_Base!$C$26:$BJ$26,4*12) -> 3790.9775 | F6: =INDEX(Modelo_Base!$C$26:$BJ$26,5*12) -> 6465.1074
A7: ARR no fim do ano | B7: =INDEX(Modelo_Base!$C$62:$BJ$62,1*12) -> 1343066.9 | C7: =INDEX(Modelo_Base!$C$62:$BJ$62,2*12) -> 5944061.6 | D7: =INDEX(Modelo_Base!$C$62:$BJ$62,3*12) -> 18263945 | E7: =INDEX(Modelo_Base!$C$62:$BJ$62,4*12) -> 39883663 | F7: =INDEX(Modelo_Base!$C$62:$BJ$62,5*12) -> 72438951
A8: Receita recorrente | B8: =SUMIFS(Modelo_Base!$C$32:$BJ$32,Modelo_Base!$C$4:$BJ$4,1) -> 757819.82 | C8: =SUMIFS(Modelo_Base!$C$32:$BJ$32,Modelo_Base!$C$4:$BJ$4,2) -> 3917805.1 | D8: =SUMIFS(Modelo_Base!$C$32:$BJ$32,Modelo_Base!$C$4:$BJ$4,3) -> 12791921 | E8: =SUMIFS(Modelo_Base!$C$32:$BJ$32,Modelo_Base!$C$4:$BJ$4,4) -> 30231632 | F8: =SUMIFS(Modelo_Base!$C$32:$BJ$32,Modelo_Base!$C$4:$BJ$4,5) -> 57837829
A9: Taxas de implantação | B9: =SUMIFS(Modelo_Base!$C$33:$BJ$33,Modelo_Base!$C$4:$BJ$4,1) -> 77559.353 | C9: =SUMIFS(Modelo_Base!$C$33:$BJ$33,Modelo_Base!$C$4:$BJ$4,2) -> 301445.74 | D9: =SUMIFS(Modelo_Base!$C$33:$BJ$33,Modelo_Base!$C$4:$BJ$4,3) -> 865784.91 | E9: =SUMIFS(Modelo_Base!$C$33:$BJ$33,Modelo_Base!$C$4:$BJ$4,4) -> 1618375.9 | F9: =SUMIFS(Modelo_Base!$C$33:$BJ$33,Modelo_Base!$C$4:$BJ$4,5) -> 2578676
A10: Serviços adicionais | B10: =SUMIFS(Modelo_Base!$C$34:$BJ$34,Modelo_Base!$C$4:$BJ$4,1) -> 37890.991 | C10: =SUMIFS(Modelo_Base!$C$34:$BJ$34,Modelo_Base!$C$4:$BJ$4,2) -> 313424.41 | D10: =SUMIFS(Modelo_Base!$C$34:$BJ$34,Modelo_Base!$C$4:$BJ$4,3) -> 1407111.3 | E10: =SUMIFS(Modelo_Base!$C$34:$BJ$34,Modelo_Base!$C$4:$BJ$4,4) -> 3930112.2 | F10: =SUMIFS(Modelo_Base!$C$34:$BJ$34,Modelo_Base!$C$4:$BJ$4,5) -> 8675674.3
A11: Receita bruta | B11: =SUMIFS(Modelo_Base!$C$35:$BJ$35,Modelo_Base!$C$4:$BJ$4,1) -> 873270.17 | C11: =SUMIFS(Modelo_Base!$C$35:$BJ$35,Modelo_Base!$C$4:$BJ$4,2) -> 4532675.3 | D11: =SUMIFS(Modelo_Base!$C$35:$BJ$35,Modelo_Base!$C$4:$BJ$4,3) -> 15064817 | E11: =SUMIFS(Modelo_Base!$C$35:$BJ$35,Modelo_Base!$C$4:$BJ$4,4) -> 35780120 | F11: =SUMIFS(Modelo_Base!$C$35:$BJ$35,Modelo_Base!$C$4:$BJ$4,5) -> 69092179
A12: (-) Impostos | B12: =SUMIFS(Modelo_Base!$C$36:$BJ$36,Modelo_Base!$C$4:$BJ$4,1) -> -96059.718 | C12: =SUMIFS(Modelo_Base!$C$36:$BJ$36,Modelo_Base!$C$4:$BJ$4,2) -> -498594.28 | D12: =SUMIFS(Modelo_Base!$C$36:$BJ$36,Modelo_Base!$C$4:$BJ$4,3) -> -1657129.9 | E12: =SUMIFS(Modelo_Base!$C$36:$BJ$36,Modelo_Base!$C$4:$BJ$4,4) -> -5842893.6 | F12: =SUMIFS(Modelo_Base!$C$36:$BJ$36,Modelo_Base!$C$4:$BJ$4,5) -> -11282753
A13: Receita líquida | B13: =SUMIFS(Modelo_Base!$C$37:$BJ$37,Modelo_Base!$C$4:$BJ$4,1) -> 777210.45 | C13: =SUMIFS(Modelo_Base!$C$37:$BJ$37,Modelo_Base!$C$4:$BJ$4,2) -> 4034081 | D13: =SUMIFS(Modelo_Base!$C$37:$BJ$37,Modelo_Base!$C$4:$BJ$4,3) -> 13407687 | E13: =SUMIFS(Modelo_Base!$C$37:$BJ$37,Modelo_Base!$C$4:$BJ$4,4) -> 29937227 | F13: =SUMIFS(Modelo_Base!$C$37:$BJ$37,Modelo_Base!$C$4:$BJ$4,5) -> 57809426
A14: (-) Custo do serviço | B14: =SUMIFS(Modelo_Base!$C$43:$BJ$43,Modelo_Base!$C$4:$BJ$4,1) -> -138682.83 | C14: =SUMIFS(Modelo_Base!$C$43:$BJ$43,Modelo_Base!$C$4:$BJ$4,2) -> -776997.86 | D14: =SUMIFS(Modelo_Base!$C$43:$BJ$43,Modelo_Base!$C$4:$BJ$4,3) -> -2731580.3 | E14: =SUMIFS(Modelo_Base!$C$43:$BJ$43,Modelo_Base!$C$4:$BJ$4,4) -> -6702146.5 | F14: =SUMIFS(Modelo_Base!$C$43:$BJ$43,Modelo_Base!$C$4:$BJ$4,5) -> -13180217
A15: Lucro bruto | B15: =SUMIFS(Modelo_Base!$C$44:$BJ$44,Modelo_Base!$C$4:$BJ$4,1) -> 638527.62 | C15: =SUMIFS(Modelo_Base!$C$44:$BJ$44,Modelo_Base!$C$4:$BJ$4,2) -> 3257083.1 | D15: =SUMIFS(Modelo_Base!$C$44:$BJ$44,Modelo_Base!$C$4:$BJ$4,3) -> 10676107 | E15: =SUMIFS(Modelo_Base!$C$44:$BJ$44,Modelo_Base!$C$4:$BJ$4,4) -> 23235080 | F15: =SUMIFS(Modelo_Base!$C$44:$BJ$44,Modelo_Base!$C$4:$BJ$4,5) -> 44629209
A16: Margem bruta | B16: =IFERROR(B15/B13,0) -> 0.82156334 | C16: =IFERROR(C15/C13,0) -> 0.80739161 | D16: =IFERROR(D15/D13,0) -> 0.7962676 | E16: =IFERROR(E15/E13,0) -> 0.77612667 | F16: =IFERROR(F15/F13,0) -> 0.77200574
A17: (-) Pessoal | B17: =SUMIFS(Modelo_Base!$C$47:$BJ$47,Modelo_Base!$C$4:$BJ$4,1) -> -1926600 | C17: =SUMIFS(Modelo_Base!$C$47:$BJ$47,Modelo_Base!$C$4:$BJ$4,2) -> -4459200 | D17: =SUMIFS(Modelo_Base!$C$47:$BJ$47,Modelo_Base!$C$4:$BJ$4,3) -> -7456800 | E17: =SUMIFS(Modelo_Base!$C$47:$BJ$47,Modelo_Base!$C$4:$BJ$4,4) -> -10791000 | F17: =SUMIFS(Modelo_Base!$C$47:$BJ$47,Modelo_Base!$C$4:$BJ$4,5) -> -13705200
A18: (-) Mídia, comissões e marca | B18: =SUMIFS(Modelo_Base!$C$48:$BJ$48,Modelo_Base!$C$4:$BJ$4,1)+SUMIFS(Modelo_Base!$C$49:$BJ$49,Modelo_Base!$C$4:$BJ$4,1)+SUMIFS(Modelo_Base!$C$51:$BJ$51,Modelo_Base!$C$4:$BJ$4,1) -> -337911.08 | C18: =SUMIFS(Modelo_Base!$C$48:$BJ$48,Modelo_Base!$C$4:$BJ$4,2)+SUMIFS(Modelo_Base!$C$49:$BJ$49,Modelo_Base!$C$4:$BJ$4,2)+SUMIFS(Modelo_Base!$C$51:$BJ$51,Modelo_Base!$C$4:$BJ$4,2) -> -986629.2 | D18: =SUMIFS(Modelo_Base!$C$48:$BJ$48,Modelo_Base!$C$4:$BJ$4,3)+SUMIFS(Modelo_Base!$C$49:$BJ$49,Modelo_Base!$C$4:$BJ$4,3)+SUMIFS(Modelo_Base!$C$51:$BJ$51,Modelo_Base!$C$4:$BJ$4,3) -> -2117810.1 | E18: =SUMIFS(Modelo_Base!$C$48:$BJ$48,Modelo_Base!$C$4:$BJ$4,4)+SUMIFS(Modelo_Base!$C$49:$BJ$49,Modelo_Base!$C$4:$BJ$4,4)+SUMIFS(Modelo_Base!$C$51:$BJ$51,Modelo_Base!$C$4:$BJ$4,4) -> -3433710 | F18: =SUMIFS(Modelo_Base!$C$48:$BJ$48,Modelo_Base!$C$4:$BJ$4,5)+SUMIFS(Modelo_Base!$C$49:$BJ$49,Modelo_Base!$C$4:$BJ$4,5)+SUMIFS(Modelo_Base!$C$51:$BJ$51,Modelo_Base!$C$4:$BJ$4,5) -> -4657471.1
A19: (-) Demais despesas | B19: =SUMIFS(Modelo_Base!$C$50:$BJ$50,Modelo_Base!$C$4:$BJ$4,1)+SUMIFS(Modelo_Base!$C$52:$BJ$52,Modelo_Base!$C$4:$BJ$4,1)+SUMIFS(Modelo_Base!$C$53:$BJ$53,Modelo_Base!$C$4:$BJ$4,1)+SUMIFS(Modelo_Base!$C$54:$BJ$54,Modelo_Base!$C$4:$BJ$4,1) -> -156000 | C19: =SUMIFS(Modelo_Base!$C$50:$BJ$50,Modelo_Base!$C$4:$BJ$4,2)+SUMIFS(Modelo_Base!$C$52:$BJ$52,Modelo_Base!$C$4:$BJ$4,2)+SUMIFS(Modelo_Base!$C$53:$BJ$53,Modelo_Base!$C$4:$BJ$4,2)+SUMIFS(Modelo_Base!$C$54:$BJ$54,Modelo_Base!$C$4:$BJ$4,2) -> -324000 | D19: =SUMIFS(Modelo_Base!$C$50:$BJ$50,Modelo_Base!$C$4:$BJ$4,3)+SUMIFS(Modelo_Base!$C$52:$BJ$52,Modelo_Base!$C$4:$BJ$4,3)+SUMIFS(Modelo_Base!$C$53:$BJ$53,Modelo_Base!$C$4:$BJ$4,3)+SUMIFS(Modelo_Base!$C$54:$BJ$54,Modelo_Base!$C$4:$BJ$4,3) -> -612000 | E19: =SUMIFS(Modelo_Base!$C$50:$BJ$50,Modelo_Base!$C$4:$BJ$4,4)+SUMIFS(Modelo_Base!$C$52:$BJ$52,Modelo_Base!$C$4:$BJ$4,4)+SUMIFS(Modelo_Base!$C$53:$BJ$53,Modelo_Base!$C$4:$BJ$4,4)+SUMIFS(Modelo_Base!$C$54:$BJ$54,Modelo_Base!$C$4:$BJ$4,4) -> -984000 | F19: =SUMIFS(Modelo_Base!$C$50:$BJ$50,Modelo_Base!$C$4:$BJ$4,5)+SUMIFS(Modelo_Base!$C$52:$BJ$52,Modelo_Base!$C$4:$BJ$4,5)+SUMIFS(Modelo_Base!$C$53:$BJ$53,Modelo_Base!$C$4:$BJ$4,5)+SUMIFS(Modelo_Base!$C$54:$BJ$54,Modelo_Base!$C$4:$BJ$4,5) -> -1380000
A20: EBITDA | B20: =SUMIFS(Modelo_Base!$C$56:$BJ$56,Modelo_Base!$C$4:$BJ$4,1) -> -1781983.5 | C20: =SUMIFS(Modelo_Base!$C$56:$BJ$56,Modelo_Base!$C$4:$BJ$4,2) -> -2512746.1 | D20: =SUMIFS(Modelo_Base!$C$56:$BJ$56,Modelo_Base!$C$4:$BJ$4,3) -> 489496.87 | E20: =SUMIFS(Modelo_Base!$C$56:$BJ$56,Modelo_Base!$C$4:$BJ$4,4) -> 8026370.2 | F20: =SUMIFS(Modelo_Base!$C$56:$BJ$56,Modelo_Base!$C$4:$BJ$4,5) -> 24886538
A21: Margem EBITDA | B21: =IFERROR(B20/B13,0) -> -2.292794 | C21: =IFERROR(C20/C13,0) -> -0.62287943 | D21: =IFERROR(D20/D13,0) -> 0.036508673 | E21: =IFERROR(E20/E13,0) -> 0.26810667 | F21: =IFERROR(F20/F13,0) -> 0.43049273
A22: Caixa no fim do ano | B22: =INDEX(Modelo_Base!$C$60:$BJ$60,1*12) -> 1518016.5 | C22: =INDEX(Modelo_Base!$C$60:$BJ$60,2*12) -> 7005270.5 | D22: =INDEX(Modelo_Base!$C$60:$BJ$60,3*12) -> 7494767.3 | E22: =INDEX(Modelo_Base!$C$60:$BJ$60,4*12) -> 15521138 | F22: =INDEX(Modelo_Base!$C$60:$BJ$60,5*12) -> 40407675
A23: Quadro de pessoas (sem gestores de conta) | B23: =INDEX(Premissas!$D$68:$H$68,1) -> 12 | C23: =INDEX(Premissas!$D$68:$H$68,2) -> 22 | D23: =INDEX(Premissas!$D$68:$H$68,3) -> 35 | E23: =INDEX(Premissas!$D$68:$H$68,4) -> 50 | F23: =INDEX(Premissas!$D$68:$H$68,5) -> 64
A25: Comparação de cenários
A26: Indicador | B26: Conservador | C26: Base | D26: Otimista
A27: Clientes ativos no fim do ano 3 | B27: =INDEX(Modelo_Conservador!$C$26:$BJ$26,3*12) -> 1058.8075 | C27: =INDEX(Modelo_Base!$C$26:$BJ$26,3*12) -> 1870.4941 | D27: =INDEX(Modelo_Otimista!$C$26:$BJ$26,3*12) -> 2882.8485
A28: Clientes ativos no fim do ano 5 | B28: =INDEX(Modelo_Conservador!$C$26:$BJ$26,5*12) -> 3529.566 | C28: =INDEX(Modelo_Base!$C$26:$BJ$26,5*12) -> 6465.1074 | D28: =INDEX(Modelo_Otimista!$C$26:$BJ$26,5*12) -> 10308.411
A29: ARR no fim do ano 3 (R$) | B29: =INDEX(Modelo_Conservador!$C$62:$BJ$62,3*12) -> 10493266 | C29: =INDEX(Modelo_Base!$C$62:$BJ$62,3*12) -> 18263945 | D29: =INDEX(Modelo_Otimista!$C$62:$BJ$62,3*12) -> 27851498
A30: ARR no fim do ano 5 (R$) | B30: =INDEX(Modelo_Conservador!$C$62:$BJ$62,5*12) -> 40211471 | C30: =INDEX(Modelo_Base!$C$62:$BJ$62,5*12) -> 72438951 | D30: =INDEX(Modelo_Otimista!$C$62:$BJ$62,5*12) -> 1.1409067e+08
A31: Receita bruta do ano 5 (R$) | B31: =SUMIFS(Modelo_Conservador!$C$35:$BJ$35,Modelo_Conservador!$C$4:$BJ$4,5) -> 37369921 | C31: =SUMIFS(Modelo_Base!$C$35:$BJ$35,Modelo_Base!$C$4:$BJ$4,5) -> 69092179 | D31: =SUMIFS(Modelo_Otimista!$C$35:$BJ$35,Modelo_Otimista!$C$4:$BJ$4,5) -> 1.1041608e+08
A32: EBITDA do ano 5 (R$) | B32: =SUMIFS(Modelo_Conservador!$C$56:$BJ$56,Modelo_Conservador!$C$4:$BJ$4,5) -> 5072790.7 | C32: =SUMIFS(Modelo_Base!$C$56:$BJ$56,Modelo_Base!$C$4:$BJ$4,5) -> 24886538 | D32: =SUMIFS(Modelo_Otimista!$C$56:$BJ$56,Modelo_Otimista!$C$4:$BJ$4,5) -> 51279553
A33: Mês do equilíbrio (EBITDA positivo daí em diante) | B33: =MIN(Modelo_Conservador!$C$65:$BJ$65) -> 50 | C33: =MIN(Modelo_Base!$C$65:$BJ$65) -> 30 | D33: =MIN(Modelo_Otimista!$C$65:$BJ$65) -> 27
A34: Menor saldo de caixa no período (R$) | B34: =MIN(Modelo_Conservador!$C$60:$BJ$60) -> -3219857.7 | C34: =MIN(Modelo_Base!$C$60:$BJ$60) -> 558638.49 | D34: =MIN(Modelo_Otimista!$C$60:$BJ$60) -> 1473064.4
A35: Total captado no período (R$) | B35: =SUM(Modelo_Conservador!$C$59:$BJ$59) -> 8300000 | C35: =SUM(Modelo_Base!$C$59:$BJ$59) -> 11300000 | D35: =SUM(Modelo_Otimista!$C$59:$BJ$59) -> 13300000
A36: Leitura: 999 em 'mês do equilíbrio' significa que o cenário não chega ao equilíbrio em 60 meses. Caixa negativo indica necessidade de captação adicional.
A38: Necessidade de caixa antes da rodada seed (cenário base)
A39: Queima acumulada até o mês anterior ao seed (R$) | B39: =-SUMIFS(Modelo_Base!$C$56:$BJ$56,Modelo_Base!$C$3:$BJ$3,"<"&INDEX(Premissas!$B$53:$D$53,2)) -> 2741361.5
A40: Reserva de segurança (meses de queima média) | B40: 3
A41: Pré-seed recomendado (R$) | B41: =ROUNDUP((B39+B39/(INDEX(Premissas!$B$53:$D$53,2)-1)*B40)/100000,0)*100000 -> 3300000 | C41: Cobre a queima até o seed mais a reserva, arredondado para R$ 100 mil.
A43: Clientes ativos no fim de cada ano por cenário (dados do gráfico)
A44: Ano | B44: Conservador | C44: Base | D44: Otimista
A45: Ano 1 | B45: =INDEX(Modelo_Conservador!$C$26:$BJ$26,1*12) -> 109.19497 | C45: =INDEX(Modelo_Base!$C$26:$BJ$26,1*12) -> 185.33502 | D45: =INDEX(Modelo_Otimista!$C$26:$BJ$26,1*12) -> 275.61225
A46: Ano 2 | B46: =INDEX(Modelo_Conservador!$C$26:$BJ$26,2*12) -> 408.1075 | C46: =INDEX(Modelo_Base!$C$26:$BJ$26,2*12) -> 709.49457 | D46: =INDEX(Modelo_Otimista!$C$26:$BJ$26,2*12) -> 1077.2792
A47: Ano 3 | B47: =INDEX(Modelo_Conservador!$C$26:$BJ$26,3*12) -> 1058.8075 | C47: =INDEX(Modelo_Base!$C$26:$BJ$26,3*12) -> 1870.4941 | D47: =INDEX(Modelo_Otimista!$C$26:$BJ$26,3*12) -> 2882.8485
A48: Ano 4 | B48: =INDEX(Modelo_Conservador!$C$26:$BJ$26,4*12) -> 2108.2094 | C48: =INDEX(Modelo_Base!$C$26:$BJ$26,4*12) -> 3790.9775 | D48: =INDEX(Modelo_Otimista!$C$26:$BJ$26,4*12) -> 5939.547
A49: Ano 5 | B49: =INDEX(Modelo_Conservador!$C$26:$BJ$26,5*12) -> 3529.566 | C49: =INDEX(Modelo_Base!$C$26:$BJ$26,5*12) -> 6465.1074 | D49: =INDEX(Modelo_Otimista!$C$26:$BJ$26,5*12) -> 10308.411
A52: Receita bruta e EBITDA por ano (cenário base, dados do gráfico)
A53: Ano | B53: Receita bruta | C53: EBITDA
A54: Ano 1 | B54: =B11 -> 873270.17 | C54: =B20 -> -1781983.5
A55: Ano 2 | B55: =C11 -> 4532675.3 | C55: =C20 -> -2512746.1
A56: Ano 3 | B56: =D11 -> 15064817 | C56: =D20 -> 489496.87
A57: Ano 4 | B57: =E11 -> 35780120 | C57: =E20 -> 8026370.2
A58: Ano 5 | B58: =F11 -> 69092179 | C58: =F20 -> 24886538

Sheet Unit_Economics
A1: Jalecon: economia por cliente (cenário base, ano 1)
A2: Margem de contribuição por conta e retorno do custo de aquisição.
A4: Item | B4: Essencial | C4: Consultório | D4: Autoridade | E4: Clínica
A5: Preço efetivo mensal (R$, após desconto anual) | B5: =Premissas!$B$18*(1-Premissas!$B$12*Premissas!$B$13) -> 283.635 | C5: =Premissas!$C$18*(1-Premissas!$B$12*Premissas!$B$13) -> 665.635 | D5: =Premissas!$D$18*(1-Premissas!$B$12*Premissas!$B$13) -> 1429.635 | E5: =Premissas!$E$18*(1-Premissas!$B$12*Premissas!$B$13) -> 3724.5
A6: (-) Impostos (Simples) | B6: =-B5*Premissas!$B$6 -> -31.19985 | C6: =-C5*Premissas!$B$6 -> -73.21985 | D6: =-D5*Premissas!$B$6 -> -157.25985 | E6: =-E5*Premissas!$B$6 -> -409.695
A7: (-) IA | B7: =-Premissas!$B$21*Premissas!$B$5 -> -21.6 | C7: =-Premissas!$C$21*Premissas!$B$5 -> -48.6 | D7: =-Premissas!$D$21*Premissas!$B$5 -> -97.2 | E7: =-Premissas!$E$21*Premissas!$B$5 -> -243
A8: (-) Infra e APIs | B8: =-Premissas!$B$22 -> -8 | C8: =-Premissas!$C$22 -> -12 | D8: =-Premissas!$D$22 -> -18 | E8: =-Premissas!$E$22 -> -40
A9: (-) Gestor de conta (rateio) | B9: =-IFERROR(Premissas!$B$24*(1+Premissas!$B$10)/Premissas!$B$23,0) -> 0 | C9: =-IFERROR(Premissas!$B$24*(1+Premissas!$B$10)/Premissas!$C$23,0) -> 0 | D9: =-IFERROR(Premissas!$B$24*(1+Premissas!$B$10)/Premissas!$D$23,0) -> -297.5 | E9: =-IFERROR(Premissas!$B$24*(1+Premissas!$B$10)/Premissas!$E$23,0) -> -595
A10: (-) Meio de pagamento | B10: =-B5*Premissas!$B$9 -> -9.927225 | C10: =-C5*Premissas!$B$9 -> -23.297225 | D10: =-D5*Premissas!$B$9 -> -50.037225 | E10: =-E5*Premissas!$B$9 -> -130.3575
A11: Margem de contribuição mensal (R$) | B11: =SUM(B5:B10) -> 212.90793 | C11: =SUM(C5:C10) -> 508.51792 | D11: =SUM(D5:D10) -> 809.63792 | E11: =SUM(E5:E10) -> 2306.4475
A12: Margem de contribuição (%) | B12: =IFERROR(B11/B5,0) -> 0.75064052 | C12: =IFERROR(C11/C5,0) -> 0.76395911 | D12: =IFERROR(D11/D5,0) -> 0.56632492 | E12: =IFERROR(E11/E5,0) -> 0.61926366
A13: Churn mensal (ano 1, base) | B13: =Premissas!$B$20 -> 0.05 | C13: =Premissas!$C$20 -> 0.03 | D13: =Premissas!$D$20 -> 0.025 | E13: =Premissas!$E$20 -> 0.02
A14: Vida média do cliente (meses) | B14: =IFERROR(1/B13,0) -> 20 | C14: =IFERROR(1/C13,0) -> 33.333333 | D14: =IFERROR(1/D13,0) -> 40 | E14: =IFERROR(1/E13,0) -> 50
A15: LTV: margem acumulada na vida do cliente (R$) | B15: =B11*B14 -> 4258.1585 | C15: =C11*C14 -> 16950.597 | D15: =D11*D14 -> 32385.517 | E15: =E11*E14 -> 115322.38
A16: CAC de mídia paga, ano 1 (R$) | B16: =Premissas!$B$42 -> 1800 | C16: =Premissas!$B$42 -> 1800 | D16: =Premissas!$B$42 -> 1800 | E16: =Premissas!$B$42 -> 1800
A17: LTV / CAC | B17: =IFERROR(B15/B16,0) -> 2.3656436 | C17: =IFERROR(C15/C16,0) -> 9.4169986 | D17: =IFERROR(D15/D16,0) -> 17.991954 | E17: =IFERROR(E15/E16,0) -> 64.067986
A18: Payback do CAC (meses) | B18: =IFERROR(B16/B11,0) -> 8.4543589 | C18: =IFERROR(C16/C11,0) -> 3.5396982 | D18: =IFERROR(D16/D11,0) -> 2.223216 | E18: =IFERROR(E16/E11,0) -> 0.78042097
A20: Referência de mercado: LTV/CAC acima de 3x e payback abaixo de 12 meses são considerados saudáveis para SaaS.

Sheet Mercado
A1: Jalecon: tamanho de mercado (TAM, SAM, SOM)
A3: Item | B3: Valor | C3: Fonte / nota
A4: Médicos em atividade no Brasil (projeção 2025) | B4: 635706 | C4: Demografia Médica no Brasil 2025 (FMUSP, AMB, Ministério da Saúde).
A5: % de médicos sem contrato formal (atuação autônoma/PJ) | B5: 0.48 | C5: Demografia Médica 2025: subiu de 30% (2015) para 48% (2025).
A6: % dos especialistas no Sudeste | B6: 0.554 | C6: Demografia Médica 2025.
A7: Receita anual média por conta (R$) | B7: =Unit_Economics!C5*12*(1+INDEX(Premissas!$B$39:$F$39,3)) -> 8866.2582 | C7: Plano Consultório + serviços adicionais do ano 3.
A8: TAM: todos os médicos × receita anual por conta (R$) | B8: =B4*B7 -> 5.6363335e+09 | C8: Mercado total se todo médico assinasse.
A9: SAM: médicos autônomos/PJ (quantidade) | B9: =B4*B5 -> 305138.88 | C9: Quem precisa gerar a própria demanda.
A10: SAM (R$ por ano) | B10: =B9*B7 -> 2.7054401e+09
A11: SOM ano 5: clientes do cenário base | B11: =INDEX(Modelo_Base!$C$26:$BJ$26,5*12) -> 6465.1074 | C11: Calculado pelo modelo.
A12: SOM como % do SAM | B12: =IFERROR(B11/B9,0) -> 0.021187426
A13: SOM (ARR do ano 5, cenário base, R$) | B13: =INDEX(Modelo_Base!$C$62:$BJ$62,5*12) -> 72438951
A14: Primeiro segmento: autônomos no Sudeste (quantidade, aproximação) | B14: =B9*B6 -> 169046.94 | C14: Aproximação usando a participação do Sudeste nos especialistas.
A16: Expansão: outras profissões de saúde (estimativas a confirmar nos conselhos)
A17: Cirurgiões-dentistas | B17: 400000 | C17: Estimativa; confirmar no painel do CFO.
A18: Psicólogos | B18: 500000 | C18: Estimativa; confirmar no CFP.
A19: Nutricionistas | B19: 150000 | C19: Estimativa; o CFN cita 'mais de 110 mil' em nota antiga.
A20: Fisioterapeutas | B20: 300000 | C20: Estimativa; confirmar no COFFITO.
A21: Profissionais na expansão (total) | B21: =SUM(B17:B20) -> 1350000
A22: TAM ampliado (médicos + expansão, R$ por ano) | B22: =(B4+B21)*B7 -> 1.7605782e+10

Sheet Modelo_Conservador
A1: Jalecon: projeção mensal, cenário conservador
A2: Cenário (1 = conservador, 2 = base, 3 = otimista) | B2: 1
A3: Mês | C3: 1 | D3: =C3+1 -> 2 | E3: =D3+1 -> 3 | F3: =E3+1 -> 4 | G3: =F3+1 -> 5 | H3: =G3+1 -> 6 | I3: =H3+1 -> 7 | J3: =I3+1 -> 8 | K3: =J3+1 -> 9 | ... BJ3: =BI3+1 -> 60
A4: Ano | C4: =ROUNDUP(C3/12,0) -> 1 | D4: =ROUNDUP(D3/12,0) -> 1 | E4: =ROUNDUP(E3/12,0) -> 1 | F4: =ROUNDUP(F3/12,0) -> 1 | G4: =ROUNDUP(G3/12,0) -> 1 | H4: =ROUNDUP(H3/12,0) -> 1 | I4: =ROUNDUP(I3/12,0) -> 1 | J4: =ROUNDUP(J3/12,0) -> 1 | ... BJ4: =ROUNDUP(BJ3/12,0) -> 5
A6: Aquisição
A7: Orçamento de mídia paga (R$) | C7: =INDEX(Premissas!$B$37:$F$37,C$4)*INDEX(Premissas!$B$51:$D$51,$B$2) -> 20000 | D7: =INDEX(Premissas!$B$37:$F$37,D$4)*INDEX(Premissas!$B$51:$D$51,$B$2) -> 20000 | E7: =INDEX(Premissas!$B$37:$F$37,E$4)*INDEX(Premissas!$B$51:$D$51,$B$2) -> 20000 | F7: =INDEX(Premissas!$B$37:$F$37,F$4)*INDEX(Premissas!$B$51:$D$51,$B$2) -> 20000 | G7: =INDEX(Premissas!$B$37:$F$37,G$4)*INDEX(Premissas!$B$51:$D$51,$B$2) -> 20000 | H7: =INDEX(Premissas!$B$37:$F$37,H$4)*INDEX(Premissas!$B$51:$D$51,$B$2) -> 20000 | I7: =INDEX(Premissas!$B$37:$F$37,I$4)*INDEX(Premissas!$B$51:$D$51,$B$2) -> 20000 | J7: =INDEX(Premissas!$B$37:$F$37,J$4)*INDEX(Premissas!$B$51:$D$51,$B$2) -> 20000 | ... BJ7: =INDEX(Premissas!$B$37:$F$37,BJ$4)*INDEX(Premissas!$B$51:$D$51,$B$2) -> 256000
A8: CAC de mídia paga (R$) | C8: =INDEX(Premissas!$B$42:$F$42,C$4)*INDEX(Premissas!$B$47:$D$47,$B$2) -> 2340 | D8: =INDEX(Premissas!$B$42:$F$42,D$4)*INDEX(Premissas!$B$47:$D$47,$B$2) -> 2340 | E8: =INDEX(Premissas!$B$42:$F$42,E$4)*INDEX(Premissas!$B$47:$D$47,$B$2) -> 2340 | F8: =INDEX(Premissas!$B$42:$F$42,F$4)*INDEX(Premissas!$B$47:$D$47,$B$2) -> 2340 | G8: =INDEX(Premissas!$B$42:$F$42,G$4)*INDEX(Premissas!$B$47:$D$47,$B$2) -> 2340 | H8: =INDEX(Premissas!$B$42:$F$42,H$4)*INDEX(Premissas!$B$47:$D$47,$B$2) -> 2340 | I8: =INDEX(Premissas!$B$42:$F$42,I$4)*INDEX(Premissas!$B$47:$D$47,$B$2) -> 2340 | J8: =INDEX(Premissas!$B$42:$F$42,J$4)*INDEX(Premissas!$B$47:$D$47,$B$2) -> 2340 | ... BJ8: =INDEX(Premissas!$B$42:$F$42,BJ$4)*INDEX(Premissas!$B$47:$D$47,$B$2) -> 1750.4417
A9: Novos clientes: mídia paga | C9: =IFERROR(C7/C8,0) -> 8.5470085 | D9: =IFERROR(D7/D8,0) -> 8.5470085 | E9: =IFERROR(E7/E8,0) -> 8.5470085 | F9: =IFERROR(F7/F8,0) -> 8.5470085 | G9: =IFERROR(G7/G8,0) -> 8.5470085 | H9: =IFERROR(H7/H8,0) -> 8.5470085 | I9: =IFERROR(I7/I8,0) -> 8.5470085 | J9: =IFERROR(J7/J8,0) -> 8.5470085 | ... BJ9: =IFERROR(BJ7/BJ8,0) -> 146.2488
A10: Novos clientes: parcerias | C10: =INDEX(Premissas!$B$38:$F$38,C$4)*INDEX(Premissas!$B$49:$D$49,$B$2) -> 2.8 | D10: =INDEX(Premissas!$B$38:$F$38,D$4)*INDEX(Premissas!$B$49:$D$49,$B$2) -> 2.8 | E10: =INDEX(Premissas!$B$38:$F$38,E$4)*INDEX(Premissas!$B$49:$D$49,$B$2) -> 2.8 | F10: =INDEX(Premissas!$B$38:$F$38,F$4)*INDEX(Premissas!$B$49:$D$49,$B$2) -> 2.8 | G10: =INDEX(Premissas!$B$38:$F$38,G$4)*INDEX(Premissas!$B$49:$D$49,$B$2) -> 2.8 | H10: =INDEX(Premissas!$B$38:$F$38,H$4)*INDEX(Premissas!$B$49:$D$49,$B$2) -> 2.8 | I10: =INDEX(Premissas!$B$38:$F$38,I$4)*INDEX(Premissas!$B$49:$D$49,$B$2) -> 2.8 | J10: =INDEX(Premissas!$B$38:$F$38,J$4)*INDEX(Premissas!$B$49:$D$49,$B$2) -> 2.8 | ... BJ10: =INDEX(Premissas!$B$38:$F$38,BJ$4)*INDEX(Premissas!$B$49:$D$49,$B$2) -> 38.5
A11: Novos clientes: indicação | C11: =0 -> 0 | D11: =C26*Premissas!$B$43*INDEX(Premissas!$B$49:$D$49,$B$2) -> 0.07942906 | E11: =D26*Premissas!$B$43*INDEX(Premissas!$B$49:$D$49,$B$2) -> 0.15554196 | F11: =E26*Premissas!$B$43*INDEX(Premissas!$B$49:$D$49,$B$2) -> 0.2284914 | G11: =F26*Premissas!$B$43*INDEX(Premissas!$B$49:$D$49,$B$2) -> 0.29842238 | H11: =G26*Premissas!$B$43*INDEX(Premissas!$B$49:$D$49,$B$2) -> 0.36547255 | I11: =H26*Premissas!$B$43*INDEX(Premissas!$B$49:$D$49,$B$2) -> 0.42977269 | J11: =I26*Premissas!$B$43*INDEX(Premissas!$B$49:$D$49,$B$2) -> 0.49144701 | K11: =J26*Premissas!$B$43*INDEX(Premissas!$B$49:$D$49,$B$2) -> 0.55061357 | ... BJ11: =BI26*Premissas!$B$43*INDEX(Premissas!$B$49:$D$49,$B$2) -> 23.976994
A12: Novos clientes: total | C12: =C9+C10+C11 -> 11.347009 | D12: =D9+D10+D11 -> 11.426438 | E12: =E9+E10+E11 -> 11.502551 | F12: =F9+F10+F11 -> 11.5755 | G12: =G9+G10+G11 -> 11.645431 | H12: =H9+H10+H11 -> 11.712481 | I12: =I9+I10+I11 -> 11.776781 | J12: =J9+J10+J11 -> 11.838456 | ... BJ12: =BJ9+BJ10+BJ11 -> 208.72579
A13: Clientes por plano
A14: Novos: Essencial | C14: =C12*INDEX(Premissas!$B$29:$B$33,C$4) -> 4.5388034 | D14: =D12*INDEX(Premissas!$B$29:$B$33,D$4) -> 4.570575 | E14: =E12*INDEX(Premissas!$B$29:$B$33,E$4) -> 4.6010202 | F14: =F12*INDEX(Premissas!$B$29:$B$33,F$4) -> 4.6302 | G14: =G12*INDEX(Premissas!$B$29:$B$33,G$4) -> 4.6581724 | H14: =H12*INDEX(Premissas!$B$29:$B$33,H$4) -> 4.6849924 | I14: =I12*INDEX(Premissas!$B$29:$B$33,I$4) -> 4.7107125 | J14: =J12*INDEX(Premissas!$B$29:$B$33,J$4) -> 4.7353822 | ... BJ14: =BJ12*INDEX(Premissas!$B$29:$B$33,BJ$4) -> 52.181449
A15: Novos: Consultório | C15: =C12*INDEX(Premissas!$C$29:$C$33,C$4) -> 5.6735043 | D15: =D12*INDEX(Premissas!$C$29:$C$33,D$4) -> 5.7132188 | E15: =E12*INDEX(Premissas!$C$29:$C$33,E$4) -> 5.7512753 | F15: =F12*INDEX(Premissas!$C$29:$C$33,F$4) -> 5.78775 | G15: =G12*INDEX(Premissas!$C$29:$C$33,G$4) -> 5.8227155 | H15: =H12*INDEX(Premissas!$C$29:$C$33,H$4) -> 5.8562405 | I15: =I12*INDEX(Premissas!$C$29:$C$33,I$4) -> 5.8883906 | J15: =J12*INDEX(Premissas!$C$29:$C$33,J$4) -> 5.9192278 | ... BJ15: =BJ12*INDEX(Premissas!$C$29:$C$33,BJ$4) -> 104.3629
A16: Novos: Autoridade | C16: =C12*INDEX(Premissas!$D$29:$D$33,C$4) -> 1.1347009 | D16: =D12*INDEX(Premissas!$D$29:$D$33,D$4) -> 1.1426438 | E16: =E12*INDEX(Premissas!$D$29:$D$33,E$4) -> 1.1502551 | F16: =F12*INDEX(Premissas!$D$29:$D$33,F$4) -> 1.15755 | G16: =G12*INDEX(Premissas!$D$29:$D$33,G$4) -> 1.1645431 | H16: =H12*INDEX(Premissas!$D$29:$D$33,H$4) -> 1.1712481 | I16: =I12*INDEX(Premissas!$D$29:$D$33,I$4) -> 1.1776781 | J16: =J12*INDEX(Premissas!$D$29:$D$33,J$4) -> 1.1838456 | ... BJ16: =BJ12*INDEX(Premissas!$D$29:$D$33,BJ$4) -> 37.570643
A17: Novos: Clínica | C17: =C12*INDEX(Premissas!$E$29:$E$33,C$4) -> 0 | D17: =D12*INDEX(Premissas!$E$29:$E$33,D$4) -> 0 | E17: =E12*INDEX(Premissas!$E$29:$E$33,E$4) -> 0 | F17: =F12*INDEX(Premissas!$E$29:$E$33,F$4) -> 0 | G17: =G12*INDEX(Premissas!$E$29:$E$33,G$4) -> 0 | H17: =H12*INDEX(Premissas!$E$29:$E$33,H$4) -> 0 | I17: =I12*INDEX(Premissas!$E$29:$E$33,I$4) -> 0 | J17: =J12*INDEX(Premissas!$E$29:$E$33,J$4) -> 0 | ... BJ17: =BJ12*INDEX(Premissas!$E$29:$E$33,BJ$4) -> 14.610806
A18: Cancelamentos: Essencial | C18: =0 -> 0 | D18: =C22*Premissas!$B$20*INDEX(Premissas!$B$48:$D$48,$B$2)*(1-Premissas!$B$25)^(D$4-1) -> 0.29502222 | E18: =D22*Premissas!$B$20*INDEX(Premissas!$B$48:$D$48,$B$2)*(1-Premissas!$B$25)^(E$4-1) -> 0.57293316 | F18: =E22*Premissas!$B$20*INDEX(Premissas!$B$48:$D$48,$B$2)*(1-Premissas!$B$25)^(F$4-1) -> 0.83475881 | G18: =F22*Premissas!$B$20*INDEX(Premissas!$B$48:$D$48,$B$2)*(1-Premissas!$B$25)^(G$4-1) -> 1.0814625 | H18: =G22*Premissas!$B$20*INDEX(Premissas!$B$48:$D$48,$B$2)*(1-Premissas!$B$25)^(H$4-1) -> 1.3139486 | I18: =H22*Premissas!$B$20*INDEX(Premissas!$B$48:$D$48,$B$2)*(1-Premissas!$B$25)^(I$4-1) -> 1.5330665 | J18: =I22*Premissas!$B$20*INDEX(Premissas!$B$48:$D$48,$B$2)*(1-Premissas!$B$25)^(J$4-1) -> 1.7396135 | K18: =J22*Premissas!$B$20*INDEX(Premissas!$B$48:$D$48,$B$2)*(1-Premissas!$B$25)^(K$4-1) -> 1.9343384 | ... BJ18: =BI22*Premissas!$B$20*INDEX(Premissas!$B$48:$D$48,$B$2)*(1-Premissas!$B$25)^(BJ$4-1) -> 35.073952
A19: Cancelamentos: Consultório | C19: =0 -> 0 | D19: =C23*Premissas!$C$20*INDEX(Premissas!$B$48:$D$48,$B$2)*(1-Premissas!$B$25)^(D$4-1) -> 0.22126667 | E19: =D23*Premissas!$C$20*INDEX(Premissas!$B$48:$D$48,$B$2)*(1-Premissas!$B$25)^(E$4-1) -> 0.4354528 | F19: =E23*Premissas!$C$20*INDEX(Premissas!$B$48:$D$48,$B$2)*(1-Premissas!$B$25)^(F$4-1) -> 0.64276988 | G19: =F23*Premissas!$C$20*INDEX(Premissas!$B$48:$D$48,$B$2)*(1-Premissas!$B$25)^(G$4-1) -> 0.8434241 | H19: =G23*Premissas!$C$20*INDEX(Premissas!$B$48:$D$48,$B$2)*(1-Premissas!$B$25)^(H$4-1) -> 1.0376165 | I19: =H23*Premissas!$C$20*INDEX(Premissas!$B$48:$D$48,$B$2)*(1-Premissas!$B$25)^(I$4-1) -> 1.2255428 | J19: =I23*Premissas!$C$20*INDEX(Premissas!$B$48:$D$48,$B$2)*(1-Premissas!$B$25)^(J$4-1) -> 1.4073939 | K19: =J23*Premissas!$C$20*INDEX(Premissas!$B$48:$D$48,$B$2)*(1-Premissas!$B$25)^(K$4-1) -> 1.5833554 | ... BJ19: =BI23*Premissas!$C$20*INDEX(Premissas!$B$48:$D$48,$B$2)*(1-Premissas!$B$25)^(BJ$4-1) -> 49.895365
A20: Cancelamentos: Autoridade | C20: =0 -> 0 | D20: =C24*Premissas!$D$20*INDEX(Premissas!$B$48:$D$48,$B$2)*(1-Premissas!$B$25)^(D$4-1) -> 0.036877778 | E20: =D24*Premissas!$D$20*INDEX(Premissas!$B$48:$D$48,$B$2)*(1-Premissas!$B$25)^(E$4-1) -> 0.072815172 | F20: =E24*Premissas!$D$20*INDEX(Premissas!$B$48:$D$48,$B$2)*(1-Premissas!$B$25)^(F$4-1) -> 0.10783197 | G20: =F24*Premissas!$D$20*INDEX(Premissas!$B$48:$D$48,$B$2)*(1-Premissas!$B$25)^(G$4-1) -> 0.1419478 | H20: =G24*Premissas!$D$20*INDEX(Premissas!$B$48:$D$48,$B$2)*(1-Premissas!$B$25)^(H$4-1) -> 0.17518215 | I20: =H24*Premissas!$D$20*INDEX(Premissas!$B$48:$D$48,$B$2)*(1-Premissas!$B$25)^(I$4-1) -> 0.20755429 | J20: =I24*Premissas!$D$20*INDEX(Premissas!$B$48:$D$48,$B$2)*(1-Premissas!$B$25)^(J$4-1) -> 0.23908332 | K20: =J24*Premissas!$D$20*INDEX(Premissas!$B$48:$D$48,$B$2)*(1-Premissas!$B$25)^(K$4-1) -> 0.26978809 | ... BJ20: =BI24*Premissas!$D$20*INDEX(Premissas!$B$48:$D$48,$B$2)*(1-Premissas!$B$25)^(BJ$4-1) -> 14.84196
A21: Cancelamentos: Clínica | C21: =0 -> 0 | D21: =C25*Premissas!$E$20*INDEX(Premissas!$B$48:$D$48,$B$2)*(1-Premissas!$B$25)^(D$4-1) -> 0 | E21: =D25*Premissas!$E$20*INDEX(Premissas!$B$48:$D$48,$B$2)*(1-Premissas!$B$25)^(E$4-1) -> 0 | F21: =E25*Premissas!$E$20*INDEX(Premissas!$B$48:$D$48,$B$2)*(1-Premissas!$B$25)^(F$4-1) -> 0 | G21: =F25*Premissas!$E$20*INDEX(Premissas!$B$48:$D$48,$B$2)*(1-Premissas!$B$25)^(G$4-1) -> 0 | H21: =G25*Premissas!$E$20*INDEX(Premissas!$B$48:$D$48,$B$2)*(1-Premissas!$B$25)^(H$4-1) -> 0 | I21: =H25*Premissas!$E$20*INDEX(Premissas!$B$48:$D$48,$B$2)*(1-Premissas!$B$25)^(I$4-1) -> 0 | J21: =I25*Premissas!$E$20*INDEX(Premissas!$B$48:$D$48,$B$2)*(1-Premissas!$B$25)^(J$4-1) -> 0 | K21: =J25*Premissas!$E$20*INDEX(Premissas!$B$48:$D$48,$B$2)*(1-Premissas!$B$25)^(K$4-1) -> 0 | ... BJ21: =BI25*Premissas!$E$20*INDEX(Premissas!$B$48:$D$48,$B$2)*(1-Premissas!$B$25)^(BJ$4-1) -> 4.6333726
A22: Ativos: Essencial | C22: =C14-C18 -> 4.5388034 | D22: =C22+D14-D18 -> 8.8143562 | E22: =D22+E14-E18 -> 12.842443 | F22: =E22+F14-F18 -> 16.637884 | G22: =F22+G14-G18 -> 20.214594 | H22: =G22+H14-H18 -> 23.585638 | I22: =H22+I14-I18 -> 26.763284 | J22: =I22+J14-J18 -> 29.759053 | K22: =J22+K14-K18 -> 32.583763 | ... BJ22: =BI22+BJ14-BJ18 -> 770.32436
A23: Ativos: Consultório | C23: =C15-C19 -> 5.6735043 | D23: =C23+D15-D19 -> 11.165456 | E23: =D23+E15-E19 -> 16.481279 | F23: =E23+F15-F19 -> 21.626259 | G23: =F23+G15-G19 -> 26.60555 | H23: =G23+H15-H19 -> 31.424174 | I23: =H23+I15-I19 -> 36.087022 | J23: =I23+J15-J19 -> 40.598856 | K23: =J23+K15-K19 -> 44.964312 | ... BJ23: =BI23+BJ15-BJ19 -> 1840.3147
A24: Ativos: Autoridade | C24: =C16-C20 -> 1.1347009 | D24: =C24+D16-D20 -> 2.2404668 | E24: =D24+E16-E20 -> 3.3179067 | F24: =E24+F16-F20 -> 4.3676247 | G24: =F24+G16-G20 -> 5.39022 | H24: =G24+H16-H20 -> 6.386286 | I24: =H24+I16-I20 -> 7.3564098 | J24: =I24+J16-J20 -> 8.3011721 | K24: =J24+K16-K20 -> 9.2211462 | ... BJ24: =BI24+BJ16-BJ20 -> 660.19406
A25: Ativos: Clínica | C25: =C17-C21 -> 0 | D25: =C25+D17-D21 -> 0 | E25: =D25+E17-E21 -> 0 | F25: =E25+F17-F21 -> 0 | G25: =F25+G17-G21 -> 0 | H25: =G25+H17-H21 -> 0 | I25: =H25+I17-I21 -> 0 | J25: =I25+J17-J21 -> 0 | K25: =J25+K17-K21 -> 0 | ... BJ25: =BI25+BJ17-BJ21 -> 258.73286
A26: Clientes ativos: total | C26: =SUM(C22:C25) -> 11.347009 | D26: =SUM(D22:D25) -> 22.220279 | E26: =SUM(E22:E25) -> 32.641629 | F26: =SUM(F22:F25) -> 42.631768 | G26: =SUM(G22:G25) -> 52.210365 | H26: =SUM(H22:H25) -> 61.396099 | I26: =SUM(I22:I25) -> 70.206716 | J26: =SUM(J22:J25) -> 78.659081 | ... BJ26: =SUM(BJ22:BJ25) -> 3529.566
A27: Receita (R$)
A28: Receita recorrente: Essencial | C28: =C22*Premissas!$B$18*(1-Premissas!$B$12*Premissas!$B$13) -> 1287.3635 | D28: =D22*Premissas!$B$18*(1-Premissas!$B$12*Premissas!$B$13) -> 2500.0599 | E28: =E22*Premissas!$B$18*(1-Premissas!$B$12*Premissas!$B$13) -> 3642.5664 | F28: =F22*Premissas!$B$18*(1-Premissas!$B$12*Premissas!$B$13) -> 4719.0864 | G28: =G22*Premissas!$B$18*(1-Premissas!$B$12*Premissas!$B$13) -> 5733.5665 | H28: =H22*Premissas!$B$18*(1-Premissas!$B$12*Premissas!$B$13) -> 6689.7125 | I28: =I22*Premissas!$B$18*(1-Premissas!$B$12*Premissas!$B$13) -> 7591.0041 | J28: =J22*Premissas!$B$18*(1-Premissas!$B$12*Premissas!$B$13) -> 8440.709 | ... BJ28: =BJ22*Premissas!$B$18*(1-Premissas!$B$12*Premissas!$B$13) -> 218490.95
A29: Receita recorrente: Consultório | C29: =C23*Premissas!$C$18*(1-Premissas!$B$12*Premissas!$B$13) -> 3776.483 | D29: =D23*Premissas!$C$18*(1-Premissas!$B$12*Premissas!$B$13) -> 7432.1186 | E29: =E23*Premissas!$C$18*(1-Premissas!$B$12*Premissas!$B$13) -> 10970.516 | F29: =F23*Premissas!$C$18*(1-Premissas!$B$12*Premissas!$B$13) -> 14395.195 | G29: =G23*Premissas!$C$18*(1-Premissas!$B$12*Premissas!$B$13) -> 17709.585 | H29: =H23*Premissas!$C$18*(1-Premissas!$B$12*Premissas!$B$13) -> 20917.03 | I29: =I23*Premissas!$C$18*(1-Premissas!$B$12*Premissas!$B$13) -> 24020.785 | J29: =J23*Premissas!$C$18*(1-Premissas!$B$12*Premissas!$B$13) -> 27024.02 | ... BJ29: =BJ23*Premissas!$C$18*(1-Premissas!$B$12*Premissas!$B$13) -> 1224977.9
A30: Receita recorrente: Autoridade | C30: =C24*Premissas!$D$18*(1-Premissas!$B$12*Premissas!$B$13) -> 1622.2081 | D30: =D24*Premissas!$D$18*(1-Premissas!$B$12*Premissas!$B$13) -> 3203.0498 | E30: =E24*Premissas!$D$18*(1-Premissas!$B$12*Premissas!$B$13) -> 4743.3956 | F30: =F24*Premissas!$D$18*(1-Premissas!$B$12*Premissas!$B$13) -> 6244.1092 | G30: =G24*Premissas!$D$18*(1-Premissas!$B$12*Premissas!$B$13) -> 7706.0472 | H30: =H24*Premissas!$D$18*(1-Premissas!$B$12*Premissas!$B$13) -> 9130.058 | I30: =I24*Premissas!$D$18*(1-Premissas!$B$12*Premissas!$B$13) -> 10516.981 | J30: =J24*Premissas!$D$18*(1-Premissas!$B$12*Premissas!$B$13) -> 11867.646 | ... BJ30: =BJ24*Premissas!$D$18*(1-Premissas!$B$12*Premissas!$B$13) -> 943836.53
A31: Receita recorrente: Clínica | C31: =C25*Premissas!$E$18*(1-Premissas!$B$12*Premissas!$B$13) -> 0 | D31: =D25*Premissas!$E$18*(1-Premissas!$B$12*Premissas!$B$13) -> 0 | E31: =E25*Premissas!$E$18*(1-Premissas!$B$12*Premissas!$B$13) -> 0 | F31: =F25*Premissas!$E$18*(1-Premissas!$B$12*Premissas!$B$13) -> 0 | G31: =G25*Premissas!$E$18*(1-Premissas!$B$12*Premissas!$B$13) -> 0 | H31: =H25*Premissas!$E$18*(1-Premissas!$B$12*Premissas!$B$13) -> 0 | I31: =I25*Premissas!$E$18*(1-Premissas!$B$12*Premissas!$B$13) -> 0 | J31: =J25*Premissas!$E$18*(1-Premissas!$B$12*Premissas!$B$13) -> 0 | ... BJ31: =BJ25*Premissas!$E$18*(1-Premissas!$B$12*Premissas!$B$13) -> 963650.54
A32: Receita recorrente mensal (MRR) | C32: =SUM(C28:C31) -> 6686.0546 | D32: =SUM(D28:D31) -> 13135.228 | E32: =SUM(E28:E31) -> 19356.478 | F32: =SUM(F28:F31) -> 25358.39 | G32: =SUM(G28:G31) -> 31149.199 | H32: =SUM(H28:H31) -> 36736.801 | I32: =SUM(I28:I31) -> 42128.77 | J32: =SUM(J28:J31) -> 47332.375 | ... BJ32: =SUM(BJ28:BJ31) -> 3350955.9
A33: Taxas de implantação | C33: =C14*Premissas!$B$19+C15*Premissas!$C$19+C16*Premissas!$D$19+C17*Premissas!$E$19 -> 3903.3709 | D33: =D14*Premissas!$B$19+D15*Premissas!$C$19+D16*Premissas!$D$19+D17*Premissas!$E$19 -> 3930.6945 | E33: =E14*Premissas!$B$19+E15*Premissas!$C$19+E16*Premissas!$D$19+E17*Premissas!$E$19 -> 3956.8774 | F33: =F14*Premissas!$B$19+F15*Premissas!$C$19+F16*Premissas!$D$19+F17*Premissas!$E$19 -> 3981.972 | G33: =G14*Premissas!$B$19+G15*Premissas!$C$19+G16*Premissas!$D$19+G17*Premissas!$E$19 -> 4006.0282 | H33: =H14*Premissas!$B$19+H15*Premissas!$C$19+H16*Premissas!$D$19+H17*Premissas!$E$19 -> 4029.0935 | I33: =I14*Premissas!$B$19+I15*Premissas!$C$19+I16*Premissas!$D$19+I17*Premissas!$E$19 -> 4051.2127 | J33: =J14*Premissas!$B$19+J15*Premissas!$C$19+J16*Premissas!$D$19+J17*Premissas!$E$19 -> 4072.4287 | ... BJ33: =BJ14*Premissas!$B$19+BJ15*Premissas!$C$19+BJ16*Premissas!$D$19+BJ17*Premissas!$E$19 -> 130704.09
A34: Serviços adicionais | C34: =C32*INDEX(Premissas!$B$39:$F$39,C$4)*INDEX(Premissas!$B$50:$D$50,$B$2) -> 234.01191 | D34: =D32*INDEX(Premissas!$B$39:$F$39,D$4)*INDEX(Premissas!$B$50:$D$50,$B$2) -> 459.73299 | E34: =E32*INDEX(Premissas!$B$39:$F$39,E$4)*INDEX(Premissas!$B$50:$D$50,$B$2) -> 677.47673 | F34: =F32*INDEX(Premissas!$B$39:$F$39,F$4)*INDEX(Premissas!$B$50:$D$50,$B$2) -> 887.54367 | G34: =G32*INDEX(Premissas!$B$39:$F$39,G$4)*INDEX(Premissas!$B$50:$D$50,$B$2) -> 1090.222 | H34: =H32*INDEX(Premissas!$B$39:$F$39,H$4)*INDEX(Premissas!$B$50:$D$50,$B$2) -> 1285.788 | I34: =I32*INDEX(Premissas!$B$39:$F$39,I$4)*INDEX(Premissas!$B$50:$D$50,$B$2) -> 1474.507 | J34: =J32*INDEX(Premissas!$B$39:$F$39,J$4)*INDEX(Premissas!$B$50:$D$50,$B$2) -> 1656.6331 | ... BJ34: =BJ32*INDEX(Premissas!$B$39:$F$39,BJ$4)*INDEX(Premissas!$B$50:$D$50,$B$2) -> 351850.37
A35: Receita bruta | C35: =C32+C33+C34 -> 10823.437 | D35: =D32+D33+D34 -> 17525.656 | E35: =E32+E33+E34 -> 23990.832 | F35: =F32+F33+F34 -> 30227.906 | G35: =G32+G33+G34 -> 36245.449 | H35: =H32+H33+H34 -> 42051.682 | I35: =I32+I33+I34 -> 47654.49 | J35: =J32+J33+J34 -> 53061.437 | ... BJ35: =BJ32+BJ33+BJ34 -> 3833510.3
A36: (-) Impostos sobre receita | C36: =-C35*IF(SUMIFS($C$35:$BJ$35,$C$4:$BJ$4,C$4-1)>Premissas!$B$8,Premissas!$B$7,Premissas!$B$6) -> -1190.5781 | D36: =-D35*IF(SUMIFS($C$35:$BJ$35,$C$4:$BJ$4,D$4-1)>Premissas!$B$8,Premissas!$B$7,Premissas!$B$6) -> -1927.8221 | E36: =-E35*IF(SUMIFS($C$35:$BJ$35,$C$4:$BJ$4,E$4-1)>Premissas!$B$8,Premissas!$B$7,Premissas!$B$6) -> -2638.9915 | F36: =-F35*IF(SUMIFS($C$35:$BJ$35,$C$4:$BJ$4,F$4-1)>Premissas!$B$8,Premissas!$B$7,Premissas!$B$6) -> -3325.0697 | G36: =-G35*IF(SUMIFS($C$35:$BJ$35,$C$4:$BJ$4,G$4-1)>Premissas!$B$8,Premissas!$B$7,Premissas!$B$6) -> -3986.9994 | H36: =-H35*IF(SUMIFS($C$35:$BJ$35,$C$4:$BJ$4,H$4-1)>Premissas!$B$8,Premissas!$B$7,Premissas!$B$6) -> -4625.6851 | I36: =-I35*IF(SUMIFS($C$35:$BJ$35,$C$4:$BJ$4,I$4-1)>Premissas!$B$8,Premissas!$B$7,Premissas!$B$6) -> -5241.9939 | J36: =-J35*IF(SUMIFS($C$35:$BJ$35,$C$4:$BJ$4,J$4-1)>Premissas!$B$8,Premissas!$B$7,Premissas!$B$6) -> -5836.758 | ... BJ36: =-BJ35*IF(SUMIFS($C$35:$BJ$35,$C$4:$BJ$4,BJ$4-1)>Premissas!$B$8,Premissas!$B$7,Premissas!$B$6) -> -626012.24
A37: Receita líquida | C37: =C35+C36 -> 9632.8593 | D37: =D35+D36 -> 15597.834 | E37: =E35+E36 -> 21351.841 | F37: =F35+F36 -> 26902.836 | G37: =G35+G36 -> 32258.45 | H37: =H35+H36 -> 37425.997 | I37: =I35+I36 -> 42412.496 | J37: =J35+J36 -> 47224.679 | ... BJ37: =BJ35+BJ36 -> 3207498.1
A38: Custo do serviço (R$)
A39: IA (modelos de linguagem e imagem) | C39: =-(C22*Premissas!$B$21+C23*Premissas!$C$21+C24*Premissas!$D$21+C25*Premissas!$E$21)*Premissas!$B$5 -> -484.06338 | D39: =-(D22*Premissas!$B$21+D23*Premissas!$C$21+D24*Premissas!$D$21+D25*Premissas!$E$21)*Premissas!$B$5 -> -950.80465 | E39: =-(E22*Premissas!$B$21+E23*Premissas!$C$21+E24*Premissas!$D$21+E25*Premissas!$E$21)*Premissas!$B$5 -> -1400.8875 | F39: =-(F22*Premissas!$B$21+F23*Premissas!$C$21+F24*Premissas!$D$21+F25*Premissas!$E$21)*Premissas!$B$5 -> -1834.9476 | G39: =-(G22*Premissas!$B$21+G23*Premissas!$C$21+G24*Premissas!$D$21+G25*Premissas!$E$21)*Premissas!$B$5 -> -2253.5944 | H39: =-(H22*Premissas!$B$21+H23*Premissas!$C$21+H24*Premissas!$D$21+H25*Premissas!$E$21)*Premissas!$B$5 -> -2657.4117 | I39: =-(I22*Premissas!$B$21+I23*Premissas!$C$21+I24*Premissas!$D$21+I25*Premissas!$E$21)*Premissas!$B$5 -> -3046.9593 | J39: =-(J22*Premissas!$B$21+J23*Premissas!$C$21+J24*Premissas!$D$21+J25*Premissas!$E$21)*Premissas!$B$5 -> -3422.7739 | ... BJ39: =-(BJ22*Premissas!$B$21+BJ23*Premissas!$C$21+BJ24*Premissas!$D$21+BJ25*Premissas!$E$21)*Premissas!$B$5 -> -233121.25
A40: Infraestrutura e APIs | C40: =-(C22*Premissas!$B$22+C23*Premissas!$C$22+C24*Premissas!$D$22+C25*Premissas!$E$22) -> -124.81709 | D40: =-(D22*Premissas!$B$22+D23*Premissas!$C$22+D24*Premissas!$D$22+D25*Premissas!$E$22) -> -244.82873 | E40: =-(E22*Premissas!$B$22+E23*Premissas!$C$22+E24*Premissas!$D$22+E25*Premissas!$E$22) -> -360.23721 | F40: =-(F22*Premissas!$B$22+F23*Premissas!$C$22+F24*Premissas!$D$22+F25*Premissas!$E$22) -> -471.23543 | G40: =-(G22*Premissas!$B$22+G23*Premissas!$C$22+G24*Premissas!$D$22+G25*Premissas!$E$22) -> -578.00732 | H40: =-(H22*Premissas!$B$22+H23*Premissas!$C$22+H24*Premissas!$D$22+H25*Premissas!$E$22) -> -680.72835 | I40: =-(I22*Premissas!$B$22+I23*Premissas!$C$22+I24*Premissas!$D$22+I25*Premissas!$E$22) -> -779.56592 | J40: =-(J22*Premissas!$B$22+J23*Premissas!$C$22+J24*Premissas!$D$22+J25*Premissas!$E$22) -> -874.67979 | ... BJ40: =-(BJ22*Premissas!$B$22+BJ23*Premissas!$C$22+BJ24*Premissas!$D$22+BJ25*Premissas!$E$22) -> -50479.179
A41: Gestores de conta (revisão humana) | C41: =-(IFERROR(C22/Premissas!$B$23,0)+IFERROR(C23/Premissas!$C$23,0)+IFERROR(C24/Premissas!$D$23,0)+IFERROR(C25/Premissas!$E$23,0))*Premissas!$B$24*(1+Premissas!$B$10) -> -337.5735 | D41: =-(IFERROR(D22/Premissas!$B$23,0)+IFERROR(D23/Premissas!$C$23,0)+IFERROR(D24/Premissas!$D$23,0)+IFERROR(D25/Premissas!$E$23,0))*Premissas!$B$24*(1+Premissas!$B$10) -> -666.53888 | E41: =-(IFERROR(E22/Premissas!$B$23,0)+IFERROR(E23/Premissas!$C$23,0)+IFERROR(E24/Premissas!$D$23,0)+IFERROR(E25/Premissas!$E$23,0))*Premissas!$B$24*(1+Premissas!$B$10) -> -987.07725 | F41: =-(IFERROR(F22/Premissas!$B$23,0)+IFERROR(F23/Premissas!$C$23,0)+IFERROR(F24/Premissas!$D$23,0)+IFERROR(F25/Premissas!$E$23,0))*Premissas!$B$24*(1+Premissas!$B$10) -> -1299.3684 | G41: =-(IFERROR(G22/Premissas!$B$23,0)+IFERROR(G23/Premissas!$C$23,0)+IFERROR(G24/Premissas!$D$23,0)+IFERROR(G25/Premissas!$E$23,0))*Premissas!$B$24*(1+Premissas!$B$10) -> -1603.5905 | H41: =-(IFERROR(H22/Premissas!$B$23,0)+IFERROR(H23/Premissas!$C$23,0)+IFERROR(H24/Premissas!$D$23,0)+IFERROR(H25/Premissas!$E$23,0))*Premissas!$B$24*(1+Premissas!$B$10) -> -1899.9201 | I41: =-(IFERROR(I22/Premissas!$B$23,0)+IFERROR(I23/Premissas!$C$23,0)+IFERROR(I24/Premissas!$D$23,0)+IFERROR(I25/Premissas!$E$23,0))*Premissas!$B$24*(1+Premissas!$B$10) -> -2188.5319 | J41: =-(IFERROR(J22/Premissas!$B$23,0)+IFERROR(J23/Premissas!$C$23,0)+IFERROR(J24/Premissas!$D$23,0)+IFERROR(J25/Premissas!$E$23,0))*Premissas!$B$24*(1+Premissas!$B$10) -> -2469.5987 | ... BJ41: =-(IFERROR(BJ22/Premissas!$B$23,0)+IFERROR(BJ23/Premissas!$C$23,0)+IFERROR(BJ24/Premissas!$D$23,0)+IFERROR(BJ25/Premissas!$E$23,0))*Premissas!$B$24*(1+Premissas!$B$10) -> -350353.78
A42: Meio de pagamento | C42: =-C35*Premissas!$B$9 -> -378.82031 | D42: =-D35*Premissas!$B$9 -> -613.39795 | E42: =-E35*Premissas!$B$9 -> -839.67912 | F42: =-F35*Premissas!$B$9 -> -1057.9767 | G42: =-G35*Premissas!$B$9 -> -1268.5907 | H42: =-H35*Premissas!$B$9 -> -1471.8089 | I42: =-I35*Premissas!$B$9 -> -1667.9071 | J42: =-J35*Premissas!$B$9 -> -1857.1503 | ... BJ42: =-BJ35*Premissas!$B$9 -> -134172.86
A43: Custo do serviço total | C43: =SUM(C39:C42) -> -1325.2743 | D43: =SUM(D39:D42) -> -2475.5702 | E43: =SUM(E39:E42) -> -3587.881 | F43: =SUM(F39:F42) -> -4663.5281 | G43: =SUM(G39:G42) -> -5703.7829 | H43: =SUM(H39:H42) -> -6709.869 | I43: =SUM(I39:I42) -> -7682.9642 | J43: =SUM(J39:J42) -> -8624.2026 | ... BJ43: =SUM(BJ39:BJ42) -> -768127.07
A44: Lucro bruto | C44: =C37+C43 -> 8307.585 | D44: =D37+D43 -> 13122.263 | E44: =E37+E43 -> 17763.96 | F44: =F37+F43 -> 22239.308 | G44: =G37+G43 -> 26554.667 | H44: =H37+H43 -> 30716.128 | I44: =I37+I43 -> 34729.532 | J44: =J37+J43 -> 38600.476 | ... BJ44: =BJ37+BJ43 -> 2439371
A45: Margem bruta (% da receita líquida) | C45: =IFERROR(C44/C37,0) -> 0.8624215 | D45: =IFERROR(D44/D37,0) -> 0.84128756 | E45: =IFERROR(E44/E37,0) -> 0.83196385 | F45: =IFERROR(F44/F37,0) -> 0.82665292 | G45: =IFERROR(G44/G37,0) -> 0.82318484 | H45: =IFERROR(H44/H37,0) -> 0.82071636 | I45: =IFERROR(I44/I37,0) -> 0.8188514 | J45: =IFERROR(J44/J37,0) -> 0.81737933 | ... BJ45: =IFERROR(BJ44/BJ37,0) -> 0.76052143
A46: Despesas operacionais (R$)
A47: Pessoal | C47: =-INDEX(Premissas!$D$67:$H$67,C$4) -> -160550 | D47: =-INDEX(Premissas!$D$67:$H$67,D$4) -> -160550 | E47: =-INDEX(Premissas!$D$67:$H$67,E$4) -> -160550 | F47: =-INDEX(Premissas!$D$67:$H$67,F$4) -> -160550 | G47: =-INDEX(Premissas!$D$67:$H$67,G$4) -> -160550 | H47: =-INDEX(Premissas!$D$67:$H$67,H$4) -> -160550 | I47: =-INDEX(Premissas!$D$67:$H$67,I$4) -> -160550 | J47: =-INDEX(Premissas!$D$67:$H$67,J$4) -> -160550 | ... BJ47: =-INDEX(Premissas!$D$67:$H$67,BJ$4) -> -1142100
A48: Mídia paga e inbound | C48: =-C7 -> -20000 | D48: =-D7 -> -20000 | E48: =-E7 -> -20000 | F48: =-F7 -> -20000 | G48: =-G7 -> -20000 | H48: =-H7 -> -20000 | I48: =-I7 -> -20000 | J48: =-J7 -> -20000 | ... BJ48: =-BJ7 -> -256000
A49: Comissões de vendas (10% do primeiro mês dos novos) | C49: =-0.1*(C14*Premissas!$B$18+C15*Premissas!$C$18+C16*Premissas!$D$18+C17*Premissas!$E$18) -> -700.11043 | D49: =-0.1*(D14*Premissas!$B$18+D15*Premissas!$C$18+D16*Premissas!$D$18+D17*Premissas!$E$18) -> -705.0112 | E49: =-0.1*(E14*Premissas!$B$18+E15*Premissas!$C$18+E16*Premissas!$D$18+E17*Premissas!$E$18) -> -709.70737 | F49: =-0.1*(F14*Premissas!$B$18+F15*Premissas!$C$18+F16*Premissas!$D$18+F17*Premissas!$E$18) -> -714.20835 | G49: =-0.1*(G14*Premissas!$B$18+G15*Premissas!$C$18+G16*Premissas!$D$18+G17*Premissas!$E$18) -> -718.52309 | H49: =-0.1*(H14*Premissas!$B$18+H15*Premissas!$C$18+H16*Premissas!$D$18+H17*Premissas!$E$18) -> -722.66008 | I49: =-0.1*(I14*Premissas!$B$18+I15*Premissas!$C$18+I16*Premissas!$D$18+I17*Premissas!$E$18) -> -726.6274 | J49: =-0.1*(J14*Premissas!$B$18+J15*Premissas!$C$18+J16*Premissas!$D$18+J17*Premissas!$E$18) -> -730.43271 | ... BJ49: =-0.1*(BJ14*Premissas!$B$18+BJ15*Premissas!$C$18+BJ16*Premissas!$D$18+BJ17*Premissas!$E$18) -> -20146.422
A50: Jurídico e curadoria normativa | C50: =-INDEX(Premissas!$B$72:$F$72,C$4) -> -5000 | D50: =-INDEX(Premissas!$B$72:$F$72,D$4) -> -5000 | E50: =-INDEX(Premissas!$B$72:$F$72,E$4) -> -5000 | F50: =-INDEX(Premissas!$B$72:$F$72,F$4) -> -5000 | G50: =-INDEX(Premissas!$B$72:$F$72,G$4) -> -5000 | H50: =-INDEX(Premissas!$B$72:$F$72,H$4) -> -5000 | I50: =-INDEX(Premissas!$B$72:$F$72,I$4) -> -5000 | J50: =-INDEX(Premissas!$B$72:$F$72,J$4) -> -5000 | ... BJ50: =-INDEX(Premissas!$B$72:$F$72,BJ$4) -> -25000
A51: Marca: eventos e congressos | C51: =-INDEX(Premissas!$B$73:$F$73,C$4) -> -2000 | D51: =-INDEX(Premissas!$B$73:$F$73,D$4) -> -2000 | E51: =-INDEX(Premissas!$B$73:$F$73,E$4) -> -2000 | F51: =-INDEX(Premissas!$B$73:$F$73,F$4) -> -2000 | G51: =-INDEX(Premissas!$B$73:$F$73,G$4) -> -2000 | H51: =-INDEX(Premissas!$B$73:$F$73,H$4) -> -2000 | I51: =-INDEX(Premissas!$B$73:$F$73,I$4) -> -2000 | J51: =-INDEX(Premissas!$B$73:$F$73,J$4) -> -2000 | ... BJ51: =-INDEX(Premissas!$B$73:$F$73,BJ$4) -> -35000
A52: Ferramentas internas | C52: =-INDEX(Premissas!$B$74:$F$74,C$4) -> -3000 | D52: =-INDEX(Premissas!$B$74:$F$74,D$4) -> -3000 | E52: =-INDEX(Premissas!$B$74:$F$74,E$4) -> -3000 | F52: =-INDEX(Premissas!$B$74:$F$74,F$4) -> -3000 | G52: =-INDEX(Premissas!$B$74:$F$74,G$4) -> -3000 | H52: =-INDEX(Premissas!$B$74:$F$74,H$4) -> -3000 | I52: =-INDEX(Premissas!$B$74:$F$74,I$4) -> -3000 | J52: =-INDEX(Premissas!$B$74:$F$74,J$4) -> -3000 | ... BJ52: =-INDEX(Premissas!$B$74:$F$74,BJ$4) -> -35000
A53: Escritório | C53: =-INDEX(Premissas!$B$75:$F$75,C$4) -> -2000 | D53: =-INDEX(Premissas!$B$75:$F$75,D$4) -> -2000 | E53: =-INDEX(Premissas!$B$75:$F$75,E$4) -> -2000 | F53: =-INDEX(Premissas!$B$75:$F$75,F$4) -> -2000 | G53: =-INDEX(Premissas!$B$75:$F$75,G$4) -> -2000 | H53: =-INDEX(Premissas!$B$75:$F$75,H$4) -> -2000 | I53: =-INDEX(Premissas!$B$75:$F$75,I$4) -> -2000 | J53: =-INDEX(Premissas!$B$75:$F$75,J$4) -> -2000 | ... BJ53: =-INDEX(Premissas!$B$75:$F$75,BJ$4) -> -35000
A54: Contabilidade, seguros e outros | C54: =-INDEX(Premissas!$B$76:$F$76,C$4) -> -3000 | D54: =-INDEX(Premissas!$B$76:$F$76,D$4) -> -3000 | E54: =-INDEX(Premissas!$B$76:$F$76,E$4) -> -3000 | F54: =-INDEX(Premissas!$B$76:$F$76,F$4) -> -3000 | G54: =-INDEX(Premissas!$B$76:$F$76,G$4) -> -3000 | H54: =-INDEX(Premissas!$B$76:$F$76,H$4) -> -3000 | I54: =-INDEX(Premissas!$B$76:$F$76,I$4) -> -3000 | J54: =-INDEX(Premissas!$B$76:$F$76,J$4) -> -3000 | ... BJ54: =-INDEX(Premissas!$B$76:$F$76,BJ$4) -> -20000
A55: Despesas operacionais totais | C55: =SUM(C47:C54) -> -196250.11 | D55: =SUM(D47:D54) -> -196255.01 | E55: =SUM(E47:E54) -> -196259.71 | F55: =SUM(F47:F54) -> -196264.21 | G55: =SUM(G47:G54) -> -196268.52 | H55: =SUM(H47:H54) -> -196272.66 | I55: =SUM(I47:I54) -> -196276.63 | J55: =SUM(J47:J54) -> -196280.43 | ... BJ55: =SUM(BJ47:BJ54) -> -1568246.4
A56: EBITDA | C56: =C44+C55 -> -187942.53 | D56: =D44+D55 -> -183132.75 | E56: =E44+E55 -> -178495.75 | F56: =F44+F55 -> -174024.9 | G56: =G44+G55 -> -169713.86 | H56: =H44+H55 -> -165556.53 | I56: =I44+I55 -> -161547.1 | J56: =J44+J55 -> -157679.96 | ... BJ56: =BJ44+BJ55 -> 871124.61
A57: Margem EBITDA (% da receita líquida) | C57: =IFERROR(C56/C37,0) -> -19.510565 | D57: =IFERROR(D56/D37,0) -> -11.740909 | E57: =IFERROR(E56/E37,0) -> -8.3597359 | F57: =IFERROR(F56/F37,0) -> -6.4686451 | G57: =IFERROR(G56/G37,0) -> -5.2610667 | H57: =IFERROR(H56/H37,0) -> -4.4235704 | I57: =IFERROR(I56/I37,0) -> -3.8089505 | J57: =IFERROR(J56/J37,0) -> -3.3389313 | ... BJ57: =IFERROR(BJ56/BJ37,0) -> 0.27159006
A58: Caixa (R$)
A59: Aportes de capital | C59: =IF(C$3=1,Premissas!$B$14,0)+IF(C$3=INDEX(Premissas!$B$53:$D$53,$B$2),INDEX(Premissas!$B$52:$D$52,$B$2),0) -> 3300000 | D59: =IF(D$3=1,Premissas!$B$14,0)+IF(D$3=INDEX(Premissas!$B$53:$D$53,$B$2),INDEX(Premissas!$B$52:$D$52,$B$2),0) -> 0 | E59: =IF(E$3=1,Premissas!$B$14,0)+IF(E$3=INDEX(Premissas!$B$53:$D$53,$B$2),INDEX(Premissas!$B$52:$D$52,$B$2),0) -> 0 | F59: =IF(F$3=1,Premissas!$B$14,0)+IF(F$3=INDEX(Premissas!$B$53:$D$53,$B$2),INDEX(Premissas!$B$52:$D$52,$B$2),0) -> 0 | G59: =IF(G$3=1,Premissas!$B$14,0)+IF(G$3=INDEX(Premissas!$B$53:$D$53,$B$2),INDEX(Premissas!$B$52:$D$52,$B$2),0) -> 0 | H59: =IF(H$3=1,Premissas!$B$14,0)+IF(H$3=INDEX(Premissas!$B$53:$D$53,$B$2),INDEX(Premissas!$B$52:$D$52,$B$2),0) -> 0 | I59: =IF(I$3=1,Premissas!$B$14,0)+IF(I$3=INDEX(Premissas!$B$53:$D$53,$B$2),INDEX(Premissas!$B$52:$D$52,$B$2),0) -> 0 | J59: =IF(J$3=1,Premissas!$B$14,0)+IF(J$3=INDEX(Premissas!$B$53:$D$53,$B$2),INDEX(Premissas!$B$52:$D$52,$B$2),0) -> 0 | ... BJ59: =IF(BJ$3=1,Premissas!$B$14,0)+IF(BJ$3=INDEX(Premissas!$B$53:$D$53,$B$2),INDEX(Premissas!$B$52:$D$52,$B$2),0) -> 0
A60: Saldo de caixa no fim do mês | C60: =C59+C56 -> 3112057.5 | D60: =C60+D59+D56 -> 2928924.7 | E60: =D60+E59+E56 -> 2750429 | F60: =E60+F59+F56 -> 2576404.1 | G60: =F60+G59+G56 -> 2406690.2 | H60: =G60+H59+H56 -> 2241133.7 | I60: =H60+I59+I56 -> 2079586.6 | J60: =I60+J59+J56 -> 1921906.6 | K60: =J60+K59+K56 -> 1767956.9 | ... BJ60: =BI60+BJ59+BJ56 -> 2158744.3
A61: Indicadores
A62: ARR (MRR × 12) | C62: =C32*12 -> 80232.655 | D62: =D32*12 -> 157622.74 | E62: =E32*12 -> 232277.74 | F62: =F32*12 -> 304300.69 | G62: =G32*12 -> 373790.39 | H62: =H32*12 -> 440841.61 | I62: =I32*12 -> 505545.24 | J62: =J32*12 -> 567988.5 | ... BJ62: =BJ32*12 -> 40211471
A63: Receita recorrente média por cliente (ARPA) | C63: =IFERROR(C32/C26,0) -> 589.235 | D63: =IFERROR(D32/D26,0) -> 591.13695 | E63: =IFERROR(E32/E26,0) -> 592.99976 | F63: =IFERROR(F32/F26,0) -> 594.8238 | G63: =IFERROR(G32/G26,0) -> 596.60949 | H63: =IFERROR(H32/H26,0) -> 598.35725 | I63: =IFERROR(I32/I26,0) -> 600.06752 | J63: =IFERROR(J32/J26,0) -> 601.74075 | ... BJ63: =IFERROR(BJ32/BJ26,0) -> 949.39602
A64: Churn mensal total (% da base do mês anterior) | C64: =0 -> 0 | D64: =IFERROR(SUM(D18:D21)/C26,0) -> 0.04875 | E64: =IFERROR(SUM(E18:E21)/D26,0) -> 0.048658305 | F64: =IFERROR(SUM(F18:F21)/E26,0) -> 0.048568675 | G64: =IFERROR(SUM(G18:G21)/F26,0) -> 0.048481085 | H64: =IFERROR(SUM(H18:H21)/G26,0) -> 0.04839551 | I64: =IFERROR(SUM(I18:I21)/H26,0) -> 0.048311923 | J64: =IFERROR(SUM(J18:J21)/I26,0) -> 0.048230295 | K64: =IFERROR(SUM(K18:K21)/J26,0) -> 0.0481506 | ... BJ64: =IFERROR(SUM(BJ18:BJ21)/BI26,0) -> 0.030492253
A65: Mês com EBITDA positivo daí em diante (auxiliar) | C65: =IF(MIN(C56:$BJ56)>0,C$3,999) -> 999 | D65: =IF(MIN(D56:$BJ56)>0,D$3,999) -> 999 | E65: =IF(MIN(E56:$BJ56)>0,E$3,999) -> 999 | F65: =IF(MIN(F56:$BJ56)>0,F$3,999) -> 999 | G65: =IF(MIN(G56:$BJ56)>0,G$3,999) -> 999 | H65: =IF(MIN(H56:$BJ56)>0,H$3,999) -> 999 | I65: =IF(MIN(I56:$BJ56)>0,I$3,999) -> 999 | J65: =IF(MIN(J56:$BJ56)>0,J$3,999) -> 999 | ... BJ65: =IF(MIN(BJ56:$BJ56)>0,BJ$3,999) -> 60

Sheet Modelo_Base
A1: Jalecon: projeção mensal, cenário base
A2: Cenário (1 = conservador, 2 = base, 3 = otimista) | B2: 2
A3: Mês | C3: 1 | D3: =C3+1 -> 2 | E3: =D3+1 -> 3 | F3: =E3+1 -> 4 | G3: =F3+1 -> 5 | H3: =G3+1 -> 6 | I3: =H3+1 -> 7 | J3: =I3+1 -> 8 | K3: =J3+1 -> 9 | ... BJ3: =BI3+1 -> 60
A4: Ano | C4: =ROUNDUP(C3/12,0) -> 1 | D4: =ROUNDUP(D3/12,0) -> 1 | E4: =ROUNDUP(E3/12,0) -> 1 | F4: =ROUNDUP(F3/12,0) -> 1 | G4: =ROUNDUP(G3/12,0) -> 1 | H4: =ROUNDUP(H3/12,0) -> 1 | I4: =ROUNDUP(I3/12,0) -> 1 | J4: =ROUNDUP(J3/12,0) -> 1 | ... BJ4: =ROUNDUP(BJ3/12,0) -> 5
A6: Aquisição
A7: Orçamento de mídia paga (R$) | C7: =INDEX(Premissas!$B$37:$F$37,C$4)*INDEX(Premissas!$B$51:$D$51,$B$2) -> 25000 | D7: =INDEX(Premissas!$B$37:$F$37,D$4)*INDEX(Premissas!$B$51:$D$51,$B$2) -> 25000 | E7: =INDEX(Premissas!$B$37:$F$37,E$4)*INDEX(Premissas!$B$51:$D$51,$B$2) -> 25000 | F7: =INDEX(Premissas!$B$37:$F$37,F$4)*INDEX(Premissas!$B$51:$D$51,$B$2) -> 25000 | G7: =INDEX(Premissas!$B$37:$F$37,G$4)*INDEX(Premissas!$B$51:$D$51,$B$2) -> 25000 | H7: =INDEX(Premissas!$B$37:$F$37,H$4)*INDEX(Premissas!$B$51:$D$51,$B$2) -> 25000 | I7: =INDEX(Premissas!$B$37:$F$37,I$4)*INDEX(Premissas!$B$51:$D$51,$B$2) -> 25000 | J7: =INDEX(Premissas!$B$37:$F$37,J$4)*INDEX(Premissas!$B$51:$D$51,$B$2) -> 25000 | ... BJ7: =INDEX(Premissas!$B$37:$F$37,BJ$4)*INDEX(Premissas!$B$51:$D$51,$B$2) -> 320000
A8: CAC de mídia paga (R$) | C8: =INDEX(Premissas!$B$42:$F$42,C$4)*INDEX(Premissas!$B$47:$D$47,$B$2) -> 1800 | D8: =INDEX(Premissas!$B$42:$F$42,D$4)*INDEX(Premissas!$B$47:$D$47,$B$2) -> 1800 | E8: =INDEX(Premissas!$B$42:$F$42,E$4)*INDEX(Premissas!$B$47:$D$47,$B$2) -> 1800 | F8: =INDEX(Premissas!$B$42:$F$42,F$4)*INDEX(Premissas!$B$47:$D$47,$B$2) -> 1800 | G8: =INDEX(Premissas!$B$42:$F$42,G$4)*INDEX(Premissas!$B$47:$D$47,$B$2) -> 1800 | H8: =INDEX(Premissas!$B$42:$F$42,H$4)*INDEX(Premissas!$B$47:$D$47,$B$2) -> 1800 | I8: =INDEX(Premissas!$B$42:$F$42,I$4)*INDEX(Premissas!$B$47:$D$47,$B$2) -> 1800 | J8: =INDEX(Premissas!$B$42:$F$42,J$4)*INDEX(Premissas!$B$47:$D$47,$B$2) -> 1800 | ... BJ8: =INDEX(Premissas!$B$42:$F$42,BJ$4)*INDEX(Premissas!$B$47:$D$47,$B$2) -> 1346.4936
A9: Novos clientes: mídia paga | C9: =IFERROR(C7/C8,0) -> 13.888889 | D9: =IFERROR(D7/D8,0) -> 13.888889 | E9: =IFERROR(E7/E8,0) -> 13.888889 | F9: =IFERROR(F7/F8,0) -> 13.888889 | G9: =IFERROR(G7/G8,0) -> 13.888889 | H9: =IFERROR(H7/H8,0) -> 13.888889 | I9: =IFERROR(I7/I8,0) -> 13.888889 | J9: =IFERROR(J7/J8,0) -> 13.888889 | ... BJ9: =IFERROR(BJ7/BJ8,0) -> 237.6543
A10: Novos clientes: parcerias | C10: =INDEX(Premissas!$B$38:$F$38,C$4)*INDEX(Premissas!$B$49:$D$49,$B$2) -> 4 | D10: =INDEX(Premissas!$B$38:$F$38,D$4)*INDEX(Premissas!$B$49:$D$49,$B$2) -> 4 | E10: =INDEX(Premissas!$B$38:$F$38,E$4)*INDEX(Premissas!$B$49:$D$49,$B$2) -> 4 | F10: =INDEX(Premissas!$B$38:$F$38,F$4)*INDEX(Premissas!$B$49:$D$49,$B$2) -> 4 | G10: =INDEX(Premissas!$B$38:$F$38,G$4)*INDEX(Premissas!$B$49:$D$49,$B$2) -> 4 | H10: =INDEX(Premissas!$B$38:$F$38,H$4)*INDEX(Premissas!$B$49:$D$49,$B$2) -> 4 | I10: =INDEX(Premissas!$B$38:$F$38,I$4)*INDEX(Premissas!$B$49:$D$49,$B$2) -> 4 | J10: =INDEX(Premissas!$B$38:$F$38,J$4)*INDEX(Premissas!$B$49:$D$49,$B$2) -> 4 | ... BJ10: =INDEX(Premissas!$B$38:$F$38,BJ$4)*INDEX(Premissas!$B$49:$D$49,$B$2) -> 55
A11: Novos clientes: indicação | C11: =0 -> 0 | D11: =C26*Premissas!$B$43*INDEX(Premissas!$B$49:$D$49,$B$2) -> 0.17888889 | E11: =D26*Premissas!$B$43*INDEX(Premissas!$B$49:$D$49,$B$2) -> 0.35285833 | F11: =E26*Premissas!$B$43*INDEX(Premissas!$B$49:$D$49,$B$2) -> 0.52206263 | G11: =F26*Premissas!$B$43*INDEX(Premissas!$B$49:$D$49,$B$2) -> 0.68665051 | H11: =G26*Premissas!$B$43*INDEX(Premissas!$B$49:$D$49,$B$2) -> 0.84676541 | I11: =H26*Premissas!$B$43*INDEX(Premissas!$B$49:$D$49,$B$2) -> 1.0025456 | J11: =I26*Premissas!$B$43*INDEX(Premissas!$B$49:$D$49,$B$2) -> 1.1541246 | K11: =J26*Premissas!$B$43*INDEX(Premissas!$B$49:$D$49,$B$2) -> 1.301631 | ... BJ11: =BI26*Premissas!$B$43*INDEX(Premissas!$B$49:$D$49,$B$2) -> 62.577373
A12: Novos clientes: total | C12: =C9+C10+C11 -> 17.888889 | D12: =D9+D10+D11 -> 18.067778 | E12: =E9+E10+E11 -> 18.241747 | F12: =F9+F10+F11 -> 18.410952 | G12: =G9+G10+G11 -> 18.575539 | H12: =H9+H10+H11 -> 18.735654 | I12: =I9+I10+I11 -> 18.891435 | J12: =J9+J10+J11 -> 19.043013 | ... BJ12: =BJ9+BJ10+BJ11 -> 355.23167
A13: Clientes por plano
A14: Novos: Essencial | C14: =C12*INDEX(Premissas!$B$29:$B$33,C$4) -> 7.1555556 | D14: =D12*INDEX(Premissas!$B$29:$B$33,D$4) -> 7.2271111 | E14: =E12*INDEX(Premissas!$B$29:$B$33,E$4) -> 7.2966989 | F14: =F12*INDEX(Premissas!$B$29:$B$33,F$4) -> 7.3643806 | G14: =G12*INDEX(Premissas!$B$29:$B$33,G$4) -> 7.4302158 | H14: =H12*INDEX(Premissas!$B$29:$B$33,H$4) -> 7.4942617 | I14: =I12*INDEX(Premissas!$B$29:$B$33,I$4) -> 7.5565738 | J14: =J12*INDEX(Premissas!$B$29:$B$33,J$4) -> 7.6172054 | ... BJ14: =BJ12*INDEX(Premissas!$B$29:$B$33,BJ$4) -> 88.807919
A15: Novos: Consultório | C15: =C12*INDEX(Premissas!$C$29:$C$33,C$4) -> 8.9444444 | D15: =D12*INDEX(Premissas!$C$29:$C$33,D$4) -> 9.0338889 | E15: =E12*INDEX(Premissas!$C$29:$C$33,E$4) -> 9.1208736 | F15: =F12*INDEX(Premissas!$C$29:$C$33,F$4) -> 9.2054758 | G15: =G12*INDEX(Premissas!$C$29:$C$33,G$4) -> 9.2877697 | H15: =H12*INDEX(Premissas!$C$29:$C$33,H$4) -> 9.3678272 | I15: =I12*INDEX(Premissas!$C$29:$C$33,I$4) -> 9.4457173 | J15: =J12*INDEX(Premissas!$C$29:$C$33,J$4) -> 9.5215067 | ... BJ15: =BJ12*INDEX(Premissas!$C$29:$C$33,BJ$4) -> 177.61584
A16: Novos: Autoridade | C16: =C12*INDEX(Premissas!$D$29:$D$33,C$4) -> 1.7888889 | D16: =D12*INDEX(Premissas!$D$29:$D$33,D$4) -> 1.8067778 | E16: =E12*INDEX(Premissas!$D$29:$D$33,E$4) -> 1.8241747 | F16: =F12*INDEX(Premissas!$D$29:$D$33,F$4) -> 1.8410952 | G16: =G12*INDEX(Premissas!$D$29:$D$33,G$4) -> 1.8575539 | H16: =H12*INDEX(Premissas!$D$29:$D$33,H$4) -> 1.8735654 | I16: =I12*INDEX(Premissas!$D$29:$D$33,I$4) -> 1.8891435 | J16: =J12*INDEX(Premissas!$D$29:$D$33,J$4) -> 1.9043013 | ... BJ16: =BJ12*INDEX(Premissas!$D$29:$D$33,BJ$4) -> 63.941701
A17: Novos: Clínica | C17: =C12*INDEX(Premissas!$E$29:$E$33,C$4) -> 0 | D17: =D12*INDEX(Premissas!$E$29:$E$33,D$4) -> 0 | E17: =E12*INDEX(Premissas!$E$29:$E$33,E$4) -> 0 | F17: =F12*INDEX(Premissas!$E$29:$E$33,F$4) -> 0 | G17: =G12*INDEX(Premissas!$E$29:$E$33,G$4) -> 0 | H17: =H12*INDEX(Premissas!$E$29:$E$33,H$4) -> 0 | I17: =I12*INDEX(Premissas!$E$29:$E$33,I$4) -> 0 | J17: =J12*INDEX(Premissas!$E$29:$E$33,J$4) -> 0 | ... BJ17: =BJ12*INDEX(Premissas!$E$29:$E$33,BJ$4) -> 24.866217
A18: Cancelamentos: Essencial | C18: =0 -> 0 | D18: =C22*Premissas!$B$20*INDEX(Premissas!$B$48:$D$48,$B$2)*(1-Premissas!$B$25)^(D$4-1) -> 0.35777778 | E18: =D22*Premissas!$B$20*INDEX(Premissas!$B$48:$D$48,$B$2)*(1-Premissas!$B$25)^(E$4-1) -> 0.70124444 | F18: =E22*Premissas!$B$20*INDEX(Premissas!$B$48:$D$48,$B$2)*(1-Premissas!$B$25)^(F$4-1) -> 1.0310172 | G18: =F22*Premissas!$B$20*INDEX(Premissas!$B$48:$D$48,$B$2)*(1-Premissas!$B$25)^(G$4-1) -> 1.3476853 | H18: =G22*Premissas!$B$20*INDEX(Premissas!$B$48:$D$48,$B$2)*(1-Premissas!$B$25)^(H$4-1) -> 1.6518119 | I18: =H22*Premissas!$B$20*INDEX(Premissas!$B$48:$D$48,$B$2)*(1-Premissas!$B$25)^(I$4-1) -> 1.9439344 | J18: =I22*Premissas!$B$20*INDEX(Premissas!$B$48:$D$48,$B$2)*(1-Premissas!$B$25)^(J$4-1) -> 2.2245663 | K18: =J22*Premissas!$B$20*INDEX(Premissas!$B$48:$D$48,$B$2)*(1-Premissas!$B$25)^(K$4-1) -> 2.4941983 | ... BJ18: =BI22*Premissas!$B$20*INDEX(Premissas!$B$48:$D$48,$B$2)*(1-Premissas!$B$25)^(BJ$4-1) -> 51.4491
A19: Cancelamentos: Consultório | C19: =0 -> 0 | D19: =C23*Premissas!$C$20*INDEX(Premissas!$B$48:$D$48,$B$2)*(1-Premissas!$B$25)^(D$4-1) -> 0.26833333 | E19: =D23*Premissas!$C$20*INDEX(Premissas!$B$48:$D$48,$B$2)*(1-Premissas!$B$25)^(E$4-1) -> 0.5313 | F19: =E23*Premissas!$C$20*INDEX(Premissas!$B$48:$D$48,$B$2)*(1-Premissas!$B$25)^(F$4-1) -> 0.78898721 | G19: =F23*Premissas!$C$20*INDEX(Premissas!$B$48:$D$48,$B$2)*(1-Premissas!$B$25)^(G$4-1) -> 1.0414819 | H19: =G23*Premissas!$C$20*INDEX(Premissas!$B$48:$D$48,$B$2)*(1-Premissas!$B$25)^(H$4-1) -> 1.2888705 | I19: =H23*Premissas!$C$20*INDEX(Premissas!$B$48:$D$48,$B$2)*(1-Premissas!$B$25)^(I$4-1) -> 1.5312392 | J19: =I23*Premissas!$C$20*INDEX(Premissas!$B$48:$D$48,$B$2)*(1-Premissas!$B$25)^(J$4-1) -> 1.7686735 | K19: =J23*Premissas!$C$20*INDEX(Premissas!$B$48:$D$48,$B$2)*(1-Premissas!$B$25)^(K$4-1) -> 2.0012585 | ... BJ19: =BI23*Premissas!$C$20*INDEX(Premissas!$B$48:$D$48,$B$2)*(1-Premissas!$B$25)^(BJ$4-1) -> 69.757831
A20: Cancelamentos: Autoridade | C20: =0 -> 0 | D20: =C24*Premissas!$D$20*INDEX(Premissas!$B$48:$D$48,$B$2)*(1-Premissas!$B$25)^(D$4-1) -> 0.044722222 | E20: =D24*Premissas!$D$20*INDEX(Premissas!$B$48:$D$48,$B$2)*(1-Premissas!$B$25)^(E$4-1) -> 0.088773611 | F20: =E24*Premissas!$D$20*INDEX(Premissas!$B$48:$D$48,$B$2)*(1-Premissas!$B$25)^(F$4-1) -> 0.13215864 | G20: =F24*Premissas!$D$20*INDEX(Premissas!$B$48:$D$48,$B$2)*(1-Premissas!$B$25)^(G$4-1) -> 0.17488205 | H20: =G24*Premissas!$D$20*INDEX(Premissas!$B$48:$D$48,$B$2)*(1-Premissas!$B$25)^(H$4-1) -> 0.21694885 | I20: =H24*Premissas!$D$20*INDEX(Premissas!$B$48:$D$48,$B$2)*(1-Premissas!$B$25)^(I$4-1) -> 0.25836426 | J20: =I24*Premissas!$D$20*INDEX(Premissas!$B$48:$D$48,$B$2)*(1-Premissas!$B$25)^(J$4-1) -> 0.29913374 | K20: =J24*Premissas!$D$20*INDEX(Premissas!$B$48:$D$48,$B$2)*(1-Premissas!$B$25)^(K$4-1) -> 0.33926293 | ... BJ20: =BI24*Premissas!$D$20*INDEX(Premissas!$B$48:$D$48,$B$2)*(1-Premissas!$B$25)^(BJ$4-1) -> 20.397637
A21: Cancelamentos: Clínica | C21: =0 -> 0 | D21: =C25*Premissas!$E$20*INDEX(Premissas!$B$48:$D$48,$B$2)*(1-Premissas!$B$25)^(D$4-1) -> 0 | E21: =D25*Premissas!$E$20*INDEX(Premissas!$B$48:$D$48,$B$2)*(1-Premissas!$B$25)^(E$4-1) -> 0 | F21: =E25*Premissas!$E$20*INDEX(Premissas!$B$48:$D$48,$B$2)*(1-Premissas!$B$25)^(F$4-1) -> 0 | G21: =F25*Premissas!$E$20*INDEX(Premissas!$B$48:$D$48,$B$2)*(1-Premissas!$B$25)^(G$4-1) -> 0 | H21: =G25*Premissas!$E$20*INDEX(Premissas!$B$48:$D$48,$B$2)*(1-Premissas!$B$25)^(H$4-1) -> 0 | I21: =H25*Premissas!$E$20*INDEX(Premissas!$B$48:$D$48,$B$2)*(1-Premissas!$B$25)^(I$4-1) -> 0 | J21: =I25*Premissas!$E$20*INDEX(Premissas!$B$48:$D$48,$B$2)*(1-Premissas!$B$25)^(J$4-1) -> 0 | K21: =J25*Premissas!$E$20*INDEX(Premissas!$B$48:$D$48,$B$2)*(1-Premissas!$B$25)^(K$4-1) -> 0 | ... BJ21: =BI25*Premissas!$E$20*INDEX(Premissas!$B$48:$D$48,$B$2)*(1-Premissas!$B$25)^(BJ$4-1) -> 6.2570084
A22: Ativos: Essencial | C22: =C14-C18 -> 7.1555556 | D22: =C22+D14-D18 -> 14.024889 | E22: =D22+E14-E18 -> 20.620343 | F22: =E22+F14-F18 -> 26.953707 | G22: =F22+G14-G18 -> 33.036237 | H22: =G22+H14-H18 -> 38.878687 | I22: =H22+I14-I18 -> 44.491327 | J22: =I22+J14-J18 -> 49.883966 | K22: =J22+K14-K18 -> 55.065975 | ... BJ22: =BI22+BJ14-BJ18 -> 1473.6962
A23: Ativos: Consultório | C23: =C15-C19 -> 8.9444444 | D23: =C23+D15-D19 -> 17.71 | E23: =D23+E15-E19 -> 26.299574 | F23: =E23+F15-F19 -> 34.716062 | G23: =F23+G15-G19 -> 42.96235 | H23: =G23+H15-H19 -> 51.041307 | I23: =H23+I15-I19 -> 58.955785 | J23: =I23+J15-J19 -> 66.708618 | K23: =J23+K15-K19 -> 74.302619 | ... BJ23: =BI23+BJ15-BJ19 -> 3353.6479
A24: Ativos: Autoridade | C24: =C16-C20 -> 1.7888889 | D24: =C24+D16-D20 -> 3.5509444 | E24: =D24+E16-E20 -> 5.2863456 | F24: =E24+F16-F20 -> 6.9952821 | G24: =F24+G16-G20 -> 8.677954 | H24: =G24+H16-H20 -> 10.334571 | I24: =H24+I16-I20 -> 11.96535 | J24: =I24+J16-J20 -> 13.570517 | K24: =J24+K16-K20 -> 15.150306 | ... BJ24: =BI24+BJ16-BJ20 -> 1182.4518
A25: Ativos: Clínica | C25: =C17-C21 -> 0 | D25: =C25+D17-D21 -> 0 | E25: =D25+E17-E21 -> 0 | F25: =E25+F17-F21 -> 0 | G25: =F25+G17-G21 -> 0 | H25: =G25+H17-H21 -> 0 | I25: =H25+I17-I21 -> 0 | J25: =I25+J17-J21 -> 0 | K25: =J25+K17-K21 -> 0 | ... BJ25: =BI25+BJ17-BJ21 -> 455.31146
A26: Clientes ativos: total | C26: =SUM(C22:C25) -> 17.888889 | D26: =SUM(D22:D25) -> 35.285833 | E26: =SUM(E22:E25) -> 52.206263 | F26: =SUM(F22:F25) -> 68.665051 | G26: =SUM(G22:G25) -> 84.676541 | H26: =SUM(H22:H25) -> 100.25456 | I26: =SUM(I22:I25) -> 115.41246 | J26: =SUM(J22:J25) -> 130.1631 | ... BJ26: =SUM(BJ22:BJ25) -> 6465.1074
A27: Receita (R$)
A28: Receita recorrente: Essencial | C28: =C22*Premissas!$B$18*(1-Premissas!$B$12*Premissas!$B$13) -> 2029.566 | D28: =D22*Premissas!$B$18*(1-Premissas!$B$12*Premissas!$B$13) -> 3977.9494 | E28: =E22*Premissas!$B$18*(1-Premissas!$B$12*Premissas!$B$13) -> 5848.6511 | F28: =F22*Premissas!$B$18*(1-Premissas!$B$12*Premissas!$B$13) -> 7645.0146 | G28: =G22*Premissas!$B$18*(1-Premissas!$B$12*Premissas!$B$13) -> 9370.2331 | H28: =H22*Premissas!$B$18*(1-Premissas!$B$12*Premissas!$B$13) -> 11027.356 | I28: =I22*Premissas!$B$18*(1-Premissas!$B$12*Premissas!$B$13) -> 12619.297 | J28: =J22*Premissas!$B$18*(1-Premissas!$B$12*Premissas!$B$13) -> 14148.839 | ... BJ28: =BJ22*Premissas!$B$18*(1-Premissas!$B$12*Premissas!$B$13) -> 417991.82
A29: Receita recorrente: Consultório | C29: =C23*Premissas!$C$18*(1-Premissas!$B$12*Premissas!$B$13) -> 5953.7353 | D29: =D23*Premissas!$C$18*(1-Premissas!$B$12*Premissas!$B$13) -> 11788.396 | E29: =E23*Premissas!$C$18*(1-Premissas!$B$12*Premissas!$B$13) -> 17505.917 | F29: =F23*Premissas!$C$18*(1-Premissas!$B$12*Premissas!$B$13) -> 23108.226 | G29: =G23*Premissas!$C$18*(1-Premissas!$B$12*Premissas!$B$13) -> 28597.244 | H29: =H23*Premissas!$C$18*(1-Premissas!$B$12*Premissas!$B$13) -> 33974.88 | I29: =I23*Premissas!$C$18*(1-Premissas!$B$12*Premissas!$B$13) -> 39243.034 | J29: =J23*Premissas!$C$18*(1-Premissas!$B$12*Premissas!$B$13) -> 44403.591 | ... BJ29: =BJ23*Premissas!$C$18*(1-Premissas!$B$12*Premissas!$B$13) -> 2232305.4
A30: Receita recorrente: Autoridade | C30: =C24*Premissas!$D$18*(1-Premissas!$B$12*Premissas!$B$13) -> 2557.4582 | D30: =D24*Premissas!$D$18*(1-Premissas!$B$12*Premissas!$B$13) -> 5076.5545 | E30: =E24*Premissas!$D$18*(1-Premissas!$B$12*Premissas!$B$13) -> 7557.5446 | F30: =F24*Premissas!$D$18*(1-Premissas!$B$12*Premissas!$B$13) -> 10000.7 | G30: =G24*Premissas!$D$18*(1-Premissas!$B$12*Premissas!$B$13) -> 12406.307 | H30: =H24*Premissas!$D$18*(1-Premissas!$B$12*Premissas!$B$13) -> 14774.664 | I30: =I24*Premissas!$D$18*(1-Premissas!$B$12*Premissas!$B$13) -> 17106.083 | J30: =J24*Premissas!$D$18*(1-Premissas!$B$12*Premissas!$B$13) -> 19400.887 | ... BJ30: =BJ24*Premissas!$D$18*(1-Premissas!$B$12*Premissas!$B$13) -> 1690474.5
A31: Receita recorrente: Clínica | C31: =C25*Premissas!$E$18*(1-Premissas!$B$12*Premissas!$B$13) -> 0 | D31: =D25*Premissas!$E$18*(1-Premissas!$B$12*Premissas!$B$13) -> 0 | E31: =E25*Premissas!$E$18*(1-Premissas!$B$12*Premissas!$B$13) -> 0 | F31: =F25*Premissas!$E$18*(1-Premissas!$B$12*Premissas!$B$13) -> 0 | G31: =G25*Premissas!$E$18*(1-Premissas!$B$12*Premissas!$B$13) -> 0 | H31: =H25*Premissas!$E$18*(1-Premissas!$B$12*Premissas!$B$13) -> 0 | I31: =I25*Premissas!$E$18*(1-Premissas!$B$12*Premissas!$B$13) -> 0 | J31: =J25*Premissas!$E$18*(1-Premissas!$B$12*Premissas!$B$13) -> 0 | ... BJ31: =BJ25*Premissas!$E$18*(1-Premissas!$B$12*Premissas!$B$13) -> 1695807.5
A32: Receita recorrente mensal (MRR) | C32: =SUM(C28:C31) -> 10540.759 | D32: =SUM(D28:D31) -> 20842.9 | E32: =SUM(E28:E31) -> 30912.112 | F32: =SUM(F28:F31) -> 40753.941 | G32: =SUM(G28:G31) -> 50373.784 | H32: =SUM(H28:H31) -> 59776.9 | I32: =SUM(I28:I31) -> 68968.414 | J32: =SUM(J28:J31) -> 77953.316 | ... BJ32: =SUM(BJ28:BJ31) -> 6036579.3
A33: Taxas de implantação | C33: =C14*Premissas!$B$19+C15*Premissas!$C$19+C16*Premissas!$D$19+C17*Premissas!$E$19 -> 6153.7778 | D33: =D14*Premissas!$B$19+D15*Premissas!$C$19+D16*Premissas!$D$19+D17*Premissas!$E$19 -> 6215.3156 | E33: =E14*Premissas!$B$19+E15*Premissas!$C$19+E16*Premissas!$D$19+E17*Premissas!$E$19 -> 6275.161 | F33: =F14*Premissas!$B$19+F15*Premissas!$C$19+F16*Premissas!$D$19+F17*Premissas!$E$19 -> 6333.3673 | G33: =G14*Premissas!$B$19+G15*Premissas!$C$19+G16*Premissas!$D$19+G17*Premissas!$E$19 -> 6389.9856 | H33: =H14*Premissas!$B$19+H15*Premissas!$C$19+H16*Premissas!$D$19+H17*Premissas!$E$19 -> 6445.0651 | I33: =I14*Premissas!$B$19+I15*Premissas!$C$19+I16*Premissas!$D$19+I17*Premissas!$E$19 -> 6498.6535 | J33: =J14*Premissas!$B$19+J15*Premissas!$C$19+J16*Premissas!$D$19+J17*Premissas!$E$19 -> 6550.7966 | ... BJ33: =BJ14*Premissas!$B$19+BJ15*Premissas!$C$19+BJ16*Premissas!$D$19+BJ17*Premissas!$E$19 -> 222446.07
A34: Serviços adicionais | C34: =C32*INDEX(Premissas!$B$39:$F$39,C$4)*INDEX(Premissas!$B$50:$D$50,$B$2) -> 527.03797 | D34: =D32*INDEX(Premissas!$B$39:$F$39,D$4)*INDEX(Premissas!$B$50:$D$50,$B$2) -> 1042.145 | E34: =E32*INDEX(Premissas!$B$39:$F$39,E$4)*INDEX(Premissas!$B$50:$D$50,$B$2) -> 1545.6056 | F34: =F32*INDEX(Premissas!$B$39:$F$39,F$4)*INDEX(Premissas!$B$50:$D$50,$B$2) -> 2037.697 | G34: =G32*INDEX(Premissas!$B$39:$F$39,G$4)*INDEX(Premissas!$B$50:$D$50,$B$2) -> 2518.6892 | H34: =H32*INDEX(Premissas!$B$39:$F$39,H$4)*INDEX(Premissas!$B$50:$D$50,$B$2) -> 2988.845 | I34: =I32*INDEX(Premissas!$B$39:$F$39,I$4)*INDEX(Premissas!$B$50:$D$50,$B$2) -> 3448.4207 | J34: =J32*INDEX(Premissas!$B$39:$F$39,J$4)*INDEX(Premissas!$B$50:$D$50,$B$2) -> 3897.6658 | ... BJ34: =BJ32*INDEX(Premissas!$B$39:$F$39,BJ$4)*INDEX(Premissas!$B$50:$D$50,$B$2) -> 905486.89
A35: Receita bruta | C35: =C32+C33+C34 -> 17221.575 | D35: =D32+D33+D34 -> 28100.36 | E35: =E32+E33+E34 -> 38732.879 | F35: =F32+F33+F34 -> 49125.005 | G35: =G32+G33+G34 -> 59282.458 | H35: =H32+H33+H34 -> 69210.81 | I35: =I32+I33+I34 -> 78915.488 | J35: =J32+J33+J34 -> 88401.778 | ... BJ35: =BJ32+BJ33+BJ34 -> 7164512.2
A36: (-) Impostos sobre receita | C36: =-C35*IF(SUMIFS($C$35:$BJ$35,$C$4:$BJ$4,C$4-1)>Premissas!$B$8,Premissas!$B$7,Premissas!$B$6) -> -1894.3733 | D36: =-D35*IF(SUMIFS($C$35:$BJ$35,$C$4:$BJ$4,D$4-1)>Premissas!$B$8,Premissas!$B$7,Premissas!$B$6) -> -3091.0396 | E36: =-E35*IF(SUMIFS($C$35:$BJ$35,$C$4:$BJ$4,E$4-1)>Premissas!$B$8,Premissas!$B$7,Premissas!$B$6) -> -4260.6167 | F36: =-F35*IF(SUMIFS($C$35:$BJ$35,$C$4:$BJ$4,F$4-1)>Premissas!$B$8,Premissas!$B$7,Premissas!$B$6) -> -5403.7506 | G36: =-G35*IF(SUMIFS($C$35:$BJ$35,$C$4:$BJ$4,G$4-1)>Premissas!$B$8,Premissas!$B$7,Premissas!$B$6) -> -6521.0704 | H36: =-H35*IF(SUMIFS($C$35:$BJ$35,$C$4:$BJ$4,H$4-1)>Premissas!$B$8,Premissas!$B$7,Premissas!$B$6) -> -7613.1891 | I36: =-I35*IF(SUMIFS($C$35:$BJ$35,$C$4:$BJ$4,I$4-1)>Premissas!$B$8,Premissas!$B$7,Premissas!$B$6) -> -8680.7037 | J36: =-J35*IF(SUMIFS($C$35:$BJ$35,$C$4:$BJ$4,J$4-1)>Premissas!$B$8,Premissas!$B$7,Premissas!$B$6) -> -9724.1956 | ... BJ36: =-BJ35*IF(SUMIFS($C$35:$BJ$35,$C$4:$BJ$4,BJ$4-1)>Premissas!$B$8,Premissas!$B$7,Premissas!$B$6) -> -1169964.8
A37: Receita líquida | C37: =C35+C36 -> 15327.202 | D37: =D35+D36 -> 25009.321 | E37: =E35+E36 -> 34472.262 | F37: =F35+F36 -> 43721.255 | G37: =G35+G36 -> 52761.388 | H37: =H35+H36 -> 61597.621 | I37: =I35+I36 -> 70234.784 | J37: =J35+J36 -> 78677.583 | ... BJ37: =BJ35+BJ36 -> 5994547.4
A38: Custo do serviço (R$)
A39: IA (modelos de linguagem e imagem) | C39: =-(C22*Premissas!$B$21+C23*Premissas!$C$21+C24*Premissas!$D$21+C25*Premissas!$E$21)*Premissas!$B$5 -> -763.14 | D39: =-(D22*Premissas!$B$21+D23*Premissas!$C$21+D24*Premissas!$D$21+D25*Premissas!$E$21)*Premissas!$B$5 -> -1508.7954 | E39: =-(E22*Premissas!$B$21+E23*Premissas!$C$21+E24*Premissas!$D$21+E25*Premissas!$E$21)*Premissas!$B$5 -> -2237.3915 | F39: =-(F22*Premissas!$B$21+F23*Premissas!$C$21+F24*Premissas!$D$21+F25*Premissas!$E$21)*Premissas!$B$5 -> -2949.3421 | G39: =-(G22*Premissas!$B$21+G23*Premissas!$C$21+G24*Premissas!$D$21+G25*Premissas!$E$21)*Premissas!$B$5 -> -3645.0501 | H39: =-(H22*Premissas!$B$21+H23*Premissas!$C$21+H24*Premissas!$D$21+H25*Premissas!$E$21)*Premissas!$B$5 -> -4324.9074 | I39: =-(I22*Premissas!$B$21+I23*Premissas!$C$21+I24*Premissas!$D$21+I25*Premissas!$E$21)*Premissas!$B$5 -> -4989.2958 | J39: =-(J22*Premissas!$B$21+J23*Premissas!$C$21+J24*Premissas!$D$21+J25*Premissas!$E$21)*Premissas!$B$5 -> -5638.5868 | ... BJ39: =-(BJ22*Premissas!$B$21+BJ23*Premissas!$C$21+BJ24*Premissas!$D$21+BJ25*Premissas!$E$21)*Premissas!$B$5 -> -420394.13
A40: Infraestrutura e APIs | C40: =-(C22*Premissas!$B$22+C23*Premissas!$C$22+C24*Premissas!$D$22+C25*Premissas!$E$22) -> -196.77778 | D40: =-(D22*Premissas!$B$22+D23*Premissas!$C$22+D24*Premissas!$D$22+D25*Premissas!$E$22) -> -388.63611 | E40: =-(E22*Premissas!$B$22+E23*Premissas!$C$22+E24*Premissas!$D$22+E25*Premissas!$E$22) -> -575.71185 | F40: =-(F22*Premissas!$B$22+F23*Premissas!$C$22+F24*Premissas!$D$22+F25*Premissas!$E$22) -> -758.13748 | G40: =-(G22*Premissas!$B$22+G23*Premissas!$C$22+G24*Premissas!$D$22+G25*Premissas!$E$22) -> -936.04127 | H40: =-(H22*Premissas!$B$22+H23*Premissas!$C$22+H24*Premissas!$D$22+H25*Premissas!$E$22) -> -1109.5474 | I40: =-(I22*Premissas!$B$22+I23*Premissas!$C$22+I24*Premissas!$D$22+I25*Premissas!$E$22) -> -1278.7763 | J40: =-(J22*Premissas!$B$22+J23*Premissas!$C$22+J24*Premissas!$D$22+J25*Premissas!$E$22) -> -1443.8445 | ... BJ40: =-(BJ22*Premissas!$B$22+BJ23*Premissas!$C$22+BJ24*Premissas!$D$22+BJ25*Premissas!$E$22) -> -91529.935
A41: Gestores de conta (revisão humana) | C41: =-(IFERROR(C22/Premissas!$B$23,0)+IFERROR(C23/Premissas!$C$23,0)+IFERROR(C24/Premissas!$D$23,0)+IFERROR(C25/Premissas!$E$23,0))*Premissas!$B$24*(1+Premissas!$B$10) -> -532.19444 | D41: =-(IFERROR(D22/Premissas!$B$23,0)+IFERROR(D23/Premissas!$C$23,0)+IFERROR(D24/Premissas!$D$23,0)+IFERROR(D25/Premissas!$E$23,0))*Premissas!$B$24*(1+Premissas!$B$10) -> -1056.406 | E41: =-(IFERROR(E22/Premissas!$B$23,0)+IFERROR(E23/Premissas!$C$23,0)+IFERROR(E24/Premissas!$D$23,0)+IFERROR(E25/Premissas!$E$23,0))*Premissas!$B$24*(1+Premissas!$B$10) -> -1572.6878 | F41: =-(IFERROR(F22/Premissas!$B$23,0)+IFERROR(F23/Premissas!$C$23,0)+IFERROR(F24/Premissas!$D$23,0)+IFERROR(F25/Premissas!$E$23,0))*Premissas!$B$24*(1+Premissas!$B$10) -> -2081.0964 | G41: =-(IFERROR(G22/Premissas!$B$23,0)+IFERROR(G23/Premissas!$C$23,0)+IFERROR(G24/Premissas!$D$23,0)+IFERROR(G25/Premissas!$E$23,0))*Premissas!$B$24*(1+Premissas!$B$10) -> -2581.6913 | H41: =-(IFERROR(H22/Premissas!$B$23,0)+IFERROR(H23/Premissas!$C$23,0)+IFERROR(H24/Premissas!$D$23,0)+IFERROR(H25/Premissas!$E$23,0))*Premissas!$B$24*(1+Premissas!$B$10) -> -3074.5347 | I41: =-(IFERROR(I22/Premissas!$B$23,0)+IFERROR(I23/Premissas!$C$23,0)+IFERROR(I24/Premissas!$D$23,0)+IFERROR(I25/Premissas!$E$23,0))*Premissas!$B$24*(1+Premissas!$B$10) -> -3559.6915 | J41: =-(IFERROR(J22/Premissas!$B$23,0)+IFERROR(J23/Premissas!$C$23,0)+IFERROR(J24/Premissas!$D$23,0)+IFERROR(J25/Premissas!$E$23,0))*Premissas!$B$24*(1+Premissas!$B$10) -> -4037.2289 | ... BJ41: =-(IFERROR(BJ22/Premissas!$B$23,0)+IFERROR(BJ23/Premissas!$C$23,0)+IFERROR(BJ24/Premissas!$D$23,0)+IFERROR(BJ25/Premissas!$E$23,0))*Premissas!$B$24*(1+Premissas!$B$10) -> -622689.73
A42: Meio de pagamento | C42: =-C35*Premissas!$B$9 -> -602.75513 | D42: =-D35*Premissas!$B$9 -> -983.51261 | E42: =-E35*Premissas!$B$9 -> -1355.6508 | F42: =-F35*Premissas!$B$9 -> -1719.3752 | G42: =-G35*Premissas!$B$9 -> -2074.886 | H42: =-H35*Premissas!$B$9 -> -2422.3784 | I42: =-I35*Premissas!$B$9 -> -2762.0421 | J42: =-J35*Premissas!$B$9 -> -3094.0622 | ... BJ42: =-BJ35*Premissas!$B$9 -> -250757.93
A43: Custo do serviço total | C43: =SUM(C39:C42) -> -2094.8674 | D43: =SUM(D39:D42) -> -3937.3501 | E43: =SUM(E39:E42) -> -5741.4419 | F43: =SUM(F39:F42) -> -7507.9512 | G43: =SUM(G39:G42) -> -9237.6687 | H43: =SUM(H39:H42) -> -10931.368 | I43: =SUM(I39:I42) -> -12589.806 | J43: =SUM(J39:J42) -> -14213.722 | ... BJ43: =SUM(BJ39:BJ42) -> -1385371.7
A44: Lucro bruto | C44: =C37+C43 -> 13232.335 | D44: =D37+D43 -> 21071.97 | E44: =E37+E43 -> 28730.82 | F44: =F37+F43 -> 36213.303 | G44: =G37+G43 -> 43523.719 | H44: =H37+H43 -> 50666.253 | I44: =I37+I43 -> 57644.979 | J44: =J37+J43 -> 64463.86 | ... BJ44: =BJ37+BJ43 -> 4609175.7
A45: Margem bruta (% da receita líquida) | C45: =IFERROR(C44/C37,0) -> 0.86332356 | D45: =IFERROR(D44/D37,0) -> 0.84256469 | E45: =IFERROR(E44/E37,0) -> 0.83344749 | F45: =IFERROR(F44/F37,0) -> 0.82827686 | G45: =IFERROR(G44/G37,0) -> 0.82491612 | H45: =IFERROR(H44/H37,0) -> 0.82253588 | I45: =IFERROR(I44/I37,0) -> 0.82074686 | J45: =IFERROR(J44/J37,0) -> 0.81934216 | ... BJ45: =IFERROR(BJ44/BJ37,0) -> 0.76889469
A46: Despesas operacionais (R$)
A47: Pessoal | C47: =-INDEX(Premissas!$D$67:$H$67,C$4) -> -160550 | D47: =-INDEX(Premissas!$D$67:$H$67,D$4) -> -160550 | E47: =-INDEX(Premissas!$D$67:$H$67,E$4) -> -160550 | F47: =-INDEX(Premissas!$D$67:$H$67,F$4) -> -160550 | G47: =-INDEX(Premissas!$D$67:$H$67,G$4) -> -160550 | H47: =-INDEX(Premissas!$D$67:$H$67,H$4) -> -160550 | I47: =-INDEX(Premissas!$D$67:$H$67,I$4) -> -160550 | J47: =-INDEX(Premissas!$D$67:$H$67,J$4) -> -160550 | ... BJ47: =-INDEX(Premissas!$D$67:$H$67,BJ$4) -> -1142100
A48: Mídia paga e inbound | C48: =-C7 -> -25000 | D48: =-D7 -> -25000 | E48: =-E7 -> -25000 | F48: =-F7 -> -25000 | G48: =-G7 -> -25000 | H48: =-H7 -> -25000 | I48: =-I7 -> -25000 | J48: =-J7 -> -25000 | ... BJ48: =-BJ7 -> -320000
A49: Comissões de vendas (10% do primeiro mês dos novos) | C49: =-0.1*(C14*Premissas!$B$18+C15*Premissas!$C$18+C16*Premissas!$D$18+C17*Premissas!$E$18) -> -1103.7444 | D49: =-0.1*(D14*Premissas!$B$18+D15*Premissas!$C$18+D16*Premissas!$D$18+D17*Premissas!$E$18) -> -1114.7819 | E49: =-0.1*(E14*Premissas!$B$18+E15*Premissas!$C$18+E16*Premissas!$D$18+E17*Premissas!$E$18) -> -1125.5158 | F49: =-0.1*(F14*Premissas!$B$18+F15*Premissas!$C$18+F16*Premissas!$D$18+F17*Premissas!$E$18) -> -1135.9557 | G49: =-0.1*(G14*Premissas!$B$18+G15*Premissas!$C$18+G16*Premissas!$D$18+G17*Premissas!$E$18) -> -1146.1108 | H49: =-0.1*(H14*Premissas!$B$18+H15*Premissas!$C$18+H16*Premissas!$D$18+H17*Premissas!$E$18) -> -1155.9899 | I49: =-0.1*(I14*Premissas!$B$18+I15*Premissas!$C$18+I16*Premissas!$D$18+I17*Premissas!$E$18) -> -1165.6015 | J49: =-0.1*(J14*Premissas!$B$18+J15*Premissas!$C$18+J16*Premissas!$D$18+J17*Premissas!$E$18) -> -1174.9539 | ... BJ49: =-0.1*(BJ14*Premissas!$B$18+BJ15*Premissas!$C$18+BJ16*Premissas!$D$18+BJ17*Premissas!$E$18) -> -34287.316
A50: Jurídico e curadoria normativa | C50: =-INDEX(Premissas!$B$72:$F$72,C$4) -> -5000 | D50: =-INDEX(Premissas!$B$72:$F$72,D$4) -> -5000 | E50: =-INDEX(Premissas!$B$72:$F$72,E$4) -> -5000 | F50: =-INDEX(Premissas!$B$72:$F$72,F$4) -> -5000 | G50: =-INDEX(Premissas!$B$72:$F$72,G$4) -> -5000 | H50: =-INDEX(Premissas!$B$72:$F$72,H$4) -> -5000 | I50: =-INDEX(Premissas!$B$72:$F$72,I$4) -> -5000 | J50: =-INDEX(Premissas!$B$72:$F$72,J$4) -> -5000 | ... BJ50: =-INDEX(Premissas!$B$72:$F$72,BJ$4) -> -25000
A51: Marca: eventos e congressos | C51: =-INDEX(Premissas!$B$73:$F$73,C$4) -> -2000 | D51: =-INDEX(Premissas!$B$73:$F$73,D$4) -> -2000 | E51: =-INDEX(Premissas!$B$73:$F$73,E$4) -> -2000 | F51: =-INDEX(Premissas!$B$73:$F$73,F$4) -> -2000 | G51: =-INDEX(Premissas!$B$73:$F$73,G$4) -> -2000 | H51: =-INDEX(Premissas!$B$73:$F$73,H$4) -> -2000 | I51: =-INDEX(Premissas!$B$73:$F$73,I$4) -> -2000 | J51: =-INDEX(Premissas!$B$73:$F$73,J$4) -> -2000 | ... BJ51: =-INDEX(Premissas!$B$73:$F$73,BJ$4) -> -35000
A52: Ferramentas internas | C52: =-INDEX(Premissas!$B$74:$F$74,C$4) -> -3000 | D52: =-INDEX(Premissas!$B$74:$F$74,D$4) -> -3000 | E52: =-INDEX(Premissas!$B$74:$F$74,E$4) -> -3000 | F52: =-INDEX(Premissas!$B$74:$F$74,F$4) -> -3000 | G52: =-INDEX(Premissas!$B$74:$F$74,G$4) -> -3000 | H52: =-INDEX(Premissas!$B$74:$F$74,H$4) -> -3000 | I52: =-INDEX(Premissas!$B$74:$F$74,I$4) -> -3000 | J52: =-INDEX(Premissas!$B$74:$F$74,J$4) -> -3000 | ... BJ52: =-INDEX(Premissas!$B$74:$F$74,BJ$4) -> -35000
A53: Escritório | C53: =-INDEX(Premissas!$B$75:$F$75,C$4) -> -2000 | D53: =-INDEX(Premissas!$B$75:$F$75,D$4) -> -2000 | E53: =-INDEX(Premissas!$B$75:$F$75,E$4) -> -2000 | F53: =-INDEX(Premissas!$B$75:$F$75,F$4) -> -2000 | G53: =-INDEX(Premissas!$B$75:$F$75,G$4) -> -2000 | H53: =-INDEX(Premissas!$B$75:$F$75,H$4) -> -2000 | I53: =-INDEX(Premissas!$B$75:$F$75,I$4) -> -2000 | J53: =-INDEX(Premissas!$B$75:$F$75,J$4) -> -2000 | ... BJ53: =-INDEX(Premissas!$B$75:$F$75,BJ$4) -> -35000
A54: Contabilidade, seguros e outros | C54: =-INDEX(Premissas!$B$76:$F$76,C$4) -> -3000 | D54: =-INDEX(Premissas!$B$76:$F$76,D$4) -> -3000 | E54: =-INDEX(Premissas!$B$76:$F$76,E$4) -> -3000 | F54: =-INDEX(Premissas!$B$76:$F$76,F$4) -> -3000 | G54: =-INDEX(Premissas!$B$76:$F$76,G$4) -> -3000 | H54: =-INDEX(Premissas!$B$76:$F$76,H$4) -> -3000 | I54: =-INDEX(Premissas!$B$76:$F$76,I$4) -> -3000 | J54: =-INDEX(Premissas!$B$76:$F$76,J$4) -> -3000 | ... BJ54: =-INDEX(Premissas!$B$76:$F$76,BJ$4) -> -20000
A55: Despesas operacionais totais | C55: =SUM(C47:C54) -> -201653.74 | D55: =SUM(D47:D54) -> -201664.78 | E55: =SUM(E47:E54) -> -201675.52 | F55: =SUM(F47:F54) -> -201685.96 | G55: =SUM(G47:G54) -> -201696.11 | H55: =SUM(H47:H54) -> -201705.99 | I55: =SUM(I47:I54) -> -201715.6 | J55: =SUM(J47:J54) -> -201724.95 | ... BJ55: =SUM(BJ47:BJ54) -> -1646387.3
A56: EBITDA | C56: =C44+C55 -> -188421.41 | D56: =D44+D55 -> -180592.81 | E56: =E44+E55 -> -172944.7 | F56: =F44+F55 -> -165472.65 | G56: =G44+G55 -> -158172.39 | H56: =H44+H55 -> -151039.74 | I56: =I44+I55 -> -144070.62 | J56: =J44+J55 -> -137261.09 | ... BJ56: =BJ44+BJ55 -> 2962788.3
A57: Margem EBITDA (% da receita líquida) | C57: =IFERROR(C56/C37,0) -> -12.293269 | D57: =IFERROR(D56/D37,0) -> -7.2210203 | E57: =IFERROR(E56/E37,0) -> -5.0169233 | F57: =IFERROR(F56/F37,0) -> -3.7847188 | G57: =IFERROR(G56/G37,0) -> -2.9978815 | H57: =IFERROR(H56/H37,0) -> -2.4520385 | I57: =IFERROR(I56/I37,0) -> -2.0512717 | J57: =IFERROR(J56/J37,0) -> -1.7446023 | ... BJ57: =IFERROR(BJ56/BJ37,0) -> 0.49424721
A58: Caixa (R$)
A59: Aportes de capital | C59: =IF(C$3=1,Premissas!$B$14,0)+IF(C$3=INDEX(Premissas!$B$53:$D$53,$B$2),INDEX(Premissas!$B$52:$D$52,$B$2),0) -> 3300000 | D59: =IF(D$3=1,Premissas!$B$14,0)+IF(D$3=INDEX(Premissas!$B$53:$D$53,$B$2),INDEX(Premissas!$B$52:$D$52,$B$2),0) -> 0 | E59: =IF(E$3=1,Premissas!$B$14,0)+IF(E$3=INDEX(Premissas!$B$53:$D$53,$B$2),INDEX(Premissas!$B$52:$D$52,$B$2),0) -> 0 | F59: =IF(F$3=1,Premissas!$B$14,0)+IF(F$3=INDEX(Premissas!$B$53:$D$53,$B$2),INDEX(Premissas!$B$52:$D$52,$B$2),0) -> 0 | G59: =IF(G$3=1,Premissas!$B$14,0)+IF(G$3=INDEX(Premissas!$B$53:$D$53,$B$2),INDEX(Premissas!$B$52:$D$52,$B$2),0) -> 0 | H59: =IF(H$3=1,Premissas!$B$14,0)+IF(H$3=INDEX(Premissas!$B$53:$D$53,$B$2),INDEX(Premissas!$B$52:$D$52,$B$2),0) -> 0 | I59: =IF(I$3=1,Premissas!$B$14,0)+IF(I$3=INDEX(Premissas!$B$53:$D$53,$B$2),INDEX(Premissas!$B$52:$D$52,$B$2),0) -> 0 | J59: =IF(J$3=1,Premissas!$B$14,0)+IF(J$3=INDEX(Premissas!$B$53:$D$53,$B$2),INDEX(Premissas!$B$52:$D$52,$B$2),0) -> 0 | ... BJ59: =IF(BJ$3=1,Premissas!$B$14,0)+IF(BJ$3=INDEX(Premissas!$B$53:$D$53,$B$2),INDEX(Premissas!$B$52:$D$52,$B$2),0) -> 0
A60: Saldo de caixa no fim do mês | C60: =C59+C56 -> 3111578.6 | D60: =C60+D59+D56 -> 2930985.8 | E60: =D60+E59+E56 -> 2758041.1 | F60: =E60+F59+F56 -> 2592568.4 | G60: =F60+G59+G56 -> 2434396 | H60: =G60+H59+H56 -> 2283356.3 | I60: =H60+I59+I56 -> 2139285.7 | J60: =I60+J59+J56 -> 2002024.6 | K60: =J60+K59+K56 -> 1871417.3 | ... BJ60: =BI60+BJ59+BJ56 -> 40407675
A61: Indicadores
A62: ARR (MRR × 12) | C62: =C32*12 -> 126489.11 | D62: =D32*12 -> 250114.8 | E62: =E32*12 -> 370945.35 | F62: =F32*12 -> 489047.29 | G62: =G32*12 -> 604485.4 | H62: =H32*12 -> 717322.8 | I62: =I32*12 -> 827620.97 | J62: =J32*12 -> 935439.79 | ... BJ62: =BJ32*12 -> 72438951
A63: Receita recorrente média por cliente (ARPA) | C63: =IFERROR(C32/C26,0) -> 589.235 | D63: =IFERROR(D32/D26,0) -> 590.68747 | E63: =IFERROR(E32/E26,0) -> 592.11502 | F63: =IFERROR(F32/F26,0) -> 593.51796 | G63: =IFERROR(G32/G26,0) -> 594.89657 | H63: =IFERROR(H32/H26,0) -> 596.25116 | I63: =IFERROR(I32/I26,0) -> 597.58204 | J63: =IFERROR(J32/J26,0) -> 598.88951 | ... BJ63: =IFERROR(BJ32/BJ26,0) -> 933.71679
A64: Churn mensal total (% da base do mês anterior) | C64: =0 -> 0 | D64: =IFERROR(SUM(D18:D21)/C26,0) -> 0.0375 | E64: =IFERROR(SUM(E18:E21)/D26,0) -> 0.037446134 | F64: =IFERROR(SUM(F18:F21)/E26,0) -> 0.037393273 | G64: =IFERROR(SUM(G18:G21)/F26,0) -> 0.037341402 | H64: =IFERROR(SUM(H18:H21)/G26,0) -> 0.037290508 | I64: =IFERROR(SUM(I18:I21)/H26,0) -> 0.037240577 | J64: =IFERROR(SUM(J18:J21)/I26,0) -> 0.037191596 | K64: =IFERROR(SUM(K18:K21)/J26,0) -> 0.037143551 | ... BJ64: =IFERROR(SUM(BJ18:BJ21)/BI26,0) -> 0.023628601
A65: Mês com EBITDA positivo daí em diante (auxiliar) | C65: =IF(MIN(C56:$BJ56)>0,C$3,999) -> 999 | D65: =IF(MIN(D56:$BJ56)>0,D$3,999) -> 999 | E65: =IF(MIN(E56:$BJ56)>0,E$3,999) -> 999 | F65: =IF(MIN(F56:$BJ56)>0,F$3,999) -> 999 | G65: =IF(MIN(G56:$BJ56)>0,G$3,999) -> 999 | H65: =IF(MIN(H56:$BJ56)>0,H$3,999) -> 999 | I65: =IF(MIN(I56:$BJ56)>0,I$3,999) -> 999 | J65: =IF(MIN(J56:$BJ56)>0,J$3,999) -> 999 | ... BJ65: =IF(MIN(BJ56:$BJ56)>0,BJ$3,999) -> 60

Sheet Modelo_Otimista
A1: Jalecon: projeção mensal, cenário otimista
A2: Cenário (1 = conservador, 2 = base, 3 = otimista) | B2: 3
A3: Mês | C3: 1 | D3: =C3+1 -> 2 | E3: =D3+1 -> 3 | F3: =E3+1 -> 4 | G3: =F3+1 -> 5 | H3: =G3+1 -> 6 | I3: =H3+1 -> 7 | J3: =I3+1 -> 8 | K3: =J3+1 -> 9 | ... BJ3: =BI3+1 -> 60
A4: Ano | C4: =ROUNDUP(C3/12,0) -> 1 | D4: =ROUNDUP(D3/12,0) -> 1 | E4: =ROUNDUP(E3/12,0) -> 1 | F4: =ROUNDUP(F3/12,0) -> 1 | G4: =ROUNDUP(G3/12,0) -> 1 | H4: =ROUNDUP(H3/12,0) -> 1 | I4: =ROUNDUP(I3/12,0) -> 1 | J4: =ROUNDUP(J3/12,0) -> 1 | ... BJ4: =ROUNDUP(BJ3/12,0) -> 5
A6: Aquisição
A7: Orçamento de mídia paga (R$) | C7: =INDEX(Premissas!$B$37:$F$37,C$4)*INDEX(Premissas!$B$51:$D$51,$B$2) -> 28750 | D7: =INDEX(Premissas!$B$37:$F$37,D$4)*INDEX(Premissas!$B$51:$D$51,$B$2) -> 28750 | E7: =INDEX(Premissas!$B$37:$F$37,E$4)*INDEX(Premissas!$B$51:$D$51,$B$2) -> 28750 | F7: =INDEX(Premissas!$B$37:$F$37,F$4)*INDEX(Premissas!$B$51:$D$51,$B$2) -> 28750 | G7: =INDEX(Premissas!$B$37:$F$37,G$4)*INDEX(Premissas!$B$51:$D$51,$B$2) -> 28750 | H7: =INDEX(Premissas!$B$37:$F$37,H$4)*INDEX(Premissas!$B$51:$D$51,$B$2) -> 28750 | I7: =INDEX(Premissas!$B$37:$F$37,I$4)*INDEX(Premissas!$B$51:$D$51,$B$2) -> 28750 | J7: =INDEX(Premissas!$B$37:$F$37,J$4)*INDEX(Premissas!$B$51:$D$51,$B$2) -> 28750 | ... BJ7: =INDEX(Premissas!$B$37:$F$37,BJ$4)*INDEX(Premissas!$B$51:$D$51,$B$2) -> 368000
A8: CAC de mídia paga (R$) | C8: =INDEX(Premissas!$B$42:$F$42,C$4)*INDEX(Premissas!$B$47:$D$47,$B$2) -> 1440 | D8: =INDEX(Premissas!$B$42:$F$42,D$4)*INDEX(Premissas!$B$47:$D$47,$B$2) -> 1440 | E8: =INDEX(Premissas!$B$42:$F$42,E$4)*INDEX(Premissas!$B$47:$D$47,$B$2) -> 1440 | F8: =INDEX(Premissas!$B$42:$F$42,F$4)*INDEX(Premissas!$B$47:$D$47,$B$2) -> 1440 | G8: =INDEX(Premissas!$B$42:$F$42,G$4)*INDEX(Premissas!$B$47:$D$47,$B$2) -> 1440 | H8: =INDEX(Premissas!$B$42:$F$42,H$4)*INDEX(Premissas!$B$47:$D$47,$B$2) -> 1440 | I8: =INDEX(Premissas!$B$42:$F$42,I$4)*INDEX(Premissas!$B$47:$D$47,$B$2) -> 1440 | J8: =INDEX(Premissas!$B$42:$F$42,J$4)*INDEX(Premissas!$B$47:$D$47,$B$2) -> 1440 | ... BJ8: =INDEX(Premissas!$B$42:$F$42,BJ$4)*INDEX(Premissas!$B$47:$D$47,$B$2) -> 1077.1949
A9: Novos clientes: mídia paga | C9: =IFERROR(C7/C8,0) -> 19.965278 | D9: =IFERROR(D7/D8,0) -> 19.965278 | E9: =IFERROR(E7/E8,0) -> 19.965278 | F9: =IFERROR(F7/F8,0) -> 19.965278 | G9: =IFERROR(G7/G8,0) -> 19.965278 | H9: =IFERROR(H7/H8,0) -> 19.965278 | I9: =IFERROR(I7/I8,0) -> 19.965278 | J9: =IFERROR(J7/J8,0) -> 19.965278 | ... BJ9: =IFERROR(BJ7/BJ8,0) -> 341.62806
A10: Novos clientes: parcerias | C10: =INDEX(Premissas!$B$38:$F$38,C$4)*INDEX(Premissas!$B$49:$D$49,$B$2) -> 5.2 | D10: =INDEX(Premissas!$B$38:$F$38,D$4)*INDEX(Premissas!$B$49:$D$49,$B$2) -> 5.2 | E10: =INDEX(Premissas!$B$38:$F$38,E$4)*INDEX(Premissas!$B$49:$D$49,$B$2) -> 5.2 | F10: =INDEX(Premissas!$B$38:$F$38,F$4)*INDEX(Premissas!$B$49:$D$49,$B$2) -> 5.2 | G10: =INDEX(Premissas!$B$38:$F$38,G$4)*INDEX(Premissas!$B$49:$D$49,$B$2) -> 5.2 | H10: =INDEX(Premissas!$B$38:$F$38,H$4)*INDEX(Premissas!$B$49:$D$49,$B$2) -> 5.2 | I10: =INDEX(Premissas!$B$38:$F$38,I$4)*INDEX(Premissas!$B$49:$D$49,$B$2) -> 5.2 | J10: =INDEX(Premissas!$B$38:$F$38,J$4)*INDEX(Premissas!$B$49:$D$49,$B$2) -> 5.2 | ... BJ10: =INDEX(Premissas!$B$38:$F$38,BJ$4)*INDEX(Premissas!$B$49:$D$49,$B$2) -> 71.5
A11: Novos clientes: indicação | C11: =0 -> 0 | D11: =C26*Premissas!$B$43*INDEX(Premissas!$B$49:$D$49,$B$2) -> 0.32714861 | E11: =D26*Premissas!$B$43*INDEX(Premissas!$B$49:$D$49,$B$2) -> 0.6487357 | F11: =E26*Premissas!$B$43*INDEX(Premissas!$B$49:$D$49,$B$2) -> 0.96487805 | G11: =F26*Premissas!$B$43*INDEX(Premissas!$B$49:$D$49,$B$2) -> 1.2756894 | H11: =G26*Premissas!$B$43*INDEX(Premissas!$B$49:$D$49,$B$2) -> 1.5812803 | I11: =H26*Premissas!$B$43*INDEX(Premissas!$B$49:$D$49,$B$2) -> 1.8817588 | J11: =I26*Premissas!$B$43*INDEX(Premissas!$B$49:$D$49,$B$2) -> 2.1772297 | K11: =J26*Premissas!$B$43*INDEX(Premissas!$B$49:$D$49,$B$2) -> 2.4677953 | ... BJ11: =BI26*Premissas!$B$43*INDEX(Premissas!$B$49:$D$49,$B$2) -> 129.4163
A12: Novos clientes: total | C12: =C9+C10+C11 -> 25.165278 | D12: =D9+D10+D11 -> 25.492426 | E12: =E9+E10+E11 -> 25.814013 | F12: =F9+F10+F11 -> 26.130156 | G12: =G9+G10+G11 -> 26.440967 | H12: =H9+H10+H11 -> 26.746558 | I12: =I9+I10+I11 -> 27.047037 | J12: =J9+J10+J11 -> 27.342507 | ... BJ12: =BJ9+BJ10+BJ11 -> 542.54436
A13: Clientes por plano
A14: Novos: Essencial | C14: =C12*INDEX(Premissas!$B$29:$B$33,C$4) -> 10.066111 | D14: =D12*INDEX(Premissas!$B$29:$B$33,D$4) -> 10.196971 | E14: =E12*INDEX(Premissas!$B$29:$B$33,E$4) -> 10.325605 | F14: =F12*INDEX(Premissas!$B$29:$B$33,F$4) -> 10.452062 | G14: =G12*INDEX(Premissas!$B$29:$B$33,G$4) -> 10.576387 | H14: =H12*INDEX(Premissas!$B$29:$B$33,H$4) -> 10.698623 | I14: =I12*INDEX(Premissas!$B$29:$B$33,I$4) -> 10.818815 | J14: =J12*INDEX(Premissas!$B$29:$B$33,J$4) -> 10.937003 | ... BJ14: =BJ12*INDEX(Premissas!$B$29:$B$33,BJ$4) -> 135.63609
A15: Novos: Consultório | C15: =C12*INDEX(Premissas!$C$29:$C$33,C$4) -> 12.582639 | D15: =D12*INDEX(Premissas!$C$29:$C$33,D$4) -> 12.746213 | E15: =E12*INDEX(Premissas!$C$29:$C$33,E$4) -> 12.907007 | F15: =F12*INDEX(Premissas!$C$29:$C$33,F$4) -> 13.065078 | G15: =G12*INDEX(Premissas!$C$29:$C$33,G$4) -> 13.220484 | H15: =H12*INDEX(Premissas!$C$29:$C$33,H$4) -> 13.373279 | I15: =I12*INDEX(Premissas!$C$29:$C$33,I$4) -> 13.523518 | J15: =J12*INDEX(Premissas!$C$29:$C$33,J$4) -> 13.671254 | ... BJ15: =BJ12*INDEX(Premissas!$C$29:$C$33,BJ$4) -> 271.27218
A16: Novos: Autoridade | C16: =C12*INDEX(Premissas!$D$29:$D$33,C$4) -> 2.5165278 | D16: =D12*INDEX(Premissas!$D$29:$D$33,D$4) -> 2.5492426 | E16: =E12*INDEX(Premissas!$D$29:$D$33,E$4) -> 2.5814013 | F16: =F12*INDEX(Premissas!$D$29:$D$33,F$4) -> 2.6130156 | G16: =G12*INDEX(Premissas!$D$29:$D$33,G$4) -> 2.6440967 | H16: =H12*INDEX(Premissas!$D$29:$D$33,H$4) -> 2.6746558 | I16: =I12*INDEX(Premissas!$D$29:$D$33,I$4) -> 2.7047037 | J16: =J12*INDEX(Premissas!$D$29:$D$33,J$4) -> 2.7342507 | ... BJ16: =BJ12*INDEX(Premissas!$D$29:$D$33,BJ$4) -> 97.657984
A17: Novos: Clínica | C17: =C12*INDEX(Premissas!$E$29:$E$33,C$4) -> 0 | D17: =D12*INDEX(Premissas!$E$29:$E$33,D$4) -> 0 | E17: =E12*INDEX(Premissas!$E$29:$E$33,E$4) -> 0 | F17: =F12*INDEX(Premissas!$E$29:$E$33,F$4) -> 0 | G17: =G12*INDEX(Premissas!$E$29:$E$33,G$4) -> 0 | H17: =H12*INDEX(Premissas!$E$29:$E$33,H$4) -> 0 | I17: =I12*INDEX(Premissas!$E$29:$E$33,I$4) -> 0 | J17: =J12*INDEX(Premissas!$E$29:$E$33,J$4) -> 0 | ... BJ17: =BJ12*INDEX(Premissas!$E$29:$E$33,BJ$4) -> 37.978105
A18: Cancelamentos: Essencial | C18: =0 -> 0 | D18: =C22*Premissas!$B$20*INDEX(Premissas!$B$48:$D$48,$B$2)*(1-Premissas!$B$25)^(D$4-1) -> 0.40264444 | E18: =D22*Premissas!$B$20*INDEX(Premissas!$B$48:$D$48,$B$2)*(1-Premissas!$B$25)^(E$4-1) -> 0.79441749 | F18: =E22*Premissas!$B$20*INDEX(Premissas!$B$48:$D$48,$B$2)*(1-Premissas!$B$25)^(F$4-1) -> 1.175665 | G18: =F22*Premissas!$B$20*INDEX(Premissas!$B$48:$D$48,$B$2)*(1-Premissas!$B$25)^(G$4-1) -> 1.5467209 | H18: =G22*Premissas!$B$20*INDEX(Premissas!$B$48:$D$48,$B$2)*(1-Premissas!$B$25)^(H$4-1) -> 1.9079075 | I18: =H22*Premissas!$B$20*INDEX(Premissas!$B$48:$D$48,$B$2)*(1-Premissas!$B$25)^(I$4-1) -> 2.2595362 | J18: =I22*Premissas!$B$20*INDEX(Premissas!$B$48:$D$48,$B$2)*(1-Premissas!$B$25)^(J$4-1) -> 2.6019073 | K18: =J22*Premissas!$B$20*INDEX(Premissas!$B$48:$D$48,$B$2)*(1-Premissas!$B$25)^(K$4-1) -> 2.9353111 | ... BJ18: =BI22*Premissas!$B$20*INDEX(Premissas!$B$48:$D$48,$B$2)*(1-Premissas!$B$25)^(BJ$4-1) -> 67.61064
A19: Cancelamentos: Consultório | C19: =0 -> 0 | D19: =C23*Premissas!$C$20*INDEX(Premissas!$B$48:$D$48,$B$2)*(1-Premissas!$B$25)^(D$4-1) -> 0.30198333 | E19: =D23*Premissas!$C$20*INDEX(Premissas!$B$48:$D$48,$B$2)*(1-Premissas!$B$25)^(E$4-1) -> 0.60064485 | F19: =E23*Premissas!$C$20*INDEX(Premissas!$B$48:$D$48,$B$2)*(1-Premissas!$B$25)^(F$4-1) -> 0.89599754 | G19: =F23*Premissas!$C$20*INDEX(Premissas!$B$48:$D$48,$B$2)*(1-Premissas!$B$25)^(G$4-1) -> 1.1880555 | H19: =G23*Premissas!$C$20*INDEX(Premissas!$B$48:$D$48,$B$2)*(1-Premissas!$B$25)^(H$4-1) -> 1.4768337 | I19: =H23*Premissas!$C$20*INDEX(Premissas!$B$48:$D$48,$B$2)*(1-Premissas!$B$25)^(I$4-1) -> 1.7623484 | J19: =I23*Premissas!$C$20*INDEX(Premissas!$B$48:$D$48,$B$2)*(1-Premissas!$B$25)^(J$4-1) -> 2.0446165 | K19: =J23*Premissas!$C$20*INDEX(Premissas!$B$48:$D$48,$B$2)*(1-Premissas!$B$25)^(K$4-1) -> 2.3236558 | ... BJ19: =BI23*Premissas!$C$20*INDEX(Premissas!$B$48:$D$48,$B$2)*(1-Premissas!$B$25)^(BJ$4-1) -> 88.360544
A20: Cancelamentos: Autoridade | C20: =0 -> 0 | D20: =C24*Premissas!$D$20*INDEX(Premissas!$B$48:$D$48,$B$2)*(1-Premissas!$B$25)^(D$4-1) -> 0.050330556 | E20: =D24*Premissas!$D$20*INDEX(Premissas!$B$48:$D$48,$B$2)*(1-Premissas!$B$25)^(E$4-1) -> 0.1003088 | F20: =E24*Premissas!$D$20*INDEX(Premissas!$B$48:$D$48,$B$2)*(1-Premissas!$B$25)^(F$4-1) -> 0.14993065 | G20: =F24*Premissas!$D$20*INDEX(Premissas!$B$48:$D$48,$B$2)*(1-Premissas!$B$25)^(G$4-1) -> 0.19919235 | H20: =G24*Premissas!$D$20*INDEX(Premissas!$B$48:$D$48,$B$2)*(1-Premissas!$B$25)^(H$4-1) -> 0.24809043 | I20: =H24*Premissas!$D$20*INDEX(Premissas!$B$48:$D$48,$B$2)*(1-Premissas!$B$25)^(I$4-1) -> 0.29662174 | J20: =I24*Premissas!$D$20*INDEX(Premissas!$B$48:$D$48,$B$2)*(1-Premissas!$B$25)^(J$4-1) -> 0.34478338 | K20: =J24*Premissas!$D$20*INDEX(Premissas!$B$48:$D$48,$B$2)*(1-Premissas!$B$25)^(K$4-1) -> 0.39257273 | ... BJ20: =BI24*Premissas!$D$20*INDEX(Premissas!$B$48:$D$48,$B$2)*(1-Premissas!$B$25)^(BJ$4-1) -> 25.526138
A21: Cancelamentos: Clínica | C21: =0 -> 0 | D21: =C25*Premissas!$E$20*INDEX(Premissas!$B$48:$D$48,$B$2)*(1-Premissas!$B$25)^(D$4-1) -> 0 | E21: =D25*Premissas!$E$20*INDEX(Premissas!$B$48:$D$48,$B$2)*(1-Premissas!$B$25)^(E$4-1) -> 0 | F21: =E25*Premissas!$E$20*INDEX(Premissas!$B$48:$D$48,$B$2)*(1-Premissas!$B$25)^(F$4-1) -> 0 | G21: =F25*Premissas!$E$20*INDEX(Premissas!$B$48:$D$48,$B$2)*(1-Premissas!$B$25)^(G$4-1) -> 0 | H21: =G25*Premissas!$E$20*INDEX(Premissas!$B$48:$D$48,$B$2)*(1-Premissas!$B$25)^(H$4-1) -> 0 | I21: =H25*Premissas!$E$20*INDEX(Premissas!$B$48:$D$48,$B$2)*(1-Premissas!$B$25)^(I$4-1) -> 0 | J21: =I25*Premissas!$E$20*INDEX(Premissas!$B$48:$D$48,$B$2)*(1-Premissas!$B$25)^(J$4-1) -> 0 | K21: =J25*Premissas!$E$20*INDEX(Premissas!$B$48:$D$48,$B$2)*(1-Premissas!$B$25)^(K$4-1) -> 0 | ... BJ21: =BI25*Premissas!$E$20*INDEX(Premissas!$B$48:$D$48,$B$2)*(1-Premissas!$B$25)^(BJ$4-1) -> 7.7360198
A22: Ativos: Essencial | C22: =C14-C18 -> 10.066111 | D22: =C22+D14-D18 -> 19.860437 | E22: =D22+E14-E18 -> 29.391625 | F22: =E22+F14-F18 -> 38.668022 | G22: =F22+G14-G18 -> 47.697688 | H22: =G22+H14-H18 -> 56.488404 | I22: =H22+I14-I18 -> 65.047683 | J22: =I22+J14-J18 -> 73.382778 | K22: =J22+K14-K18 -> 81.500696 | ... BJ22: =BI22+BJ14-BJ18 -> 2427.4372
A23: Ativos: Consultório | C23: =C15-C19 -> 12.582639 | D23: =C23+D15-D19 -> 25.026869 | E23: =D23+E15-E19 -> 37.333231 | F23: =E23+F15-F19 -> 49.502311 | G23: =F23+G15-G19 -> 61.534739 | H23: =G23+H15-H19 -> 73.431184 | I23: =H23+I15-I19 -> 85.192354 | J23: =I23+J15-J19 -> 96.818992 | K23: =J23+K15-K19 -> 108.31187 | ... BJ23: =BI23+BJ15-BJ19 -> 5322.1153
A24: Ativos: Autoridade | C24: =C16-C20 -> 2.5165278 | D24: =C24+D16-D20 -> 5.0154399 | E24: =D24+E16-E20 -> 7.4965324 | F24: =E24+F16-F20 -> 9.9596173 | G24: =F24+G16-G20 -> 12.404522 | H24: =G24+H16-H20 -> 14.831087 | I24: =H24+I16-I20 -> 17.239169 | J24: =I24+J16-J20 -> 19.628636 | K24: =J24+K16-K20 -> 21.999371 | ... BJ24: =BI24+BJ16-BJ20 -> 1853.7056
A25: Ativos: Clínica | C25: =C17-C21 -> 0 | D25: =C25+D17-D21 -> 0 | E25: =D25+E17-E21 -> 0 | F25: =E25+F17-F21 -> 0 | G25: =F25+G17-G21 -> 0 | H25: =G25+H17-H21 -> 0 | I25: =H25+I17-I21 -> 0 | J25: =I25+J17-J21 -> 0 | K25: =J25+K17-K21 -> 0 | ... BJ25: =BI25+BJ17-BJ21 -> 705.15274
A26: Clientes ativos: total | C26: =SUM(C22:C25) -> 25.165278 | D26: =SUM(D22:D25) -> 49.902746 | E26: =SUM(E22:E25) -> 74.221388 | F26: =SUM(F22:F25) -> 98.129951 | G26: =SUM(G22:G25) -> 121.63695 | H26: =SUM(H22:H25) -> 144.75068 | I26: =SUM(I22:I25) -> 167.47921 | J26: =SUM(J22:J25) -> 189.83041 | ... BJ26: =SUM(BJ22:BJ25) -> 10308.411
A27: Receita (R$)
A28: Receita recorrente: Essencial | C28: =C22*Premissas!$B$18*(1-Premissas!$B$12*Premissas!$B$13) -> 2855.1014 | D28: =D22*Premissas!$B$18*(1-Premissas!$B$12*Premissas!$B$13) -> 5633.1151 | E28: =E22*Premissas!$B$18*(1-Premissas!$B$12*Premissas!$B$13) -> 8336.4936 | F28: =F22*Premissas!$B$18*(1-Premissas!$B$12*Premissas!$B$13) -> 10967.605 | G28: =G22*Premissas!$B$18*(1-Premissas!$B$12*Premissas!$B$13) -> 13528.734 | H28: =H22*Premissas!$B$18*(1-Premissas!$B$12*Premissas!$B$13) -> 16022.089 | I28: =I22*Premissas!$B$18*(1-Premissas!$B$12*Premissas!$B$13) -> 18449.799 | J28: =J22*Premissas!$B$18*(1-Premissas!$B$12*Premissas!$B$13) -> 20813.924 | ... BJ28: =BJ22*Premissas!$B$18*(1-Premissas!$B$12*Premissas!$B$13) -> 688506.16
A29: Receita recorrente: Consultório | C29: =C23*Premissas!$C$18*(1-Premissas!$B$12*Premissas!$B$13) -> 8375.4448 | D29: =D23*Premissas!$C$18*(1-Premissas!$B$12*Premissas!$B$13) -> 16658.76 | E29: =E23*Premissas!$C$18*(1-Premissas!$B$12*Premissas!$B$13) -> 24850.305 | F29: =F23*Premissas!$C$18*(1-Premissas!$B$12*Premissas!$B$13) -> 32950.471 | G29: =G23*Premissas!$C$18*(1-Premissas!$B$12*Premissas!$B$13) -> 40959.676 | H29: =H23*Premissas!$C$18*(1-Premissas!$B$12*Premissas!$B$13) -> 48878.366 | I29: =I23*Premissas!$C$18*(1-Premissas!$B$12*Premissas!$B$13) -> 56707.013 | J29: =J23*Premissas!$C$18*(1-Premissas!$B$12*Premissas!$B$13) -> 64446.109 | ... BJ29: =BJ23*Premissas!$C$18*(1-Premissas!$B$12*Premissas!$B$13) -> 3542586.2
A30: Receita recorrente: Autoridade | C30: =C24*Premissas!$D$18*(1-Premissas!$B$12*Premissas!$B$13) -> 3597.7162 | D30: =D24*Premissas!$D$18*(1-Premissas!$B$12*Premissas!$B$13) -> 7170.2484 | E30: =E24*Premissas!$D$18*(1-Premissas!$B$12*Premissas!$B$13) -> 10717.305 | F30: =F24*Premissas!$D$18*(1-Premissas!$B$12*Premissas!$B$13) -> 14238.618 | G30: =G24*Premissas!$D$18*(1-Premissas!$B$12*Premissas!$B$13) -> 17733.938 | H30: =H24*Premissas!$D$18*(1-Premissas!$B$12*Premissas!$B$13) -> 21203.041 | I30: =I24*Premissas!$D$18*(1-Premissas!$B$12*Premissas!$B$13) -> 24645.719 | J30: =J24*Premissas!$D$18*(1-Premissas!$B$12*Premissas!$B$13) -> 28061.786 | ... BJ30: =BJ24*Premissas!$D$18*(1-Premissas!$B$12*Premissas!$B$13) -> 2650122.4
A31: Receita recorrente: Clínica | C31: =C25*Premissas!$E$18*(1-Premissas!$B$12*Premissas!$B$13) -> 0 | D31: =D25*Premissas!$E$18*(1-Premissas!$B$12*Premissas!$B$13) -> 0 | E31: =E25*Premissas!$E$18*(1-Premissas!$B$12*Premissas!$B$13) -> 0 | F31: =F25*Premissas!$E$18*(1-Premissas!$B$12*Premissas!$B$13) -> 0 | G31: =G25*Premissas!$E$18*(1-Premissas!$B$12*Premissas!$B$13) -> 0 | H31: =H25*Premissas!$E$18*(1-Premissas!$B$12*Premissas!$B$13) -> 0 | I31: =I25*Premissas!$E$18*(1-Premissas!$B$12*Premissas!$B$13) -> 0 | J31: =J25*Premissas!$E$18*(1-Premissas!$B$12*Premissas!$B$13) -> 0 | ... BJ31: =BJ25*Premissas!$E$18*(1-Premissas!$B$12*Premissas!$B$13) -> 2626341.4
A32: Receita recorrente mensal (MRR) | C32: =SUM(C28:C31) -> 14828.262 | D32: =SUM(D28:D31) -> 29462.123 | E32: =SUM(E28:E31) -> 43904.104 | F32: =SUM(F28:F31) -> 58156.693 | G32: =SUM(G28:G31) -> 72222.348 | H32: =SUM(H28:H31) -> 86103.496 | I32: =SUM(I28:I31) -> 99802.532 | J32: =SUM(J28:J31) -> 113321.82 | ... BJ32: =SUM(BJ28:BJ31) -> 9507556.2
A33: Taxas de implantação | C33: =C14*Premissas!$B$19+C15*Premissas!$C$19+C16*Premissas!$D$19+C17*Premissas!$E$19 -> 8656.8556 | D33: =D14*Premissas!$B$19+D15*Premissas!$C$19+D16*Premissas!$D$19+D17*Premissas!$E$19 -> 8769.3947 | E33: =E14*Premissas!$B$19+E15*Premissas!$C$19+E16*Premissas!$D$19+E17*Premissas!$E$19 -> 8880.0206 | F33: =F14*Premissas!$B$19+F15*Premissas!$C$19+F16*Premissas!$D$19+F17*Premissas!$E$19 -> 8988.7736 | G33: =G14*Premissas!$B$19+G15*Premissas!$C$19+G16*Premissas!$D$19+G17*Premissas!$E$19 -> 9095.6927 | H33: =H14*Premissas!$B$19+H15*Premissas!$C$19+H16*Premissas!$D$19+H17*Premissas!$E$19 -> 9200.816 | I33: =I14*Premissas!$B$19+I15*Premissas!$C$19+I16*Premissas!$D$19+I17*Premissas!$E$19 -> 9304.1806 | J33: =J14*Premissas!$B$19+J15*Premissas!$C$19+J16*Premissas!$D$19+J17*Premissas!$E$19 -> 9405.8226 | ... BJ33: =BJ14*Premissas!$B$19+BJ15*Premissas!$C$19+BJ16*Premissas!$D$19+BJ17*Premissas!$E$19 -> 339741.28
A34: Serviços adicionais | C34: =C32*INDEX(Premissas!$B$39:$F$39,C$4)*INDEX(Premissas!$B$50:$D$50,$B$2) -> 889.69575 | D34: =D32*INDEX(Premissas!$B$39:$F$39,D$4)*INDEX(Premissas!$B$50:$D$50,$B$2) -> 1767.7274 | E34: =E32*INDEX(Premissas!$B$39:$F$39,E$4)*INDEX(Premissas!$B$50:$D$50,$B$2) -> 2634.2462 | F34: =F32*INDEX(Premissas!$B$39:$F$39,F$4)*INDEX(Premissas!$B$50:$D$50,$B$2) -> 3489.4016 | G34: =G32*INDEX(Premissas!$B$39:$F$39,G$4)*INDEX(Premissas!$B$50:$D$50,$B$2) -> 4333.3409 | H34: =H32*INDEX(Premissas!$B$39:$F$39,H$4)*INDEX(Premissas!$B$50:$D$50,$B$2) -> 5166.2098 | I34: =I32*INDEX(Premissas!$B$39:$F$39,I$4)*INDEX(Premissas!$B$50:$D$50,$B$2) -> 5988.1519 | J34: =J32*INDEX(Premissas!$B$39:$F$39,J$4)*INDEX(Premissas!$B$50:$D$50,$B$2) -> 6799.3092 | ... BJ34: =BJ32*INDEX(Premissas!$B$39:$F$39,BJ$4)*INDEX(Premissas!$B$50:$D$50,$B$2) -> 1711360.1
A35: Receita bruta | C35: =C32+C33+C34 -> 24374.814 | D35: =D32+D33+D34 -> 39999.245 | E35: =E32+E33+E34 -> 55418.371 | F35: =F32+F33+F34 -> 70634.868 | G35: =G32+G33+G34 -> 85651.382 | H35: =H32+H33+H34 -> 100470.52 | I35: =I32+I33+I34 -> 115094.86 | J35: =J32+J33+J34 -> 129526.95 | ... BJ35: =BJ32+BJ33+BJ34 -> 11558658
A36: (-) Impostos sobre receita | C36: =-C35*IF(SUMIFS($C$35:$BJ$35,$C$4:$BJ$4,C$4-1)>Premissas!$B$8,Premissas!$B$7,Premissas!$B$6) -> -2681.2295 | D36: =-D35*IF(SUMIFS($C$35:$BJ$35,$C$4:$BJ$4,D$4-1)>Premissas!$B$8,Premissas!$B$7,Premissas!$B$6) -> -4399.917 | E36: =-E35*IF(SUMIFS($C$35:$BJ$35,$C$4:$BJ$4,E$4-1)>Premissas!$B$8,Premissas!$B$7,Premissas!$B$6) -> -6096.0208 | F36: =-F35*IF(SUMIFS($C$35:$BJ$35,$C$4:$BJ$4,F$4-1)>Premissas!$B$8,Premissas!$B$7,Premissas!$B$6) -> -7769.8355 | G36: =-G35*IF(SUMIFS($C$35:$BJ$35,$C$4:$BJ$4,G$4-1)>Premissas!$B$8,Premissas!$B$7,Premissas!$B$6) -> -9421.652 | H36: =-H35*IF(SUMIFS($C$35:$BJ$35,$C$4:$BJ$4,H$4-1)>Premissas!$B$8,Premissas!$B$7,Premissas!$B$6) -> -11051.757 | I36: =-I35*IF(SUMIFS($C$35:$BJ$35,$C$4:$BJ$4,I$4-1)>Premissas!$B$8,Premissas!$B$7,Premissas!$B$6) -> -12660.435 | J36: =-J35*IF(SUMIFS($C$35:$BJ$35,$C$4:$BJ$4,J$4-1)>Premissas!$B$8,Premissas!$B$7,Premissas!$B$6) -> -14247.965 | ... BJ36: =-BJ35*IF(SUMIFS($C$35:$BJ$35,$C$4:$BJ$4,BJ$4-1)>Premissas!$B$8,Premissas!$B$7,Premissas!$B$6) -> -1887528.8
A37: Receita líquida | C37: =C35+C36 -> 21693.584 | D37: =D35+D36 -> 35599.328 | E37: =E35+E36 -> 49322.35 | F37: =F35+F36 -> 62865.033 | G37: =G35+G36 -> 76229.73 | H37: =H35+H36 -> 89418.764 | I37: =I35+I36 -> 102434.43 | J37: =J35+J36 -> 115278.99 | ... BJ37: =BJ35+BJ36 -> 9671128.8
A38: Custo do serviço (R$)
A39: IA (modelos de linguagem e imagem) | C39: =-(C22*Premissas!$B$21+C23*Premissas!$C$21+C24*Premissas!$D$21+C25*Premissas!$E$21)*Premissas!$B$5 -> -1073.5508 | D39: =-(D22*Premissas!$B$21+D23*Premissas!$C$21+D24*Premissas!$D$21+D25*Premissas!$E$21)*Premissas!$B$5 -> -2132.792 | E39: =-(E22*Premissas!$B$21+E23*Premissas!$C$21+E24*Premissas!$D$21+E25*Premissas!$E$21)*Premissas!$B$5 -> -3177.9171 | F39: =-(F22*Premissas!$B$21+F23*Premissas!$C$21+F24*Premissas!$D$21+F25*Premissas!$E$21)*Premissas!$B$5 -> -4209.1164 | G39: =-(G22*Premissas!$B$21+G23*Premissas!$C$21+G24*Premissas!$D$21+G25*Premissas!$E$21)*Premissas!$B$5 -> -5226.5779 | H39: =-(H22*Premissas!$B$21+H23*Premissas!$C$21+H24*Premissas!$D$21+H25*Premissas!$E$21)*Premissas!$B$5 -> -6230.4868 | I39: =-(I22*Premissas!$B$21+I23*Premissas!$C$21+I24*Premissas!$D$21+I25*Premissas!$E$21)*Premissas!$B$5 -> -7221.0256 | J39: =-(J22*Premissas!$B$21+J23*Premissas!$C$21+J24*Premissas!$D$21+J25*Premissas!$E$21)*Premissas!$B$5 -> -8198.3745 | ... BJ39: =-(BJ22*Premissas!$B$21+BJ23*Premissas!$C$21+BJ24*Premissas!$D$21+BJ25*Premissas!$E$21)*Premissas!$B$5 -> -662619.75
A40: Infraestrutura e APIs | C40: =-(C22*Premissas!$B$22+C23*Premissas!$C$22+C24*Premissas!$D$22+C25*Premissas!$E$22) -> -276.81806 | D40: =-(D22*Premissas!$B$22+D23*Premissas!$C$22+D24*Premissas!$D$22+D25*Premissas!$E$22) -> -549.48384 | E40: =-(E22*Premissas!$B$22+E23*Premissas!$C$22+E24*Premissas!$D$22+E25*Premissas!$E$22) -> -818.06935 | F40: =-(F22*Premissas!$B$22+F23*Premissas!$C$22+F24*Premissas!$D$22+F25*Premissas!$E$22) -> -1082.645 | G40: =-(G22*Premissas!$B$22+G23*Premissas!$C$22+G24*Premissas!$D$22+G25*Premissas!$E$22) -> -1343.2798 | H40: =-(H22*Premissas!$B$22+H23*Premissas!$C$22+H24*Premissas!$D$22+H25*Premissas!$E$22) -> -1600.041 | I40: =-(I22*Premissas!$B$22+I23*Premissas!$C$22+I24*Premissas!$D$22+I25*Premissas!$E$22) -> -1852.9948 | J40: =-(J22*Premissas!$B$22+J23*Premissas!$C$22+J24*Premissas!$D$22+J25*Premissas!$E$22) -> -2102.2056 | ... BJ40: =-(BJ22*Premissas!$B$22+BJ23*Premissas!$C$22+BJ24*Premissas!$D$22+BJ25*Premissas!$E$22) -> -144857.69
A41: Gestores de conta (revisão humana) | C41: =-(IFERROR(C22/Premissas!$B$23,0)+IFERROR(C23/Premissas!$C$23,0)+IFERROR(C24/Premissas!$D$23,0)+IFERROR(C25/Premissas!$E$23,0))*Premissas!$B$24*(1+Premissas!$B$10) -> -748.66701 | D41: =-(IFERROR(D22/Premissas!$B$23,0)+IFERROR(D23/Premissas!$C$23,0)+IFERROR(D24/Premissas!$D$23,0)+IFERROR(D25/Premissas!$E$23,0))*Premissas!$B$24*(1+Premissas!$B$10) -> -1492.0934 | E41: =-(IFERROR(E22/Premissas!$B$23,0)+IFERROR(E23/Premissas!$C$23,0)+IFERROR(E24/Premissas!$D$23,0)+IFERROR(E25/Premissas!$E$23,0))*Premissas!$B$24*(1+Premissas!$B$10) -> -2230.2184 | F41: =-(IFERROR(F22/Premissas!$B$23,0)+IFERROR(F23/Premissas!$C$23,0)+IFERROR(F24/Premissas!$D$23,0)+IFERROR(F25/Premissas!$E$23,0))*Premissas!$B$24*(1+Premissas!$B$10) -> -2962.9862 | G41: =-(IFERROR(G22/Premissas!$B$23,0)+IFERROR(G23/Premissas!$C$23,0)+IFERROR(G24/Premissas!$D$23,0)+IFERROR(G25/Premissas!$E$23,0))*Premissas!$B$24*(1+Premissas!$B$10) -> -3690.3452 | H41: =-(IFERROR(H22/Premissas!$B$23,0)+IFERROR(H23/Premissas!$C$23,0)+IFERROR(H24/Premissas!$D$23,0)+IFERROR(H25/Premissas!$E$23,0))*Premissas!$B$24*(1+Premissas!$B$10) -> -4412.2484 | I41: =-(IFERROR(I22/Premissas!$B$23,0)+IFERROR(I23/Premissas!$C$23,0)+IFERROR(I24/Premissas!$D$23,0)+IFERROR(I25/Premissas!$E$23,0))*Premissas!$B$24*(1+Premissas!$B$10) -> -5128.6528 | J41: =-(IFERROR(J22/Premissas!$B$23,0)+IFERROR(J23/Premissas!$C$23,0)+IFERROR(J24/Premissas!$D$23,0)+IFERROR(J25/Premissas!$E$23,0))*Premissas!$B$24*(1+Premissas!$B$10) -> -5839.5193 | ... BJ41: =-(IFERROR(BJ22/Premissas!$B$23,0)+IFERROR(BJ23/Premissas!$C$23,0)+IFERROR(BJ24/Premissas!$D$23,0)+IFERROR(BJ25/Premissas!$E$23,0))*Premissas!$B$24*(1+Premissas!$B$10) -> -971043.29
A42: Meio de pagamento | C42: =-C35*Premissas!$B$9 -> -853.11848 | D42: =-D35*Premissas!$B$9 -> -1399.9736 | E42: =-E35*Premissas!$B$9 -> -1939.643 | F42: =-F35*Premissas!$B$9 -> -2472.2204 | G42: =-G35*Premissas!$B$9 -> -2997.7984 | H42: =-H35*Premissas!$B$9 -> -3516.4683 | I42: =-I35*Premissas!$B$9 -> -4028.3202 | J42: =-J35*Premissas!$B$9 -> -4533.4433 | ... BJ42: =-BJ35*Premissas!$B$9 -> -404553.01
A43: Custo do serviço total | C43: =SUM(C39:C42) -> -2952.1543 | D43: =SUM(D39:D42) -> -5574.3428 | E43: =SUM(E39:E42) -> -8165.8478 | F43: =SUM(F39:F42) -> -10726.968 | G43: =SUM(G39:G42) -> -13258.001 | H43: =SUM(H39:H42) -> -15759.244 | I43: =SUM(I39:I42) -> -18230.993 | J43: =SUM(J39:J42) -> -20673.543 | ... BJ43: =SUM(BJ39:BJ42) -> -2183073.8
A44: Lucro bruto | C44: =C37+C43 -> 18741.43 | D44: =D37+D43 -> 30024.986 | E44: =E37+E43 -> 41156.502 | F44: =F37+F43 -> 52138.065 | G44: =G37+G43 -> 62971.729 | H44: =H37+H43 -> 73659.52 | I44: =I37+I43 -> 84203.436 | J44: =J37+J43 -> 94605.444 | ... BJ44: =BJ37+BJ43 -> 7488055
A45: Margem bruta (% da receita líquida) | C45: =IFERROR(C44/C37,0) -> 0.86391579 | D45: =IFERROR(D44/D37,0) -> 0.84341438 | E45: =IFERROR(E44/E37,0) -> 0.8344392 | F45: =IFERROR(F44/F37,0) -> 0.82936511 | G45: =IFERROR(G44/G37,0) -> 0.82607834 | H45: =IFERROR(H44/H37,0) -> 0.82375909 | I45: =IFERROR(I44/I37,0) -> 0.8220228 | J45: =IFERROR(J44/J37,0) -> 0.82066512 | ... BJ45: =IFERROR(BJ44/BJ37,0) -> 0.77426898
A46: Despesas operacionais (R$)
A47: Pessoal | C47: =-INDEX(Premissas!$D$67:$H$67,C$4) -> -160550 | D47: =-INDEX(Premissas!$D$67:$H$67,D$4) -> -160550 | E47: =-INDEX(Premissas!$D$67:$H$67,E$4) -> -160550 | F47: =-INDEX(Premissas!$D$67:$H$67,F$4) -> -160550 | G47: =-INDEX(Premissas!$D$67:$H$67,G$4) -> -160550 | H47: =-INDEX(Premissas!$D$67:$H$67,H$4) -> -160550 | I47: =-INDEX(Premissas!$D$67:$H$67,I$4) -> -160550 | J47: =-INDEX(Premissas!$D$67:$H$67,J$4) -> -160550 | ... BJ47: =-INDEX(Premissas!$D$67:$H$67,BJ$4) -> -1142100
A48: Mídia paga e inbound | C48: =-C7 -> -28750 | D48: =-D7 -> -28750 | E48: =-E7 -> -28750 | F48: =-F7 -> -28750 | G48: =-G7 -> -28750 | H48: =-H7 -> -28750 | I48: =-I7 -> -28750 | J48: =-J7 -> -28750 | ... BJ48: =-BJ7 -> -368000
A49: Comissões de vendas (10% do primeiro mês dos novos) | C49: =-0.1*(C14*Premissas!$B$18+C15*Premissas!$C$18+C16*Premissas!$D$18+C17*Premissas!$E$18) -> -1552.6976 | D49: =-0.1*(D14*Premissas!$B$18+D15*Premissas!$C$18+D16*Premissas!$D$18+D17*Premissas!$E$18) -> -1572.8827 | E49: =-0.1*(E14*Premissas!$B$18+E15*Premissas!$C$18+E16*Premissas!$D$18+E17*Premissas!$E$18) -> -1592.7246 | F49: =-0.1*(F14*Premissas!$B$18+F15*Premissas!$C$18+F16*Premissas!$D$18+F17*Premissas!$E$18) -> -1612.2306 | G49: =-0.1*(G14*Premissas!$B$18+G15*Premissas!$C$18+G16*Premissas!$D$18+G17*Premissas!$E$18) -> -1631.4077 | H49: =-0.1*(H14*Premissas!$B$18+H15*Premissas!$C$18+H16*Premissas!$D$18+H17*Premissas!$E$18) -> -1650.2626 | I49: =-0.1*(I14*Premissas!$B$18+I15*Premissas!$C$18+I16*Premissas!$D$18+I17*Premissas!$E$18) -> -1668.8022 | J49: =-0.1*(J14*Premissas!$B$18+J15*Premissas!$C$18+J16*Premissas!$D$18+J17*Premissas!$E$18) -> -1687.0327 | ... BJ49: =-0.1*(BJ14*Premissas!$B$18+BJ15*Premissas!$C$18+BJ16*Premissas!$D$18+BJ17*Premissas!$E$18) -> -52366.924
A50: Jurídico e curadoria normativa | C50: =-INDEX(Premissas!$B$72:$F$72,C$4) -> -5000 | D50: =-INDEX(Premissas!$B$72:$F$72,D$4) -> -5000 | E50: =-INDEX(Premissas!$B$72:$F$72,E$4) -> -5000 | F50: =-INDEX(Premissas!$B$72:$F$72,F$4) -> -5000 | G50: =-INDEX(Premissas!$B$72:$F$72,G$4) -> -5000 | H50: =-INDEX(Premissas!$B$72:$F$72,H$4) -> -5000 | I50: =-INDEX(Premissas!$B$72:$F$72,I$4) -> -5000 | J50: =-INDEX(Premissas!$B$72:$F$72,J$4) -> -5000 | ... BJ50: =-INDEX(Premissas!$B$72:$F$72,BJ$4) -> -25000
A51: Marca: eventos e congressos | C51: =-INDEX(Premissas!$B$73:$F$73,C$4) -> -2000 | D51: =-INDEX(Premissas!$B$73:$F$73,D$4) -> -2000 | E51: =-INDEX(Premissas!$B$73:$F$73,E$4) -> -2000 | F51: =-INDEX(Premissas!$B$73:$F$73,F$4) -> -2000 | G51: =-INDEX(Premissas!$B$73:$F$73,G$4) -> -2000 | H51: =-INDEX(Premissas!$B$73:$F$73,H$4) -> -2000 | I51: =-INDEX(Premissas!$B$73:$F$73,I$4) -> -2000 | J51: =-INDEX(Premissas!$B$73:$F$73,J$4) -> -2000 | ... BJ51: =-INDEX(Premissas!$B$73:$F$73,BJ$4) -> -35000
A52: Ferramentas internas | C52: =-INDEX(Premissas!$B$74:$F$74,C$4) -> -3000 | D52: =-INDEX(Premissas!$B$74:$F$74,D$4) -> -3000 | E52: =-INDEX(Premissas!$B$74:$F$74,E$4) -> -3000 | F52: =-INDEX(Premissas!$B$74:$F$74,F$4) -> -3000 | G52: =-INDEX(Premissas!$B$74:$F$74,G$4) -> -3000 | H52: =-INDEX(Premissas!$B$74:$F$74,H$4) -> -3000 | I52: =-INDEX(Premissas!$B$74:$F$74,I$4) -> -3000 | J52: =-INDEX(Premissas!$B$74:$F$74,J$4) -> -3000 | ... BJ52: =-INDEX(Premissas!$B$74:$F$74,BJ$4) -> -35000
A53: Escritório | C53: =-INDEX(Premissas!$B$75:$F$75,C$4) -> -2000 | D53: =-INDEX(Premissas!$B$75:$F$75,D$4) -> -2000 | E53: =-INDEX(Premissas!$B$75:$F$75,E$4) -> -2000 | F53: =-INDEX(Premissas!$B$75:$F$75,F$4) -> -2000 | G53: =-INDEX(Premissas!$B$75:$F$75,G$4) -> -2000 | H53: =-INDEX(Premissas!$B$75:$F$75,H$4) -> -2000 | I53: =-INDEX(Premissas!$B$75:$F$75,I$4) -> -2000 | J53: =-INDEX(Premissas!$B$75:$F$75,J$4) -> -2000 | ... BJ53: =-INDEX(Premissas!$B$75:$F$75,BJ$4) -> -35000
A54: Contabilidade, seguros e outros | C54: =-INDEX(Premissas!$B$76:$F$76,C$4) -> -3000 | D54: =-INDEX(Premissas!$B$76:$F$76,D$4) -> -3000 | E54: =-INDEX(Premissas!$B$76:$F$76,E$4) -> -3000 | F54: =-INDEX(Premissas!$B$76:$F$76,F$4) -> -3000 | G54: =-INDEX(Premissas!$B$76:$F$76,G$4) -> -3000 | H54: =-INDEX(Premissas!$B$76:$F$76,H$4) -> -3000 | I54: =-INDEX(Premissas!$B$76:$F$76,I$4) -> -3000 | J54: =-INDEX(Premissas!$B$76:$F$76,J$4) -> -3000 | ... BJ54: =-INDEX(Premissas!$B$76:$F$76,BJ$4) -> -20000
A55: Despesas operacionais totais | C55: =SUM(C47:C54) -> -205852.7 | D55: =SUM(D47:D54) -> -205872.88 | E55: =SUM(E47:E54) -> -205892.72 | F55: =SUM(F47:F54) -> -205912.23 | G55: =SUM(G47:G54) -> -205931.41 | H55: =SUM(H47:H54) -> -205950.26 | I55: =SUM(I47:I54) -> -205968.8 | J55: =SUM(J47:J54) -> -205987.03 | ... BJ55: =SUM(BJ47:BJ54) -> -1712466.9
A56: EBITDA | C56: =C44+C55 -> -187111.27 | D56: =D44+D55 -> -175847.9 | E56: =E44+E55 -> -164736.22 | F56: =F44+F55 -> -153774.17 | G56: =G44+G55 -> -142959.68 | H56: =H44+H55 -> -132290.74 | I56: =I44+I55 -> -121765.37 | J56: =J44+J55 -> -111381.59 | ... BJ56: =BJ44+BJ55 -> 5775588.1
A57: Margem EBITDA (% da receita líquida) | C57: =IFERROR(C56/C37,0) -> -8.6251892 | D57: =IFERROR(D56/D37,0) -> -4.9396409 | E57: =IFERROR(E56/E37,0) -> -3.3399914 | F57: =IFERROR(F56/F37,0) -> -2.4461002 | G57: =IFERROR(G56/G37,0) -> -1.8753796 | H57: =IFERROR(H56/H37,0) -> -1.4794517 | I57: =IFERROR(I56/I37,0) -> -1.1887152 | J57: =IFERROR(J56/J37,0) -> -0.96619161 | ... BJ57: =IFERROR(BJ56/BJ37,0) -> 0.59719897
A58: Caixa (R$)
A59: Aportes de capital | C59: =IF(C$3=1,Premissas!$B$14,0)+IF(C$3=INDEX(Premissas!$B$53:$D$53,$B$2),INDEX(Premissas!$B$52:$D$52,$B$2),0) -> 3300000 | D59: =IF(D$3=1,Premissas!$B$14,0)+IF(D$3=INDEX(Premissas!$B$53:$D$53,$B$2),INDEX(Premissas!$B$52:$D$52,$B$2),0) -> 0 | E59: =IF(E$3=1,Premissas!$B$14,0)+IF(E$3=INDEX(Premissas!$B$53:$D$53,$B$2),INDEX(Premissas!$B$52:$D$52,$B$2),0) -> 0 | F59: =IF(F$3=1,Premissas!$B$14,0)+IF(F$3=INDEX(Premissas!$B$53:$D$53,$B$2),INDEX(Premissas!$B$52:$D$52,$B$2),0) -> 0 | G59: =IF(G$3=1,Premissas!$B$14,0)+IF(G$3=INDEX(Premissas!$B$53:$D$53,$B$2),INDEX(Premissas!$B$52:$D$52,$B$2),0) -> 0 | H59: =IF(H$3=1,Premissas!$B$14,0)+IF(H$3=INDEX(Premissas!$B$53:$D$53,$B$2),INDEX(Premissas!$B$52:$D$52,$B$2),0) -> 0 | I59: =IF(I$3=1,Premissas!$B$14,0)+IF(I$3=INDEX(Premissas!$B$53:$D$53,$B$2),INDEX(Premissas!$B$52:$D$52,$B$2),0) -> 0 | J59: =IF(J$3=1,Premissas!$B$14,0)+IF(J$3=INDEX(Premissas!$B$53:$D$53,$B$2),INDEX(Premissas!$B$52:$D$52,$B$2),0) -> 0 | ... BJ59: =IF(BJ$3=1,Premissas!$B$14,0)+IF(BJ$3=INDEX(Premissas!$B$53:$D$53,$B$2),INDEX(Premissas!$B$52:$D$52,$B$2),0) -> 0
A60: Saldo de caixa no fim do mês | C60: =C59+C56 -> 3112888.7 | D60: =C60+D59+D56 -> 2937040.8 | E60: =D60+E59+E56 -> 2772304.6 | F60: =E60+F59+F56 -> 2618530.4 | G60: =F60+G59+G56 -> 2475570.8 | H60: =G60+H59+H56 -> 2343280 | I60: =H60+I59+I56 -> 2221514.7 | J60: =I60+J59+J56 -> 2110133.1 | K60: =J60+K59+K56 -> 2008995.6 | ... BJ60: =BI60+BJ59+BJ56 -> 87583376
A61: Indicadores
A62: ARR (MRR × 12) | C62: =C32*12 -> 177939.15 | D62: =D32*12 -> 353545.48 | E62: =E32*12 -> 526849.24 | F62: =F32*12 -> 697880.31 | G62: =G32*12 -> 866668.18 | H62: =H32*12 -> 1033242 | I62: =I32*12 -> 1197630.4 | J62: =J32*12 -> 1359861.8 | ... BJ62: =BJ32*12 -> 1.1409067e+08
A63: Receita recorrente média por cliente (ARPA) | C63: =IFERROR(C32/C26,0) -> 589.235 | D63: =IFERROR(D32/D26,0) -> 590.39082 | E63: =IFERROR(E32/E26,0) -> 591.529 | F63: =IFERROR(F32/F26,0) -> 592.64977 | G63: =IFERROR(G32/G26,0) -> 593.75337 | H63: =IFERROR(H32/H26,0) -> 594.84003 | I63: =IFERROR(I32/I26,0) -> 595.90999 | J63: =IFERROR(J32/J26,0) -> 596.96348 | ... BJ63: =IFERROR(BJ32/BJ26,0) -> 922.31055
A64: Churn mensal total (% da base do mês anterior) | C64: =0 -> 0 | D64: =IFERROR(SUM(D18:D21)/C26,0) -> 0.03 | E64: =IFERROR(SUM(E18:E21)/D26,0) -> 0.029965709 | F64: =IFERROR(SUM(F18:F21)/E26,0) -> 0.029931981 | G64: =IFERROR(SUM(G18:G21)/F26,0) -> 0.02989881 | H64: =IFERROR(SUM(H18:H21)/G26,0) -> 0.029866186 | I64: =IFERROR(SUM(I18:I21)/H26,0) -> 0.029834101 | J64: =IFERROR(SUM(J18:J21)/I26,0) -> 0.029802549 | K64: =IFERROR(SUM(K18:K21)/J26,0) -> 0.02977152 | ... BJ64: =IFERROR(SUM(BJ18:BJ21)/BI26,0) -> 0.019008683
A65: Mês com EBITDA positivo daí em diante (auxiliar) | C65: =IF(MIN(C56:$BJ56)>0,C$3,999) -> 999 | D65: =IF(MIN(D56:$BJ56)>0,D$3,999) -> 999 | E65: =IF(MIN(E56:$BJ56)>0,E$3,999) -> 999 | F65: =IF(MIN(F56:$BJ56)>0,F$3,999) -> 999 | G65: =IF(MIN(G56:$BJ56)>0,G$3,999) -> 999 | H65: =IF(MIN(H56:$BJ56)>0,H$3,999) -> 999 | I65: =IF(MIN(I56:$BJ56)>0,I$3,999) -> 999 | J65: =IF(MIN(J56:$BJ56)>0,J$3,999) -> 999 | ... BJ65: =IF(MIN(BJ56:$BJ56)>0,BJ$3,999) -> 60

Sheet Fontes_e_Notas
A1: Fontes de mercado
A2: Demografia Médica no Brasil 2025 (FMUSP, AMB, Ministério da Saúde): https://www.medway.com.br/conteudos/demografia-medica-no-brasil-2025-veja-os-principais-dados-do-novo-levantamento/
A3: Vínculos sem contrato formal 30% → 48%: https://www.medway.com.br/conteudos/como-esta-o-mercado-e-a-remuneracao-na-medicina/
A4: Preços de agências de marketing em saúde: https://farmacerto.com/quanto-custa-marketing-saude-brasil/ ; https://plusbusiness.com.br/blog/quanto-custa-agencia-de-marketing-digital/
A5: Preços de geradores de conteúdo médico com IA: https://www.pulmo.com.br/ ; https://instamed.temfavo.com/ ; https://www.doutorconteudo.com.br/ ; https://medcontent-ai.vercel.app/
A6: Preços de modelos de IA (Claude Sonnet 5.5: US$ 2 / US$ 10 por milhão de tokens de entrada/saída; Haiku 5.5: US$ 0,10 / 0,50; Batch com 50% de desconto): documentação da Anthropic, outubro/2026.
A8: Notas de método
A9: 1. Clientes são calculados como valores esperados (podem ser fracionados); a exibição arredonda.
A10: 2. Fluxo de caixa = EBITDA + aportes. Não considera capital de giro, capex relevante nem IR/CSLL além do que está na carga sobre receita.
A11: 3. A troca de regime tributário usa a receita do ano anterior contra o limite do Simples.
A12: 4. CAC de mídia paga inclui mídia e ferramentas de captação; comissões de vendas estão em linha própria; parcerias e indicação não têm CAC de mídia.
A13: 5. Cenários alteram CAC, churn, parcerias/indicação, serviços adicionais, orçamento de mídia e a rodada seed. Todas as outras premissas são iguais.
A14: 6. Tudo o que está em azul é premissa e deve ser revisado após as entrevistas de validação (Kit de Validação, documento 06).
